Workbook

Sheet Dados
A1: IBGE | B1: Município | C1: Latitude | D1: Longitude | E1: Área colhida HE | F1: Quantidade produzida Ton | G1: Regiao Cafeeira | H1: CNPJ | I1: Situacao do Cadastro | J1: Grau | K1: Denominação | L1: Razao Social | M1: Codigo Sindical | N1: Central sindical | O1: Confederacao | P1: Federacao | Q1: Funcionamento da direcao | R1: Número total de dirigentes eleitos | S1: Número de votos da chapa vencedora | T1: Forma de Eleicao | U1: Numero de Chapas | V1: Total de Sindicalizados / Filiados | W1: Total de Votantes | X1: Area Geoeconômica | Y1: Grupo | Z1: Classe | AA1: Categoria | AB1: CEP | AC1: UF da sede | AD1: Localidade da sede | AE1: Bairro | AF1: Logradouro | AG1: Número | AH1: Complemento | AI1: Email | AJ1: Telefone principal | AK1: Site | AL1: Data de Início do Mandato | AM1: Data Fim do Mandato | AN1: Presidente | AO1: Abrangencia | AP1: Base Territorial
A2: =_xlfn.XLOOKUP(AD2,'Municipios MG'!$B$2:$B$853,'Municipios MG'!$A$2:$A$853) -> 3145604 | B2: =_xlfn.XLOOKUP(AD2,'Municipios MG'!$B$2:$B$853,'Municipios MG'!$B$2:$B$853) -> Oliveira | C2: =_xlfn.XLOOKUP(AD2,'Municipios MG'!$B$2:$B$853,'Municipios MG'!$C$2:$C$853) -> -20.697516 | D2: =_xlfn.XLOOKUP(AD2,'Municipios MG'!$B$2:$B$853,'Municipios MG'!$D$2:$D$853) -> -44.826411 | E2: =_xlfn.XLOOKUP(A2,Planilha3!$A$2:$A$5543,Planilha3!$C$2:$C$5543) -> 7035 | F2: =_xlfn.XLOOKUP(A2,Planilha3!$A$2:$A$5543,Planilha3!$E$2:$E$5543) -> 10764 | G2: =_xlfn.XLOOKUP(A2,'Municipios MG'!$A$2:$A$853,'Municipios MG'!$E$2:$E$853) -> Campo das Vertentes | H2: 20.919.320/0001-57 | I2: ATIVO | J2: SINDICATO | K2: STR Oliveira/MG - Sindicato dos Trabalhadores Rurais de Oliveira/MG | L2: SINDICATO DOS TRABALHADORES RURAIS DE OLIVEIRA | M2: 000.000.000.00000-0 | N2: - | O2: Confederação Nacional dos Trabalhadores Rurais Agricultores e Agricultoras Familiares | P2: FETAEMG - Federação dos Trabalhadores na Agricultura do Estado de Minas Gerais | Q2: PRESIDENCIALISMO | R2: 15 | S2: 144 | T2: DIRETA | U2: 1 | V2: 3699 | W2: 144 | X2: RURAL | Y2: TRABALHADORES | Z2: RURAL | AA2: Profissional dos Trabalhadores Rurais, do Plano da CONTAG | AB2: 35540-000 | AC2: MG | AD2: Oliveira | AE2: - | AF2: Rua Francisco Cambraia Campos | AG2: 545 | AH2: Centro | AI2: stroliveira@hotmail.com | AJ2: 3733314343 | AK2: - | AL2: 08/10/2023 | AM2: 07/10/2027 | AN2: SONIA APARECIDA NASCIMENTO STACANELLI | AO2: MUNICIPAL | AP2: Minas Gerais: Oliveira
A3: =_xlfn.XLOOKUP(AD3,'Municipios MG'!$B$2:$B$853,'Municipios MG'!$A$2:$A$853) -> 3161205 | B3: =_xlfn.XLOOKUP(AD3,'Municipios MG'!$B$2:$B$853,'Municipios MG'!$B$2:$B$853) -> São Francisco de Paula | C3: =_xlfn.XLOOKUP(AD3,'Municipios MG'!$B$2:$B$853,'Municipios MG'!$C$2:$C$853) -> -20.713532 | D3: =_xlfn.XLOOKUP(AD3,'Municipios MG'!$B$2:$B$853,'Municipios MG'!$D$2:$D$853) -> -44.982631 | E3: =_xlfn.XLOOKUP(A3,Planilha3!$A$2:$A$5543,Planilha3!$C$2:$C$5543) -> 2850 | F3: =_xlfn.XLOOKUP(A3,Planilha3!$A$2:$A$5543,Planilha3!$E$2:$E$5543) -> 4617 | G3: =_xlfn.XLOOKUP(A3,'Municipios MG'!$A$2:$A$853,'Municipios MG'!$E$2:$E$853) -> Campo das Vertentes | H3: 20.919.296/0001-56 | I3: ATIVO | J3: SINDICATO | K3: STR - STR SÃO FRANCISCO PAULA | L3: SINDICATO DOS TRABALHADORES RURAIS, ASSALARIADOS AGRICULTORE | M3: 000.000.000.00000-0 | N3: CTB - Central dos Trabalhadores e Trabalhadoras do Brasil | O3: Confederação Nacional dos Trabalhadores Rurais Agricultores e Agricultoras Familiares | P3: FETAEMG - Federação dos Trabalhadores na Agricultura do Estado de Minas Gerais | Q3: PRESIDENCIALISMO | R3: 16 | S3: 73 | T3: DIRETA | U3: 1 | V3: 1655 | W3: 74 | X3: RURAL | Y3: TRABALHADORES | Z3: RURAL | AA3: Profissional dos Trabalhadores Rurais, do Plano da CONTAG | AB3: 35543-000 | AC3: MG | AD3: São Francisco de Paula | AE3: CENTRO | AF3: RUA DA GLORIA | AG3: 79 | AH3: - | AI3: sindicatosaofrancisco2021@gmail.com | AJ3: 3733321380 | AK3: - | AL3: 08/03/2026 | AM3: 07/03/2030 | AN3: SIMONE ALVES DE ARAUJO | AO3: MUNICIPAL | AP3: Minas Gerais: São Francisco de Paula
A4: =_xlfn.XLOOKUP(AD4,'Municipios MG'!$B$2:$B$853,'Municipios MG'!$A$2:$A$853) -> 3114006 | B4: =_xlfn.XLOOKUP(AD4,'Municipios MG'!$B$2:$B$853,'Municipios MG'!$B$2:$B$853) -> Carmo da Mata | C4: =_xlfn.XLOOKUP(AD4,'Municipios MG'!$B$2:$B$853,'Municipios MG'!$C$2:$C$853) -> -20.55921 | D4: =_xlfn.XLOOKUP(AD4,'Municipios MG'!$B$2:$B$853,'Municipios MG'!$D$2:$D$853) -> -44.868383 | E4: =_xlfn.XLOOKUP(A4,Planilha3!$A$2:$A$5543,Planilha3!$C$2:$C$5543) -> 900 | F4: =_xlfn.XLOOKUP(A4,Planilha3!$A$2:$A$5543,Planilha3!$E$2:$E$5543) -> 1458 | G4: =_xlfn.XLOOKUP(A4,'Municipios MG'!$A$2:$A$853,'Municipios MG'!$E$2:$E$853) -> Campo das Vertentes | H4: 20.919.205/0001-82 | I4: ATIVO | J4: SINDICATO | K4: STR - Sindicato dos Trabalhadores Rurais de Carmo da Mata | L4: SINDICATO DOS TRABALHADORES RURAIS DE CARMO DA MATA | M4: 000.000.000.00000-0 | N4: CTB - Central dos Trabalhadores e Trabalhadoras do Brasil | O4: Confederação Nacional dos Trabalhadores Rurais Agricultores e Agricultoras Familiares | P4: FETAEMG - Federação dos Trabalhadores na Agricultura do Estado de Minas Gerais | Q4: PRESIDENCIALISMO | R4: 16 | S4: 54 | T4: DIRETA | U4: 1 | V4: 2184 | W4: 54 | X4: RURAL | Y4: TRABALHADORES | Z4: RURAL | AA4: trabalhadores e trabalhadoras rurais: os assalariados e assalariadas rurais, empregados permanentes, safristas e eventuais na agricultura, criação de animais, silvicultura, hortifruticultura e extrativismo rural; e agricultores e_x000D_ agricultoras que exerçam atividades individualmente ou em regime de economia familiar, na qualidade de pequenos produtores, proprietários, posseiros, assentados, meeiros parceiros, arrendatários, comodatários, extrativistas e os aposentados (as) rurais | AB4: 35547-000 | AC4: MG | AD4: Carmo da Mata | AE4: Centro | AF4: Rua Felisberto Corrêa Vaz | AG4: 245 | AH4: Casa | AI4: sdostrabalhadoresrurais@yahoo.com.br | AJ4: 3733831042 | AK4: - | AL4: 18/06/2026 | AM4: 17/06/2030 | AN4: MARIA HELENA DA SILVA | AO4: MUNICIPAL | AP4: Minas Gerais: Carmo da Mata
A5: =_xlfn.XLOOKUP(AD5,'Municipios MG'!$B$2:$B$853,'Municipios MG'!$A$2:$A$853) -> 3112208 | B5: =_xlfn.XLOOKUP(AD5,'Municipios MG'!$B$2:$B$853,'Municipios MG'!$B$2:$B$853) -> Capela Nova | C5: =_xlfn.XLOOKUP(AD5,'Municipios MG'!$B$2:$B$853,'Municipios MG'!$C$2:$C$853) -> -20.916668 | D5: =_xlfn.XLOOKUP(AD5,'Municipios MG'!$B$2:$B$853,'Municipios MG'!$D$2:$D$853) -> -43.612422 | E5: =_xlfn.XLOOKUP(A5,Planilha3!$A$2:$A$5543,Planilha3!$C$2:$C$5543) -> 450 | F5: =_xlfn.XLOOKUP(A5,Planilha3!$A$2:$A$5543,Planilha3!$E$2:$E$5543) -> 675 | G5: =_xlfn.XLOOKUP(A5,'Municipios MG'!$A$2:$A$853,'Municipios MG'!$E$2:$E$853) -> Campo das Vertentes | H5: 19.557.537/0001-85 | I5: ATIVO | J5: SINDICATO | K5: STR Capela Nova/MG - Sindicato dos Trabalhadores Rurais, Assalariados e Agricultores Familiares de Capela Nova e Caranaíba/MG | L5: SINDICATO DOS TRABALHADORES RURAIS ASSALARIADOS AGRICULTORES | M5: 000.000.000.00000-0 | N5: CTB - Central dos Trabalhadores e Trabalhadoras do Brasil | O5: Confederação Nacional dos Trabalhadores Rurais Agricultores e Agricultoras Familiares | P5: FETAEMG - Federação dos Trabalhadores na Agricultura do Estado de Minas Gerais | Q5: PRESIDENCIALISMO | R5: 12 | S5: 108 | T5: DECISAO_ASSEMBLEIA | U5: 1 | V5: 1800 | W5: 108 | X5: RURAL | Y5: TRABALHADORES | Z5: RURAL | AA5: São considerados Trabalhadores Rurais, os que exercem atividades como Assalariados na Agricultura, Pecuária e Similares, na Produção Rural, bem como Agricultores Familiares, Proprietários ou não, que exerçam atividade Rural, Individualmente ou em Regime de Economia Familiar, assim entendido o trabalho dos membros da família, executando em condições de mútua dependência e colaboração, ainda que com a ajuda eventual de terceiros, Trabalhadores no Reflorestamento, Hortifrutigranjeiros, Assentados e Parceleiros da Reforma Agrária, Pescadores e Garimpeiros Artensanais que Trabalham por Conta Própria e não Tenham Empregados, Trabalhadores na Área da Cana e da Avicultura, Tratorista Rural e os que Trabalham com Artesanato Rural | AB5: 36290-000 | AC5: MG | AD5: Capela Nova | AE5: - | AF5: Rua Avelina Damascena | AG5: 302 | AH5: Centro | AI5: strcapelanova@hotmail.com | AJ5: 3137271209 | AK5: - | AL5: 11/04/2023 | AM5: 10/04/2027 | AN5: ROBSON DOS REMEDIOS E SOUZA | AO5: INTERMUNICIPAL | AP5: Minas Gerais: Capela Nova, Caranaíba
A6: =_xlfn.XLOOKUP(AD6,'Municipios MG'!$B$2:$B$853,'Municipios MG'!$A$2:$A$853) -> 3152303 | B6: =_xlfn.XLOOKUP(AD6,'Municipios MG'!$B$2:$B$853,'Municipios MG'!$B$2:$B$853) -> Porto Firme | C6: =_xlfn.XLOOKUP(AD6,'Municipios MG'!$B$2:$B$853,'Municipios MG'!$C$2:$C$853) -> -20.668267 | D6: =_xlfn.XLOOKUP(AD6,'Municipios MG'!$B$2:$B$853,'Municipios MG'!$D$2:$D$853) -> -43.091411 | E6: =_xlfn.XLOOKUP(A6,Planilha3!$A$2:$A$5543,Planilha3!$C$2:$C$5543) -> 450 | F6: =_xlfn.XLOOKUP(A6,Planilha3!$A$2:$A$5543,Planilha3!$E$2:$E$5543) -> 594 | G6: =_xlfn.XLOOKUP(A6,'Municipios MG'!$A$2:$A$853,'Municipios MG'!$E$2:$E$853) -> Campo das Vertentes | H6: 19.484.351/0001-43 | I6: ATIVO | J6: SINDICATO | K6: STR - STR PORTO FIRME | L6: SINDICATO DOS TRABALHADORES RURAIS DE PORTO FIRME | M6: 000.000.000.00000-0 | N6: CTB - Central dos Trabalhadores e Trabalhadoras do Brasil | O6: Confederação Nacional dos Trabalhadores Rurais Agricultores e Agricultoras Familiares | P6: FETAEMG - Federação dos Trabalhadores na Agricultura do Estado de Minas Gerais | Q6: PRESIDENCIALISMO | R6: 12 | S6: 670 | T6: DECISAO_ASSEMBLEIA | U6: 1 | V6: 7873 | W6: 674 | X6: RURAL | Y6: TRABALHADORES | Z6: RURAL | AA6: Profissional dos Trabalhadores Rurais, do Plano da CONTAG | AB6: 36576-000 | AC6: MG | AD6: Porto Firme | AE6: CENTRO | AF6: RUA DOM SILVERIO | AG6: 352 | AH6: - | AI6: ednasindicato@hotmail.com | AJ6: 3138931350 | AK6: - | AL6: 05/12/2023 | AM6: 05/12/2027 | AN6: MARIA DO CARMO RAMOS SIQUEIRA | AO6: MUNICIPAL | AP6: Minas Gerais: Porto Firme
A7: =_xlfn.XLOOKUP(AD7,'Municipios MG'!$B$2:$B$853,'Municipios MG'!$A$2:$A$853) -> 3133501 | B7: =_xlfn.XLOOKUP(AD7,'Municipios MG'!$B$2:$B$853,'Municipios MG'!$B$2:$B$853) -> Itapecerica | C7: =_xlfn.XLOOKUP(AD7,'Municipios MG'!$B$2:$B$853,'Municipios MG'!$C$2:$C$853) -> -20.47289 | D7: =_xlfn.XLOOKUP(AD7,'Municipios MG'!$B$2:$B$853,'Municipios MG'!$D$2:$D$853) -> -45.12468 | E7: =_xlfn.XLOOKUP(A7,Planilha3!$A$2:$A$5543,Planilha3!$C$2:$C$5543) -> 395 | F7: =_xlfn.XLOOKUP(A7,Planilha3!$A$2:$A$5543,Planilha3!$E$2:$E$5543) -> 740 | G7: =_xlfn.XLOOKUP(A7,'Municipios MG'!$A$2:$A$853,'Municipios MG'!$E$2:$E$853) -> Campo das Vertentes | H7: 21.231.980/0001-03 | I7: ATIVO | J7: SINDICATO | K7: str - str camacho e itapecerica no estado de minas gerais | L7: SINDICATO DOS TRABALHADORES RURAIS DE ITAPECERICA | M7: 000.000.000.00000-0 | N7: - | O7: Confederação Nacional dos Trabalhadores Rurais Agricultores e Agricultoras Familiares | P7: FETAEMG - Federação dos Trabalhadores na Agricultura do Estado de Minas Gerais | Q7: PRESIDENCIALISMO | R7: 12 | S7: 273 | T7: DIRETA | U7: 1 | V7: 10214 | W7: 291 | X7: RURAL | Y7: TRABALHADORES | Z7: RURAL | AA7: Profissional dos Trabalhadores Rurais, do Plano da CONTAG | AB7: 35550-000 | AC7: MG | AD7: Itapecerica | AE7: CENTRO | AF7: PRAÇA SEVERO RIBEIRO | AG7: 16 | AH7: A | AI7: sindicatoitapecerica@gmail.com | AJ7: 3733411517 | AK7: - | AL7: 01/06/2023 | AM7: 31/05/2027 | AN7: ILDEU ASSIS DOS SANTOS | AO7: INTERMUNICIPAL | AP7: Minas Gerais: Camacho, Itapecerica
A8: =_xlfn.XLOOKUP(AD8,'Municipios MG'!$B$2:$B$853,'Municipios MG'!$A$2:$A$853) -> 3116605 | B8: =_xlfn.XLOOKUP(AD8,'Municipios MG'!$B$2:$B$853,'Municipios MG'!$B$2:$B$853) -> Cláudio | C8: =_xlfn.XLOOKUP(AD8,'Municipios MG'!$B$2:$B$853,'Municipios MG'!$C$2:$C$853) -> -20.444575 | D8: =_xlfn.XLOOKUP(AD8,'Municipios MG'!$B$2:$B$853,'Municipios MG'!$D$2:$D$853) -> -44.768423 | E8: =_xlfn.XLOOKUP(A8,Planilha3!$A$2:$A$5543,Planilha3!$C$2:$C$5543) -> 330 | F8: =_xlfn.XLOOKUP(A8,Planilha3!$A$2:$A$5543,Planilha3!$E$2:$E$5543) -> 594 | G8: =_xlfn.XLOOKUP(A8,'Municipios MG'!$A$2:$A$853,'Municipios MG'!$E$2:$E$853) -> Campo das Vertentes | H8: 16.748.774/0001-35 | I8: ATIVO | J8: SINDICATO | K8: STR de Cláudio-MG - Sindicato dos Trabalhadores Rurais, Assalariados e Agricultores Familiares do Município de Cláudio ", MG | L8: SINDICATO DOS TRABALHADORES RURAIS, ASSALARIADOS E AGRICULTORES FAMILIARES DO MUNICIPIO DE CLAUDIO - MG | M8: 000.000.000.00000-0 | N8: CTB - Central dos Trabalhadores e Trabalhadoras do Brasil | O8: Confederação Nacional dos Trabalhadores Rurais Agricultores e Agricultoras Familiares | P8: FETAEMG - Federação dos Trabalhadores na Agricultura do Estado de Minas Gerais | Q8: PRESIDENCIALISMO | R8: 14 | S8: 241 | T8: DIRETA | U8: 1 | V8: 897 | W8: 246 | X8: RURAL | Y8: TRABALHADORES | Z8: RURAL | AA8: Trabalhadores Rurais, os que exercem atividade como Assalariados na Agricultura, Pecuária e Similares, na Produção Rural, bem como os Agricultores Familiares, Proprietários ou não, que exerçam atividade Rural, individualmente ou em regime de Economia Familiar, assim entendido o trabalho dos membros da mesma família, executando em condições de mútua dependência e colaboração, ainda que com ajuda eventual de terceiros, Trabalhadores no Reflorestameto, Hortifrutigranjeiros, Assentados e Parceleiros da Reforma Agrária, Pescadores e Garimpeiros Artesanais que trabalham por conta própria e não tenham empregados, trabalhadores na área da cana e da Avicultura, Tratorista Rural e os que trabalham com Artesanato Rural. | AB8: 35530-000 | AC8: MG | AD8: Cláudio | AE8: Centro | AF8: Rua Goiás | AG8: 109 | AH8: casa | AI8: sindicatoclaudio@hotmail.com | AJ8: 3733811513 | AK8: - | AL8: 08/04/2024 | AM8: 07/04/2028 | AN8: MAURILO MARCELINO TOMAZ | AO8: MUNICIPAL | AP8: Minas Gerais: Cláudio
A9: =_xlfn.XLOOKUP(AD9,'Municipios MG'!$B$2:$B$853,'Municipios MG'!$A$2:$A$853) -> 3153103 | B9: =_xlfn.XLOOKUP(AD9,'Municipios MG'!$B$2:$B$853,'Municipios MG'!$B$2:$B$853) -> Presidente Bernardes | C9: =_xlfn.XLOOKUP(AD9,'Municipios MG'!$B$2:$B$853,'Municipios MG'!$C$2:$C$853) -> -20.765678 | D9: =_xlfn.XLOOKUP(AD9,'Municipios MG'!$B$2:$B$853,'Municipios MG'!$D$2:$D$853) -> -43.190056 | E9: =_xlfn.XLOOKUP(A9,Planilha3!$A$2:$A$5543,Planilha3!$C$2:$C$5543) -> 300 | F9: =_xlfn.XLOOKUP(A9,Planilha3!$A$2:$A$5543,Planilha3!$E$2:$E$5543) -> 360 | G9: =_xlfn.XLOOKUP(A9,'Municipios MG'!$A$2:$A$853,'Municipios MG'!$E$2:$E$853) -> Campo das Vertentes | H9: 16.760.449/0001-98 | I9: ATIVO | J9: SINDICATO | K9: STR Presidente Bernardes/MG - Sindicato dos Trabalhadores Rurais de Presidente Bernardes/MG | L9: SINDICATO DOS TRABALHADORES RURAIS DE PRES BERNARDES | M9: 000.000.000.00000-0 | N9: - | O9: Confederação Nacional dos Trabalhadores Rurais Agricultores e Agricultoras Familiares | P9: FETAEMG - Federação dos Trabalhadores na Agricultura do Estado de Minas Gerais | Q9: PRESIDENCIALISMO | R9: 11 | S9: 648 | T9: DECISAO_ASSEMBLEIA | U9: 1 | V9: 1580 | W9: 659 | X9: RURAL | Y9: TRABALHADORES | Z9: RURAL | AA9: Categoria Profissional dos Trabalhadores Rurais do Plano da CONTAG | AB9: 36475-000 | AC9: MG | AD9: Presidente Bernardes | AE9: - | AF9: Rua São José | AG9: 41 | AH9: Centro | AI9: sindicatobernardes@hotmail.com | AJ9: 3235381105 | AK9: - | AL9: 27/01/2024 | AM9: 26/01/2028 | AN9: CARLOS EVANGELINO DE SOUZA | AO9: MUNICIPAL | AP9: Minas Gerais: Presidente Bernardes
A10: =_xlfn.XLOOKUP(AD10,'Municipios MG'!$B$2:$B$853,'Municipios MG'!$A$2:$A$853) -> 3115201 | B10: =_xlfn.XLOOKUP(AD10,'Municipios MG'!$B$2:$B$853,'Municipios MG'!$B$2:$B$853) -> Conceição da Barra de Minas | C10: =_xlfn.XLOOKUP(AD10,'Municipios MG'!$B$2:$B$853,'Municipios MG'!$C$2:$C$853) -> -21.131769 | D10: =_xlfn.XLOOKUP(AD10,'Municipios MG'!$B$2:$B$853,'Municipios MG'!$D$2:$D$853) -> -44.477808 | E10: =_xlfn.XLOOKUP(A10,Planilha3!$A$2:$A$5543,Planilha3!$C$2:$C$5543) -> 275 | F10: =_xlfn.XLOOKUP(A10,Planilha3!$A$2:$A$5543,Planilha3!$E$2:$E$5543) -> 462 | G10: =_xlfn.XLOOKUP(A10,'Municipios MG'!$A$2:$A$853,'Municipios MG'!$E$2:$E$853) -> Campo das Vertentes | H10: 07.681.707/0001-50 | I10: ATIVO | J10: SINDICATO | K10: Sindicato dos Trabalhadores Rurais, Assalariados e Agricultores Familiares do Município de Conceição da Barra de Minas /MG | L10: SINDICATO DOS TRABALHADORES RURAIS, ASSALARIADOS E AGRICULTORES FAMILIARES DO MUNICIPIO DE CONCEICAO DA BARRA DE MINAS/MG | M10: 000.000.000.00000-0 | N10: - | O10: - | P10: - | Q10: PRESIDENCIALISMO | R10: 15 | S10: 47 | T10: DIRETA | U10: 1 | V10: 47 | W10: 47 | X10: RURAL | Y10: TRABALHADORES | Z10: RURAL | AA10: Profissional dos Trabalhadores e Trabalhadoras Rurais ativos e inativos: assalariados e assalariadas rurais, empregados permanentes, safristas e eventuais na agricultura, criação de animais, hortifruticultura; e agricultores e agricultoras que exerçam atividades individualmente ou em regime de economia familiar, na qualidade de pequenos produtores, proprietários até dois módulos rurais, posseiros, assentados, meeiros, parceiros, arrendatários, comodatários e os aposentados(as) rurais. | AB10: 36360-000 | AC10: MG | AD10: Conceição da Barra de Minas | AE10: CENTRO | AF10: RUA PREFEITO ANTONIO SILVA | AG10: 66 | AH10: A | AI10: sindruralcbm@yahoo.com.br | AJ10: 32984873328 | AK10: - | AL10: 06/07/2022 | AM10: 05/07/2026 | AN10: RENATO MAURO DA SILVA | AO10: MUNICIPAL | AP10: Minas Gerais: Conceição da Barra de Minas
A11: =_xlfn.XLOOKUP(AD11,'Municipios MG'!$B$2:$B$853,'Municipios MG'!$A$2:$A$853) -> 3150802 | B11: =_xlfn.XLOOKUP(AD11,'Municipios MG'!$B$2:$B$853,'Municipios MG'!$B$2:$B$853) -> Piranga | C11: =_xlfn.XLOOKUP(AD11,'Municipios MG'!$B$2:$B$853,'Municipios MG'!$C$2:$C$853) -> -20.685144 | D11: =_xlfn.XLOOKUP(AD11,'Municipios MG'!$B$2:$B$853,'Municipios MG'!$D$2:$D$853) -> -43.287346 | E11: =_xlfn.XLOOKUP(A11,Planilha3!$A$2:$A$5543,Planilha3!$C$2:$C$5543) -> 200 | F11: =_xlfn.XLOOKUP(A11,Planilha3!$A$2:$A$5543,Planilha3!$E$2:$E$5543) -> 360 | G11: =_xlfn.XLOOKUP(A11,'Municipios MG'!$A$2:$A$853,'Municipios MG'!$E$2:$E$853) -> Campo das Vertentes | H11: 20.131.991/0001-59 | I11: ATIVO | J11: SINDICATO | K11: STRAAF PIRANGA-MG - Sindicato dos Trabalhadores Rurais, Assalariados e Agricultores Familiares do Município de Piranga", MG | L11: SINDICATO DOS TRABALHADORES RURAIS,ASSALARIADOS E AGRICULTORES FAMILIARES DE PIRANGA | M11: 000.000.000.00000-0 | N11: CTB - Central dos Trabalhadores e Trabalhadoras do Brasil | O11: Confederação Nacional dos Trabalhadores Rurais Agricultores e Agricultoras Familiares | P11: FETAEMG - Federação dos Trabalhadores na Agricultura do Estado de Minas Gerais | Q11: PRESIDENCIALISMO | R11: 12 | S11: 1374 | T11: DIRETA | U11: 1 | V11: 10493 | W11: 1379 | X11: RURAL | Y11: TRABALHADORES | Z11: RURAL | AA11: São considerados Trabalhadores Rurais, os que exercem atividade como Assalariados na Agricultura, Pecuária e Similares, na Produção Rural, bem como os Agricultores Familiares, Proprietários ou não, que exerçam atividade Rural, individualmente ou em regime economia familiar, assim entendido o trabalho dos membros da família, executando em condições de mútua dependência e colaboração, ainda com ajuda eventual de terceiros, Trabalhadores no Reflorestamento, Hortifrutigranjeiros, assentados e parceleiros da Reforma Agrária, Pescadores e Garimpeiros Artesanais que trabalham por conta própria e não tenham Empregados, Trabalhadores na Área da Cana e da Avicultura, Tratorista Rural e os que Trabalham com Artesanato Rural. | AB11: 36480-000 | AC11: MG | AD11: Piranga | AE11: CENTRO | AF11: RUA JOSÉ EUCLIDES | AG11: 21 | AH11: - | AI11: sindicatopirangamg@gmail.com | AJ11: 3137461391 | AK11: - | AL11: 14/12/2023 | AM11: 13/12/2027 | AN11: FRANCISCO LOURIVAL RIBEIRO | AO11: MUNICIPAL | AP11: Minas Gerais: Piranga
A12: =_xlfn.XLOOKUP(AD12,'Municipios MG'!$B$2:$B$853,'Municipios MG'!$A$2:$A$853) -> 3128204 | B12: =_xlfn.XLOOKUP(AD12,'Municipios MG'!$B$2:$B$853,'Municipios MG'!$B$2:$B$853) -> Guaraciaba | C12: =_xlfn.XLOOKUP(AD12,'Municipios MG'!$B$2:$B$853,'Municipios MG'!$C$2:$C$853) -> -20.571704 | D12: =_xlfn.XLOOKUP(AD12,'Municipios MG'!$B$2:$B$853,'Municipios MG'!$D$2:$D$853) -> -43.011282 | E12: =_xlfn.XLOOKUP(A12,Planilha3!$A$2:$A$5543,Planilha3!$C$2:$C$5543) -> 130 | F12: =_xlfn.XLOOKUP(A12,Planilha3!$A$2:$A$5543,Planilha3!$E$2:$E$5543) -> 234 | G12: =_xlfn.XLOOKUP(A12,'Municipios MG'!$A$2:$A$853,'Municipios MG'!$E$2:$E$853) -> Campo das Vertentes | H12: 04.064.224/0001-18 | I12: ATIVO | J12: SINDICATO | K12: Sindicato dos Trabalhadores Rurais de Guaraciaba/MG | L12: SINDICATO DOS TRABALHADORES RURAIS DE GUARACIABA/MG | M12: 000.000.000.00000-0 | N12: - | O12: - | P12: - | Q12: PRESIDENCIALISMO | R12: 16 | S12: 505 | T12: DIRETA | U12: 1 | V12: 4123 | W12: 528 | X12: RURAL | Y12: TRABALHADORES | Z12: RURAL | AA12: Profissional dos Trabalhadores e_x000D_ Trabalhadoras Rurais ativos e inativos: assalariados e assalariadas rurais, empregados_x000D_ permanentes, safristas e eventuais na agricultura, criação de animais, hortifruticultura;_x000D_ e agricultores e agricultoras que exerçam atividades individualmente ou em regime de_x000D_ economia familiar, na qualidade de pequenos produtores, proprietários até dois_x000D_ módulos rurais, posseiros, assentados, meeiros, parceiros, arrendatários, comodatários_x000D_ e os aposentados(as) rurais. | AB12: 35436-000 | AC12: MG | AD12: GUARACIABA | AE12: CENTRO | AF12: RUA PADRE MANOEL | AG12: 56 | AH12: - | AI12: sindicato.guara@hotmail.com | AJ12: 3138935337 | AK12: - | AL12: 16/08/2023 | AM12: 15/08/2027 | AN12: DORVALINA TEIXEIRA DA CUNHA DA SILVA | AO12: MUNICIPAL | AP12: Minas Gerais: Guaraciaba
A13: =_xlfn.XLOOKUP(AD13,'Municipios MG'!$B$2:$B$853,'Municipios MG'!$A$2:$A$853) -> 3147709 | B13: =_xlfn.XLOOKUP(AD13,'Municipios MG'!$B$2:$B$853,'Municipios MG'!$B$2:$B$853) -> Passa Tempo | C13: =_xlfn.XLOOKUP(AD13,'Municipios MG'!$B$2:$B$853,'Municipios MG'!$C$2:$C$853) -> -20.652388 | D13: =_xlfn.XLOOKUP(AD13,'Municipios MG'!$B$2:$B$853,'Municipios MG'!$D$2:$D$853) -> -44.493417 | E13: =_xlfn.XLOOKUP(A13,Planilha3!$A$2:$A$5543,Planilha3!$C$2:$C$5543) -> 120 | F13: =_xlfn.XLOOKUP(A13,Planilha3!$A$2:$A$5543,Planilha3!$E$2:$E$5543) -> 194 | G13: =_xlfn.XLOOKUP(A13,'Municipios MG'!$A$2:$A$853,'Municipios MG'!$E$2:$E$853) -> Campo das Vertentes | H13: 20.660.858/0001-90 | I13: ATIVO | J13: SINDICATO | K13: STR Passa Tempo/MG - Sindicato dos Trabalhadores Rurais de Passa Tempo/MG | L13: SINDICATO DOS TRABALHADORES RURAIS DE PASSA TEMPO | M13: 000.000.000.00000-0 | N13: - | O13: Confederação Nacional dos Trabalhadores Rurais Agricultores e Agricultoras Familiares | P13: FETAEMG - Federação dos Trabalhadores na Agricultura do Estado de Minas Gerais | Q13: PRESIDENCIALISMO | R13: 16 | S13: 68 | T13: DECISAO_ASSEMBLEIA | U13: 1 | V13: 561 | W13: 68 | X13: RURAL | Y13: TRABALHADORES | Z13: RURAL | AA13: Categoria Profissional dos Trabalhadores Rurais do Plano da CONTAG | AB13: 35537-000 | AC13: MG | AD13: Passa Tempo | AE13: - | AF13: Rua Cícero Ferreira de Resende | AG13: 07 | AH13: Centro | AI13: - | AJ13: 3733351199 | AK13: - | AL13: 05/07/2022 | AM13: 05/07/2026 | AN13: NEIDE ANTONIA DE SOUZA | AO13: MUNICIPAL | AP13: Minas Gerais: Passa Tempo
... A232: =_xlfn.XLOOKUP(AD232,'Municipios MG'!$B$2:$B$853,'Municipios MG'!$A$2:$A$853) -> 3110608 | B232: =_xlfn.XLOOKUP(AD232,'Municipios MG'!$B$2:$B$853,'Municipios MG'!$B$2:$B$853) -> Cambuí | C232: =_xlfn.XLOOKUP(AD232,'Municipios MG'!$B$2:$B$853,'Municipios MG'!$C$2:$C$853) -> -22.611097 | D232: =_xlfn.XLOOKUP(AD232,'Municipios MG'!$B$2:$B$853,'Municipios MG'!$D$2:$D$853) -> -46.058019 | E232: =_xlfn.XLOOKUP(A232,Planilha3!$A$2:$A$5543,Planilha3!$C$2:$C$5543) -> 4 | F232: =_xlfn.XLOOKUP(A232,Planilha3!$A$2:$A$5543,Planilha3!$E$2:$E$5543) -> 5 | G232: =_xlfn.XLOOKUP(A232,'Municipios MG'!$A$2:$A$853,'Municipios MG'!$E$2:$E$853) -> Sul de Minas | H232: 20.382.099/0001-40 | I232: ATIVO | J232: SINDICATO | K232: SINDICATO DOS TRABALHADORES RURAIS DE CAMBUI/MG - SINDICATO DOS TRABALHADORES RURAIS DE CAMBUI/MG | L232: SINDICATO DOS TRABALHADORES RURAIS, ASSAL E AGRIC FAMILIARES DE CAMBUI, CORREGO B JESUS E SENADOR AMARAL | M232: 000.000.000.00000-0 | N232: - | O232: - | P232: - | Q232: PRESIDENCIALISMO | R232: 12 | S232: 28 | T232: DIRETA | U232: 1 | V232: 5118 | W232: 28 | X232: RURAL | Y232: TRABALHADORES | Z232: RURAL | AA232: Profissional dos Trabalhadores Rurais, do Plano da CONTAG | AB232: 37600-000 | AC232: MG | AD232: CAMBUÍ | AE232: VL JD SAO BENEDITO | AF232: RUA VEREADOR BENEDITO ARTUR DE MELO | AG232: 145 | AH232: A | AI232: strcambui@micropic.com.br | AJ232: 3534311558 | AK232: - | AL232: 07/03/2023 | AM232: 06/03/2027 | AN232: DIONESIO ANTONIO DA SILVA | AO232: MUNICIPAL | AP232: Minas Gerais: Cambuí
A233: =_xlfn.XLOOKUP(AD233,'Municipios MG'!$B$2:$B$853,'Municipios MG'!$A$2:$A$853) -> 3106200 | B233: =_xlfn.XLOOKUP(AD233,'Municipios MG'!$B$2:$B$853,'Municipios MG'!$B$2:$B$853) -> Belo Horizonte | C233: =_xlfn.XLOOKUP(AD233,'Municipios MG'!$B$2:$B$853,'Municipios MG'!$C$2:$C$853) -> -19.937524 | D233: =_xlfn.XLOOKUP(AD233,'Municipios MG'!$B$2:$B$853,'Municipios MG'!$D$2:$D$853) -> -43.926453 | E233: =_xlfn.XLOOKUP(A233,Planilha3!$A$2:$A$5543,Planilha3!$C$2:$C$5543) -> ... | F233: =_xlfn.XLOOKUP(A233,Planilha3!$A$2:$A$5543,Planilha3!$E$2:$E$5543) -> ... | H233: 17.388.158/0001-83 | I233: ATIVO | J233: FEDERACAO | K233: FETAEMG - Federação dos Trabalhadores na Agricultura do Estado de Minas Gerais | L233: FEDERACAO DOS TRABALHADORES NA AGRIC DO ESTADO M GERAIS | M233: 000.000.000.00000-0 | N233: CTB - Central dos Trabalhadores e Trabalhadoras do Brasil | O233: Confederação Nacional dos Trabalhadores Rurais Agricultores e Agricultoras Familiares | P233: - | Q233: PRESIDENCIALISMO | R233: 47 | S233: 446 | T233: DECISAO_ASSEMBLEIA | U233: 1 | V233: 535 | W233: 457 | X233: RURAL | Y233: TRABALHADORES | Z233: RURAL | AA233: Coordenação, Representação e Integração dos Trabalhadores (as) e empregados (as) rurais e agricultores familiares, ativos (as) e aposentados (as), são considerados trabalhadores e trabalhadoras rurais: os assalariados (as) rurais, empregados permanentes, safristas e eventuais na agricultura, criação de animais, silvicultura, hortifruticultura e extrativismo rural e agricultores (as) que exerçam atividades individualmente ou em regime de economia familiar, na qualidade de pequenos produtores, proprietários, posseiros, assentados, meeiros, parceiros, arrendatários, comodatários e extrativistas, tendo como representação o somatório das Categorias e Bases Territoriais dos Sindicatos a ela Filiados. | AB233: 30150-250 | AC233: MG | AD233: Belo Horizonte | AE233: Santa Efigênia | AF233: Rua Álvares Maciel | AG233: 154 | AH233: Santa Efigênia | AI233: fetaemg@fetaemg.org.br | AJ233: 3130730000 | AK233: www.fetaemg.org.br | AL233: 14/06/2023 | AM233: 13/06/2027 | AN233: VILSON LUIZ DA SILVA | AO233: ESTADUAL | AP233: Minas Gerais
A234: =_xlfn.XLOOKUP(AD234,'Municipios MG'!$B$2:$B$853,'Municipios MG'!$A$2:$A$853) -> 3108701 | B234: =_xlfn.XLOOKUP(AD234,'Municipios MG'!$B$2:$B$853,'Municipios MG'!$B$2:$B$853) -> Brás Pires | C234: =_xlfn.XLOOKUP(AD234,'Municipios MG'!$B$2:$B$853,'Municipios MG'!$C$2:$C$853) -> -20.848456 | D234: =_xlfn.XLOOKUP(AD234,'Municipios MG'!$B$2:$B$853,'Municipios MG'!$D$2:$D$853) -> -43.239123 | E234: =_xlfn.XLOOKUP(A234,Planilha3!$A$2:$A$5543,Planilha3!$C$2:$C$5543) -> ... | F234: =_xlfn.XLOOKUP(A234,Planilha3!$A$2:$A$5543,Planilha3!$E$2:$E$5543) -> ... | H234: 18.129.353/0001-51 | I234: ATIVO | J234: SINDICATO | K234: STR BRAS PIRES - SINDICATO DOS TRABALHADORES RURAIS DE BRAS PIRES/MG | L234: SINDICATO DOS TRABALHADORES RURAIS DE BRAS PIRES | M234: 000.000.000.00000-0 | N234: - | O234: - | P234: - | Q234: PRESIDENCIALISMO | R234: 12 | S234: 381 | T234: DECISAO_ASSEMBLEIA | U234: 1 | V234: 2782 | W234: 396 | X234: RURAL | Y234: TRABALHADORES | Z234: RURAL | AA234: Profissional dos Trabalhadores Rurais, do Plano da CONTAG | AB234: 36542-000 | AC234: MG | AD234: Brás Pires | AE234: CENTRO | AF234: RUA JOAO DA CRUZ NUNES | AG234: 160 | AH234: CASA | AI234: strbraspires@yahoo.com.br | AJ234: 3235341173 | AK234: - | AL234: 06/01/2021 | AM234: 05/01/2025 | AN234: GERALDO CAMILO ARAUJO | AO234: MUNICIPAL | AP234: Minas Gerais: Brás Pires
A235: =_xlfn.XLOOKUP(AD235,'Municipios MG'!$B$2:$B$853,'Municipios MG'!$A$2:$A$853) -> 3115474 | B235: =_xlfn.XLOOKUP(AD235,'Municipios MG'!$B$2:$B$853,'Municipios MG'!$B$2:$B$853) -> Catuti | C235: =_xlfn.XLOOKUP(AD235,'Municipios MG'!$B$2:$B$853,'Municipios MG'!$C$2:$C$853) -> -15.357379 | D235: =_xlfn.XLOOKUP(AD235,'Municipios MG'!$B$2:$B$853,'Municipios MG'!$D$2:$D$853) -> -42.963523 | E235: =_xlfn.XLOOKUP(A235,Planilha3!$A$2:$A$5543,Planilha3!$C$2:$C$5543) -> ... | F235: =_xlfn.XLOOKUP(A235,Planilha3!$A$2:$A$5543,Planilha3!$E$2:$E$5543) -> ... | H235: 26.354.614/0001-65 | I235: ATIVO | J235: SINDICATO | K235: Sindicato dos Trabalhadores e Trabalhadoras Rurais do Município de Catuti/MG | L235: SINDICATO DOS TRABALHADORES E TRABALHADORAS RURAIS DO MUNICI | M235: 000.000.000.00000-0 | N235: - | O235: - | P235: - | Q235: PRESIDENCIALISMO | R235: 11 | S235: 74 | T235: DECISAO_ASSEMBLEIA | U235: 1 | V235: 143 | W235: 74 | X235: RURAL | Y235: TRABALHADORES | Z235: RURAL | AA235: Profissional dos Trabalhadores e Trabalhadoras Rurais, assalariados e assalariadas rurais, empregados permanentes, safristas_x000D_ e eventuais na agricultura, criação de animais e hortifruticultura; e agricultores e_x000D_ agricultoras que exerçam atividades individualmente ou em regime de economia familiar,_x000D_ na qualidade de pequenos produtores, proprietários até dois módulos rurais, posseiros,_x000D_ assentados, meeiros, parceiros, arrendatários, comodatários e os aposentados (as) rurais. | AB235: 39526-000 | AC235: MG | AD235: Catuti | AE235: CENTRO | AF235: PRAÇA PRESIDENTE VARGAS | AG235: 60 | AH235: CASA | AI235: sindicatocatuti@yahoo.com | AJ235: 38999328207 | AK235: - | AL235: 01/07/2022 | AM235: 30/06/2026 | AN235: JOAO ELTON SILVEIRA | AO235: MUNICIPAL | AP235: Minas Gerais: Catuti
A236: =_xlfn.XLOOKUP(AD236,'Municipios MG'!$B$2:$B$853,'Municipios MG'!$A$2:$A$853) -> 3123106 | B236: =_xlfn.XLOOKUP(AD236,'Municipios MG'!$B$2:$B$853,'Municipios MG'!$B$2:$B$853) -> Dores de Guanhães | C236: =_xlfn.XLOOKUP(AD236,'Municipios MG'!$B$2:$B$853,'Municipios MG'!$C$2:$C$853) -> -19.054262 | D236: =_xlfn.XLOOKUP(AD236,'Municipios MG'!$B$2:$B$853,'Municipios MG'!$D$2:$D$853) -> -42.926722 | E236: =_xlfn.XLOOKUP(A236,Planilha3!$A$2:$A$5543,Planilha3!$C$2:$C$5543) -> ... | F236: =_xlfn.XLOOKUP(A236,Planilha3!$A$2:$A$5543,Planilha3!$E$2:$E$5543) -> ... | H236: 19.210.996/0001-98 | I236: ATIVO | J236: SINDICATO | K236: STR - STRDORESGUANHAES | L236: SINDICATO DOS TRABALHADORES RURAIS DE DORES DE GUANHAES/MG | M236: 000.000.000.00000-0 | N236: CTB - Central dos Trabalhadores e Trabalhadoras do Brasil | O236: Confederação Nacional dos Trabalhadores Rurais Agricultores e Agricultoras Familiares | P236: FETAEMG - Federação dos Trabalhadores na Agricultura do Estado de Minas Gerais | Q236: PRESIDENCIALISMO | R236: 15 | S236: 94 | T236: DIRETA | U236: 1 | V236: 500 | W236: 94 | X236: RURAL | Y236: TRABALHADORES | Z236: RURAL | AA236: Profissional, dos Trabalhadores Rurais do plano da CONTAG | AB236: 35894-000 | AC236: MG | AD236: Dores de Guanhães | AE236: Centro | AF236: Travessa Bias Fortes | AG236: 122 | AH236: - | AI236: sindicatodoresdeguanhaes@yahoo.com.br | AJ236: 3334261395 | AK236: - | AL236: 09/04/2022 | AM236: 08/04/2026 | AN236: GERALDO JULIO DAMIAO | AO236: MUNICIPAL | AP236: Minas Gerais: Dores de Guanhães
A237: =_xlfn.XLOOKUP(AD237,'Municipios MG'!$B$2:$B$853,'Municipios MG'!$A$2:$A$853) -> 3129657 | B237: =_xlfn.XLOOKUP(AD237,'Municipios MG'!$B$2:$B$853,'Municipios MG'!$B$2:$B$853) -> Ibiracatu | C237: =_xlfn.XLOOKUP(AD237,'Municipios MG'!$B$2:$B$853,'Municipios MG'!$C$2:$C$853) -> -15.665467 | D237: =_xlfn.XLOOKUP(AD237,'Municipios MG'!$B$2:$B$853,'Municipios MG'!$D$2:$D$853) -> -44.167709 | E237: =_xlfn.XLOOKUP(A237,Planilha3!$A$2:$A$5543,Planilha3!$C$2:$C$5543) -> ... | F237: =_xlfn.XLOOKUP(A237,Planilha3!$A$2:$A$5543,Planilha3!$E$2:$E$5543) -> ... | H237: 07.371.820/0001-39 | I237: ATIVO | J237: SINDICATO | K237: SINDICATO DOS TRABALHADORES RURAIS DE IBIRACATU-MG | L237: SINDICATO DOS TRABALHADORES RURAIS DE IBIRACATU | M237: 000.000.000.00000-0 | N237: - | O237: - | P237: - | Q237: PRESIDENCIALISMO | R237: 12 | S237: 115 | T237: DIRETA | U237: 1 | V237: 115 | W237: 115 | X237: RURAL | Y237: TRABALHADORES | Z237: RURAL | AA237: Profissional dos Trabalhadores e Trabalhadoras rurais: assalariados e assalariadas rurais, empregados permanentes, safristas e eventuais na agricultura, criação de animais e hortifruticultura; e agricultores e agricultoras que exerçam atividades individualmente ou em regime de economia familiar, na qualidade de pequenos produtores, proprietários até dois módulos rurais, posseiros, assentados, meeiros, parceiros, arrendatários, comodatários e os aposenados(as) rurais. | AB237: 39455-000 | AC237: MG | AD237: Ibiracatu | AE237: CENTRO | AF237: RUA JOAO CARDOSO GOUDINHO | AG237: 104 | AH237: A | AI237: strdeibiracatu@yahoo.com.br | AJ237: 3836257167 | AK237: - | AL237: 25/07/2023 | AM237: 24/07/2027 | AN237: MARIA APARECIDA TEIXEIRA DOS SANTOS | AO237: MUNICIPAL | AP237: Minas Gerais: Ibiracatu
A238: =_xlfn.XLOOKUP(AD238,'Municipios MG'!$B$2:$B$853,'Municipios MG'!$A$2:$A$853) -> 3136959 | B238: =_xlfn.XLOOKUP(AD238,'Municipios MG'!$B$2:$B$853,'Municipios MG'!$B$2:$B$853) -> Juvenília | C238: =_xlfn.XLOOKUP(AD238,'Municipios MG'!$B$2:$B$853,'Municipios MG'!$C$2:$C$853) -> -14.263595 | D238: =_xlfn.XLOOKUP(AD238,'Municipios MG'!$B$2:$B$853,'Municipios MG'!$D$2:$D$853) -> -44.15959 | E238: =_xlfn.XLOOKUP(A238,Planilha3!$A$2:$A$5543,Planilha3!$C$2:$C$5543) -> ... | F238: =_xlfn.XLOOKUP(A238,Planilha3!$A$2:$A$5543,Planilha3!$E$2:$E$5543) -> ... | H238: 04.157.776/0001-70 | I238: ATIVO | J238: SINDICATO | K238: SINDICATO DOS TRABALHADORES RURAIS DE JUVENILIA - SINDICATO DOS TRABALHADORES RURAIS DE JUVENILIA | L238: SINDICATO DOS TRABALHADORES RURAIS DE JUVENILIA | M238: 000.000.000.00000-0 | N238: - | O238: - | P238: - | Q238: PRESIDENCIALISMO | R238: 8 | S238: 104 | T238: DIRETA | U238: 1 | V238: 2339 | W238: 109 | X238: RURAL | Y238: TRABALHADORES | Z238: RURAL | AA238: TRABALHADORES RURAIS | AB238: 39467-000 | AC238: MG | AD238: JUVENÍLIA | AE238: CENTRO | AF238: RUA BERNARDO DA FONSECA PINTO | AG238: 378 | AH238: A | AI238: strjuvenilia.mg@hotmail.com | AJ238: 3836149230 | AK238: - | AL238: 03/03/2021 | AM238: 03/03/2025 | AN238: SEBASTIAO ANTONIO DE SOUZA | AO238: MUNICIPAL | AP238: Minas Gerais: Juvenília
A239: =_xlfn.XLOOKUP(AD239,'Municipios MG'!$B$2:$B$853,'Municipios MG'!$A$2:$A$853) -> 3138658 | B239: =_xlfn.XLOOKUP(AD239,'Municipios MG'!$B$2:$B$853,'Municipios MG'!$B$2:$B$853) -> Lontra | C239: =_xlfn.XLOOKUP(AD239,'Municipios MG'!$B$2:$B$853,'Municipios MG'!$C$2:$C$853) -> -15.902058 | D239: =_xlfn.XLOOKUP(AD239,'Municipios MG'!$B$2:$B$853,'Municipios MG'!$D$2:$D$853) -> -44.306115 | E239: =_xlfn.XLOOKUP(A239,Planilha3!$A$2:$A$5543,Planilha3!$C$2:$C$5543) -> ... | F239: =_xlfn.XLOOKUP(A239,Planilha3!$A$2:$A$5543,Planilha3!$E$2:$E$5543) -> ... | H239: 11.230.237/0001-85 | I239: ATIVO | J239: SINDICATO | K239: Sindicato dos Trabalhadores e Trabalhadoras Rurais de Lontra - MG | L239: SINDICATO DOS TRABALHADORES E TRABALHADORAS RURAIS DE LONTRA | M239: 000.000.000.00000-0 | N239: - | O239: - | P239: - | Q239: PRESIDENCIALISMO | R239: 12 | S239: 237 | T239: DECISAO_ASSEMBLEIA | U239: 1 | V239: 1021 | W239: 238 | X239: RURAL | Y239: TRABALHADORES | Z239: RURAL | AA239: Trabalhadores e trabalhadoras rurais: Assalariados e assalariadas rurais, empregados permanentes, safristas e eventuais na agricultura, criação de animais, silvicultura, hortifruticultura e extrativismo rural; e agricultores e_x000D_ agricultoras que exerçam atividades individualmente ou em regime de economia familiar, na qualidade de pequenos produtores, proprietários, posseiros, assentados, meeiros, parceiros, arrendatários, comodatários, extrativistas e os aposentados rurais, nos termos do Decreto 1166/71. | AB239: 39437-000 | AC239: MG | AD239: Lontra | AE239: - | AF239: Av. Belo Horizonte | AG239: 493 | AH239: Centro | AI239: moradamy@hotmail.com | AJ239: 3832348222 | AK239: - | AL239: 05/02/2022 | AM239: 05/02/2026 | AN239: SILVANO ANTONIO DE FREITAS | AO239: MUNICIPAL | AP239: Minas Gerais: Lontra
A240: =_xlfn.XLOOKUP(AD240,'Municipios MG'!$B$2:$B$853,'Municipios MG'!$A$2:$A$853) -> 3145208 | B240: =_xlfn.XLOOKUP(AD240,'Municipios MG'!$B$2:$B$853,'Municipios MG'!$B$2:$B$853) -> Nova Serrana | C240: =_xlfn.XLOOKUP(AD240,'Municipios MG'!$B$2:$B$853,'Municipios MG'!$C$2:$C$853) -> -19.875867 | D240: =_xlfn.XLOOKUP(AD240,'Municipios MG'!$B$2:$B$853,'Municipios MG'!$D$2:$D$853) -> -44.985579 | E240: =_xlfn.XLOOKUP(A240,Planilha3!$A$2:$A$5543,Planilha3!$C$2:$C$5543) -> ... | F240: =_xlfn.XLOOKUP(A240,Planilha3!$A$2:$A$5543,Planilha3!$E$2:$E$5543) -> ... | H240: 18.707.703/0001-10 | I240: INATIVO | J240: SINDICATO | K240: Sindicato dos Trabalhadores Rurais de Nova Serrana | L240: SINDICATO DOS TRABALHADORES RURAIS DE NOVA SERRANA | M240: 000.000.000.00000-0 | N240: FS - Força Sindical | O240: Confederação Nacional dos Trabalhadores Rurais Agricultores e Agricultoras Familiares | P240: FETAEMG - Federação dos Trabalhadores na Agricultura do Estado de Minas Gerais | Q240: PRESIDENCIALISMO | R240: 13 | S240: 45 | T240: DIRETA | U240: 1 | V240: 85 | W240: 47 | X240: RURAL | Y240: TRABALHADORES | Z240: RURAL | AA240: Profissional dos Trabalhadores Rurais, do Plano da CONTAG; | AB240: 35519-000 | AC240: MG | AD240: Nova Serrana | AE240: Frei Paulo | AF240: Rua Paraiba | AG240: 31 | AH240: - | AI240: sindtrabrural@digimaster.com.br | AJ240: 3732261171 | AK240: - | AL240: 06/06/2009 | AM240: 06/06/2012 | AN240: GERALDO MAGELA VIEGAS | AO240: MUNICIPAL | AP240: Minas Gerais: Nova Serrana
A241: =_xlfn.XLOOKUP(AD241,'Municipios MG'!$B$2:$B$853,'Municipios MG'!$A$2:$A$853) -> 3155009 | B241: =_xlfn.XLOOKUP(AD241,'Municipios MG'!$B$2:$B$853,'Municipios MG'!$B$2:$B$853) -> Rio Doce | C241: =_xlfn.XLOOKUP(AD241,'Municipios MG'!$B$2:$B$853,'Municipios MG'!$C$2:$C$853) -> -20.244646 | D241: =_xlfn.XLOOKUP(AD241,'Municipios MG'!$B$2:$B$853,'Municipios MG'!$D$2:$D$853) -> -42.895681 | E241: =_xlfn.XLOOKUP(A241,Planilha3!$A$2:$A$5543,Planilha3!$C$2:$C$5543) -> ... | F241: =_xlfn.XLOOKUP(A241,Planilha3!$A$2:$A$5543,Planilha3!$E$2:$E$5543) -> ... | H241: 07.627.616/0001-36 | I241: INATIVO | J241: SINDICATO | K241: sindro - sindicato dos trabalhadores rurais de rio doce-mg | L241: SINDICATO DOS TRABALHADORES RURAIS DE RIO DOCE | M241: 000.000.000.00000-0 | N241: CENTRAL DO BRASIL DEMOCRATICA DE TRABALHADORES - CBDT NACIONAL | O241: Confederação Nacional dos Trabalhadores Rurais Agricultores e Agricultoras Familiares | P241: - | Q241: PRESIDENCIALISMO | R241: 14 | S241: 42 | T241: DIRETA | U241: 1 | V241: 73 | W241: 42 | X241: RURAL | Y241: TRABALHADORES | Z241: RURAL | AA241: Profissional dos Trabalhadores Rurais, plano da CONTAG | AB241: 35442-000 | AC241: MG | AD241: Rio Doce | AE241: centro | AF241: rua Major eugenio palermo | AG241: 102 | AH241: - | AI241: - | AJ241: 3138835139 | AK241: - | AL241: 19/06/2009 | AM241: 19/06/2013 | AN241: NOE CORCINI CAMPOS | AO241: MUNICIPAL | AP241: Minas Gerais: Rio Doce
A242: =_xlfn.XLOOKUP(AD242,'Municipios MG'!$B$2:$B$853,'Municipios MG'!$A$2:$A$853) -> 3157609 | B242: =_xlfn.XLOOKUP(AD242,'Municipios MG'!$B$2:$B$853,'Municipios MG'!$B$2:$B$853) -> Santa Fé de Minas | C242: =_xlfn.XLOOKUP(AD242,'Municipios MG'!$B$2:$B$853,'Municipios MG'!$C$2:$C$853) -> -16.687373 | D242: =_xlfn.XLOOKUP(AD242,'Municipios MG'!$B$2:$B$853,'Municipios MG'!$D$2:$D$853) -> -45.413633 | E242: =_xlfn.XLOOKUP(A242,Planilha3!$A$2:$A$5543,Planilha3!$C$2:$C$5543) -> ... | F242: =_xlfn.XLOOKUP(A242,Planilha3!$A$2:$A$5543,Planilha3!$E$2:$E$5543) -> ... | H242: 02.670.864/0001-46 | I242: ATIVO | J242: SINDICATO | K242: Sindicato dos Trabalhadores Rurais de Santa Fé de Minas/MG | L242: SINDICATO DOS TRABALHADORES RURAIS DE SANTA FE DE MINAS | M242: 000.000.000.00000-0 | N242: - | O242: - | P242: - | Q242: PRESIDENCIALISMO | R242: 15 | S242: 15 | T242: DIRETA | U242: 1 | V242: 15 | W242: 15 | X242: RURAL | Y242: TRABALHADORES | Z242: RURAL | AA242: Profissional dos trabalhadores e trabalhadoras rurais: assalariados e assalariadas rurais, empregados permanentes, safristas e eventuais na agricultura, criação de animais e hortifruticultura; e agricultores e agricultoras que exerçam atividades individualmente ou em regime de economia familiar, na qualidade de pequenos produtores, proprietários até dois módulos rurais (Decreto 1166/71), posseiros, assentados, meeiros, parceiros, arrendatários, comodatários e os aposentados(as) rurais. | AB242: 39295-000 | AC242: MG | AD242: Santa Fé de Minas | AE242: Centro | AF242: Av. Belo Horizonte | AG242: 1816 | AH242: Santa Cruz | AI242: adailtontotoca@yahoo.com.br | AJ242: 3836321176 | AK242: - | AL242: 20/04/2020 | AM242: 20/04/2024 | AN242: MAURILIO GONCALVES DA SILVA | AO242: MUNICIPAL | AP242: Minas Gerais: Santa Fé de Minas
A243: =_xlfn.XLOOKUP(AD243,'Municipios MG'!$B$2:$B$853,'Municipios MG'!$A$2:$A$853) -> 3164209 | B243: =_xlfn.XLOOKUP(AD243,'Municipios MG'!$B$2:$B$853,'Municipios MG'!$B$2:$B$853) -> São Romão | C243: =_xlfn.XLOOKUP(AD243,'Municipios MG'!$B$2:$B$853,'Municipios MG'!$C$2:$C$853) -> -16.368639 | D243: =_xlfn.XLOOKUP(AD243,'Municipios MG'!$B$2:$B$853,'Municipios MG'!$D$2:$D$853) -> -45.069135 | E243: =_xlfn.XLOOKUP(A243,Planilha3!$A$2:$A$5543,Planilha3!$C$2:$C$5543) -> ... | F243: =_xlfn.XLOOKUP(A243,Planilha3!$A$2:$A$5543,Planilha3!$E$2:$E$5543) -> ... | H243: 21.366.745/0001-49 | I243: ATIVO | J243: SINDICATO | K243: STR São Romão/MG - Sindicato dos Trabalhadores Rurais de São Romão/MG | L243: SINDICATO DOS TRABALHADORES RURAIS DE SAO ROMAO | M243: 000.000.000.00000-0 | N243: - | O243: Confederação Nacional dos Trabalhadores Rurais Agricultores e Agricultoras Familiares | P243: FETAEMG - Federação dos Trabalhadores na Agricultura do Estado de Minas Gerais | Q243: PRESIDENCIALISMO | R243: 12 | S243: 60 | T243: DIRETA | U243: 1 | V243: 5016 | W243: 61 | X243: RURAL | Y243: TRABALHADORES | Z243: RURAL | AA243: Trabalhadores rurais | AB243: 39290-000 | AC243: MG | AD243: São Romão | AE243: - | AF243: Av. Eustáquio Martins | AG243: 400 | AH243: centro | AI243: strsaoromao@hotmail.com | AJ243: 3836241532 | AK243: - | AL243: 18/02/2026 | AM243: 18/02/2030 | AN243: LILIAN ALVES DOS SANTOS | AO243: MUNICIPAL | AP243: Minas Gerais: São Romão
A244: =_xlfn.XLOOKUP(AD244,'Municipios MG'!$B$2:$B$853,'Municipios MG'!$A$2:$A$853) -> 3171006 | B244: =_xlfn.XLOOKUP(AD244,'Municipios MG'!$B$2:$B$853,'Municipios MG'!$B$2:$B$853) -> Vazante | C244: =_xlfn.XLOOKUP(AD244,'Municipios MG'!$B$2:$B$853,'Municipios MG'!$C$2:$C$853) -> -17.991038 | D244: =_xlfn.XLOOKUP(AD244,'Municipios MG'!$B$2:$B$853,'Municipios MG'!$D$2:$D$853) -> -46.901967 | E244: =_xlfn.XLOOKUP(A244,Planilha3!$A$2:$A$5543,Planilha3!$C$2:$C$5543) -> ... | F244: =_xlfn.XLOOKUP(A244,Planilha3!$A$2:$A$5543,Planilha3!$E$2:$E$5543) -> ... | H244: 02.074.018/0001-63 | I244: INATIVO | J244: SINDICATO | K244: straafv - Sindicato dos Trabalhadores Rurais,Assalariados e Agricultores Familiares do Município de Varzante - MG | L244: SINDICATO DOS TRABALHADORES RURAIS, ASSALARIADOS E AGRICULTO | M244: 000.000.000.00000-0 | N244: - | O244: Confederação Nacional dos Trabalhadores Rurais Agricultores e Agricultoras Familiares | P244: FETAEMG - Federação dos Trabalhadores na Agricultura do Estado de Minas Gerais | Q244: PRESIDENCIALISMO | R244: 15 | S244: 136 | T244: DIRETA | U244: 1 | V244: 242 | W244: 186 | X244: RURAL | Y244: TRABALHADORES | Z244: RURAL | AA244: Profissional dos Trabalhadores(as) Rurais, Empregados (as)Rurais e Agricultores Familiares, Ativos (as) e Aposentados (as).São considerados Trabalhadores Rurais, os que exercem atividade como assalariados na Agricultura, Pecuária e similares, na Produção Rural, bem como os Agricultores Familiares, proprietários ou não, que exerçam atividade Rural, Individualmente ou em Regime de Economia Familiar, assim entendido o trabalho dos membros da mesma família, executado em condições de mútua dependência e colaboração, ainda que com ajuda eventual de terceiros, Trabalhadores no Reflorestamento, Hortifrutigranjeiros, Assentados e parceleiros da Reforma Agrária, Pescadores e Garimpeiros Artesanais que Trabalham por conta própria e não tenham Empregados, Trabalhadores na Área da Cana e da Avicultura, Tratorista Rural e os que Trabalham com Artesanato Rural | AB244: 38780-000 | AC244: MG | AD244: Vazante | AE244: Centro | AF244: Rua : Joao Claudio | AG244: 107 | AH244: Casa | AI244: strvazante@gmail.com.br | AJ244: 3438131510 | AK244: - | AL244: 05/01/2010 | AM244: 01/01/2014 | AN244: ELICIA FERREIRA DO PRADO | AO244: MUNICIPAL | AP244: Minas Gerais: Vazante
... A282: =_xlfn.XLOOKUP(AD282,'Municipios MG'!$B$2:$B$853,'Municipios MG'!$A$2:$A$853) -> 3119401 | B282: =_xlfn.XLOOKUP(AD282,'Municipios MG'!$B$2:$B$853,'Municipios MG'!$B$2:$B$853) -> Coronel Fabriciano | C282: =_xlfn.XLOOKUP(AD282,'Municipios MG'!$B$2:$B$853,'Municipios MG'!$C$2:$C$853) -> -19.525053 | D282: =_xlfn.XLOOKUP(AD282,'Municipios MG'!$B$2:$B$853,'Municipios MG'!$D$2:$D$853) -> -42.624347 | E282: =_xlfn.XLOOKUP(A282,Planilha3!$A$2:$A$5543,Planilha3!$C$2:$C$5543) -> - | F282: =_xlfn.XLOOKUP(A282,Planilha3!$A$2:$A$5543,Planilha3!$E$2:$E$5543) -> - | H282: 21.449.768/0001-17 | I282: ATIVO | J282: SINDICATO | K282: STR Coronel Fabricano - Sindicato dos Trabalhadores Rurais de Coronel Fabriciano | L282: SINDICATO DOS TRABALHADORES RURAIS DE CORONEL FABRICIANO | M282: 000.000.000.00000-0 | N282: - | O282: - | P282: - | Q282: PRESIDENCIALISMO | R282: 15 | S282: 26 | T282: DECISAO_ASSEMBLEIA | U282: 1 | V282: 26 | W282: 26 | X282: RURAL | Y282: TRABALHADORES | Z282: RURAL | AA282: Trabalhadores e trabalhadoras rurais: assalariados e assalariadas rurais, empregados permanentes, safristas e eventuais na agricultura, criação de animais e hortifruticultura; e agricultores e agricultoras que exerçam atividades individualmente ou em regime de economia familiar, na qualidades de pequenos produtores, proprietários ate dois módulos rurais, posseiros, assentados, meeiros, parceiros, arrendatários, comodatários e os aposentados (as) rurais. | AB282: 35171-353 | AC282: MG | AD282: Coronel Fabriciano | AE282: Sylvio Pereira I | AF282: Rua Osvaldina Vieira Mota | AG282: 52 | AH282: - | AI282: sintrucelf@outloo.com | AJ282: 3138468733 | AK282: - | AL282: 16/06/2016 | AM282: 15/06/2020 | AN282: JOSE PEREIRA DE MOURA | AO282: INTERMUNICIPAL | AP282: Minas Gerais: Antônio Dias, Coronel Fabriciano, Jaguaraçu, Marliéria
A283: =_xlfn.XLOOKUP(AD283,'Municipios MG'!$B$2:$B$853,'Municipios MG'!$A$2:$A$853) -> 3119500 | B283: =_xlfn.XLOOKUP(AD283,'Municipios MG'!$B$2:$B$853,'Municipios MG'!$B$2:$B$853) -> Coronel Murta | C283: =_xlfn.XLOOKUP(AD283,'Municipios MG'!$B$2:$B$853,'Municipios MG'!$C$2:$C$853) -> -16.610268 | D283: =_xlfn.XLOOKUP(AD283,'Municipios MG'!$B$2:$B$853,'Municipios MG'!$D$2:$D$853) -> -42.184804 | E283: =_xlfn.XLOOKUP(A283,Planilha3!$A$2:$A$5543,Planilha3!$C$2:$C$5543) -> - | F283: =_xlfn.XLOOKUP(A283,Planilha3!$A$2:$A$5543,Planilha3!$E$2:$E$5543) -> - | H283: 06.531.793/0001-51 | I283: INATIVO | J283: SINDICATO | K283: Sindicato dos Garimpeiros de Coronel Murta e do Médio Jequitinhonha”,MG | L283: SINDICATO DOS GARIMPEIROS DE CORONEL MURTA E DO MEDIO JEQUITINHONHA | M283: 000.000.000.00000-0 | N283: - | O283: - | P283: - | Q283: COLEGIADA | R283: - | S283: - | T283: - | U283: - | V283: 0 | W283: - | X283: RURAL | Y283: TRABALHADORES | Z283: RURAL | AA283: Profissional dos Garimpeiros | AB283: 39635-000 | AC283: MG | AD283: Coronel Murta | AE283: Centro | AF283: Inacio Figueiredo | AG283: 127 | AH283: - | AI283: pmcmurta@pop.com.br | AJ283: 3337351442 | AK283: - | AL283: 08/02/2007 | AM283: 08/02/2010 | AN283: - | AO283: INTERMUNICIPAL | AP283: Minas Gerais: Araçuaí, Coronel Murta, Itaobim, Itinga, Rubelita, Salinas, Virgem da Lapa
A284: =_xlfn.XLOOKUP(AD284,'Municipios MG'!$B$2:$B$853,'Municipios MG'!$A$2:$A$853) -> 3119500 | B284: =_xlfn.XLOOKUP(AD284,'Municipios MG'!$B$2:$B$853,'Municipios MG'!$B$2:$B$853) -> Coronel Murta | C284: =_xlfn.XLOOKUP(AD284,'Municipios MG'!$B$2:$B$853,'Municipios MG'!$C$2:$C$853) -> -16.610268 | D284: =_xlfn.XLOOKUP(AD284,'Municipios MG'!$B$2:$B$853,'Municipios MG'!$D$2:$D$853) -> -42.184804 | E284: =_xlfn.XLOOKUP(A284,Planilha3!$A$2:$A$5543,Planilha3!$C$2:$C$5543) -> - | F284: =_xlfn.XLOOKUP(A284,Planilha3!$A$2:$A$5543,Planilha3!$E$2:$E$5543) -> - | H284: 18.355.214/0001-46 | I284: ATIVO | J284: SINDICATO | K284: STR de Coronel Murta - Sindicato dos Trabalhadores Rurais de Corone | L284: SINDICATO DOS TRABALHADORES RURAIS DE CORONEL MURTA | M284: 000.000.000.00000-0 | N284: - | O284: Confederação Nacional dos Trabalhadores Rurais Agricultores e Agricultoras Familiares | P284: FETAEMG - Federação dos Trabalhadores na Agricultura do Estado de Minas Gerais | Q284: PRESIDENCIALISMO | R284: 5 | S284: 436 | T284: DIRETA | U284: 2 | V284: 3956 | W284: 1005 | X284: RURAL | Y284: TRABALHADORES | Z284: RURAL | AA284: Profissional, dos Trabalhadores Rurais do Plano da CONTAG | AB284: 39635-000 | AC284: MG | AD284: Coronel Murta | AE284: Centro | AF284: Rua Rita Murta | AG284: 27 | AH284: Sede | AI284: strmurta@yahoo.com.br | AJ284: 3337351211 | AK284: - | AL284: 01/01/2022 | AM284: 31/12/2025 | AN284: AUXILIADORA ALVES MARTINS | AO284: MUNICIPAL | AP284: Minas Gerais: Coronel Murta
A285: =_xlfn.XLOOKUP(AD285,'Municipios MG'!$B$2:$B$853,'Municipios MG'!$A$2:$A$853) -> 3120607 | B285: =_xlfn.XLOOKUP(AD285,'Municipios MG'!$B$2:$B$853,'Municipios MG'!$B$2:$B$853) -> Crucilândia | C285: =_xlfn.XLOOKUP(AD285,'Municipios MG'!$B$2:$B$853,'Municipios MG'!$C$2:$C$853) -> -20.393292 | D285: =_xlfn.XLOOKUP(AD285,'Municipios MG'!$B$2:$B$853,'Municipios MG'!$D$2:$D$853) -> -44.337837 | E285: =_xlfn.XLOOKUP(A285,Planilha3!$A$2:$A$5543,Planilha3!$C$2:$C$5543) -> - | F285: =_xlfn.XLOOKUP(A285,Planilha3!$A$2:$A$5543,Planilha3!$E$2:$E$5543) -> - | H285: 19.164.110/0001-17 | I285: ATIVO | J285: SINDICATO | K285: Sindicato dos Trabalhadores Rurais de Crucilândia | L285: SINDICATO DOS TRABALHADORES RURAIS DE CRUCILANDIA | M285: 000.000.000.00000-0 | N285: CENTRAL DO BRASIL DEMOCRATICA DE TRABALHADORES - CBDT NACIONAL | O285: Confederação Nacional dos Trabalhadores Rurais Agricultores e Agricultoras Familiares | P285: FETAEMG - Federação dos Trabalhadores na Agricultura do Estado de Minas Gerais | Q285: PRESIDENCIALISMO | R285: 12 | S285: 221 | T285: DECISAO_ASSEMBLEIA | U285: 2 | V285: 1861 | W285: 329 | X285: RURAL | Y285: TRABALHADORES | Z285: RURAL | AA285: Profissionais, dos Trabalhadores Rurais do plano da CONTAG. | AB285: 35520-000 | AC285: MG | AD285: Crucilândia | AE285: Centro | AF285: Rua Luiz Alves de Souza | AG285: 09 | AH285: casa | AI285: strcruci@ig.com.br | AJ285: 3135741132 | AK285: - | AL285: 19/12/2020 | AM285: 18/12/2024 | AN285: LUIZ CARLOS DINIZ | AO285: MUNICIPAL | AP285: Minas Gerais: Crucilândia
A286: =_xlfn.XLOOKUP(AD286,'Municipios MG'!$B$2:$B$853,'Municipios MG'!$A$2:$A$853) -> 3120904 | B286: =_xlfn.XLOOKUP(AD286,'Municipios MG'!$B$2:$B$853,'Municipios MG'!$B$2:$B$853) -> Curvelo | C286: =_xlfn.XLOOKUP(AD286,'Municipios MG'!$B$2:$B$853,'Municipios MG'!$C$2:$C$853) -> -18.755481 | D286: =_xlfn.XLOOKUP(AD286,'Municipios MG'!$B$2:$B$853,'Municipios MG'!$D$2:$D$853) -> -44.428399 | E286: =_xlfn.XLOOKUP(A286,Planilha3!$A$2:$A$5543,Planilha3!$C$2:$C$5543) -> - | F286: =_xlfn.XLOOKUP(A286,Planilha3!$A$2:$A$5543,Planilha3!$E$2:$E$5543) -> - | H286: 04.650.348/0001-85 | I286: ATIVO | J286: SINDICATO | K286: Sindicato dos Empregados Rurais de de Curvelo", MG. | L286: SINDICATO DOS TRABALHADORES E TRABALHADORAS RURAIS DE CURVELO-MG | M286: 000.000.000.00000-0 | N286: CUT - Central Única dos Trabalhadores | O286: - | P286: - | Q286: PRESIDENCIALISMO | R286: 11 | S286: 140 | T286: DECISAO_ASSEMBLEIA | U286: 1 | V286: 3415 | W286: 140 | X286: RURAL | Y286: TRABALHADORES | Z286: RURAL | AA286: Trabalhadores rurais: assalariados e assalariadas rurais empregados permanentes, safrista e eventuais na agricultura, criação de animais, silvicultura, hortifruticultura e extrativismo rural; e agricultores e agricultoras que exerçam atividades individualmente ou em regime de economia familiar, na qualidade de pequenos produtores, proprietários, posseiros assentados meeiros, parceiros, arrendatário, comodatários e extrativista. | AB286: 35790-000 | AC286: MG | AD286: Curvelo | AE286: palmeiras | AF286: RUA:Campo alto | AG286: 268 | AH286: casa | AI286: strcurvelo@rznet.com.br | AJ286: 3837225718 | AK286: - | AL286: 09/07/2016 | AM286: 09/07/2021 | AN286: ROGERIO TAVARES LEITE | AO286: MUNICIPAL | AP286: Minas Gerais: Curvelo
A287: =_xlfn.XLOOKUP(AD287,'Municipios MG'!$B$2:$B$853,'Municipios MG'!$A$2:$A$853) -> 3121258 | B287: =_xlfn.XLOOKUP(AD287,'Municipios MG'!$B$2:$B$853,'Municipios MG'!$B$2:$B$853) -> Delta | C287: =_xlfn.XLOOKUP(AD287,'Municipios MG'!$B$2:$B$853,'Municipios MG'!$C$2:$C$853) -> -19.977473 | D287: =_xlfn.XLOOKUP(AD287,'Municipios MG'!$B$2:$B$853,'Municipios MG'!$D$2:$D$853) -> -47.772971 | E287: =_xlfn.XLOOKUP(A287,Planilha3!$A$2:$A$5543,Planilha3!$C$2:$C$5543) -> - | F287: =_xlfn.XLOOKUP(A287,Planilha3!$A$2:$A$5543,Planilha3!$E$2:$E$5543) -> - | H287: 04.142.910/0001-60 | I287: ATIVO | J287: SINDICATO | K287: STRDELTA - SINDICATO DOS TRABALHADORES RURAIS DE DELTA/MG | L287: SINDICATO DOS TRABALHADORES RURAIS E DO SETOR SUCROENERGETIC | M287: 000.000.000.00000-0 | N287: CTB - Central dos Trabalhadores e Trabalhadoras do Brasil | O287: - | P287: FETAEMG - Federação dos Trabalhadores na Agricultura do Estado de Minas Gerais | Q287: PRESIDENCIALISMO | R287: 12 | S287: 16 | T287: DECISAO_ASSEMBLEIA | U287: 1 | V287: 19 | W287: 16 | X287: RURAL | Y287: TRABALHADORES | Z287: RURAL | AA287: Trabalhadores Rurais, Empregados, Assalariados em Geral, que exercem atividades nos seguintes setores: Canavieiro, Citricultura, Cultura Diversificada, Granjeiros, Pecuária, Reflorestamento, Corte de Madeira e Extrativismo Rural | AB287: 38108-000 | AC287: MG | AD287: Delta | AE287: Centro | AF287: Rua Manoel Abadia da Silva | AG287: 378 | AH287: - | AI287: strdelta@netsite.com.br | AJ287: 3433251495 | AK287: - | AL287: 07/04/2020 | AM287: 06/04/2028 | AN287: EDILSO LEANDRO RIBEIRO | AO287: MUNICIPAL | AP287: Minas Gerais: Delta
A288: =_xlfn.XLOOKUP(AD288,'Municipios MG'!$B$2:$B$853,'Municipios MG'!$A$2:$A$853) -> 3121803 | B288: =_xlfn.XLOOKUP(AD288,'Municipios MG'!$B$2:$B$853,'Municipios MG'!$B$2:$B$853) -> Dionísio | C288: =_xlfn.XLOOKUP(AD288,'Municipios MG'!$B$2:$B$853,'Municipios MG'!$C$2:$C$853) -> -19.843997 | D288: =_xlfn.XLOOKUP(AD288,'Municipios MG'!$B$2:$B$853,'Municipios MG'!$D$2:$D$853) -> -42.782368 | E288: =_xlfn.XLOOKUP(A288,Planilha3!$A$2:$A$5543,Planilha3!$C$2:$C$5543) -> - | F288: =_xlfn.XLOOKUP(A288,Planilha3!$A$2:$A$5543,Planilha3!$E$2:$E$5543) -> - | H288: 05.195.955/0001-65 | I288: ATIVO | J288: SINDICATO | K288: STRD - SINDICATO DOS TRABALHADORES RURAIS DE DIONÍSIO | L288: SINDICATO DOS TRABALHADORES RURAIS DE DIONISIO | M288: 000.000.000.00000-0 | N288: CUT - Central Única dos Trabalhadores | O288: Confederação Nacional dos Trabalhadores Rurais Agricultores e Agricultoras Familiares | P288: FETAEMG - Federação dos Trabalhadores na Agricultura do Estado de Minas Gerais | Q288: PRESIDENCIALISMO | R288: 12 | S288: 45 | T288: DIRETA | U288: 1 | V288: 233 | W288: 45 | X288: RURAL | Y288: TRABALHADORES | Z288: RURAL | AA288: Profissional dos Trabalhadores Rurais, do Plano da CONTAG | AB288: 35984-000 | AC288: MG | AD288: Dionísio | AE288: Centro | AF288: Rua Senador Milton Campos | AG288: 136 | AH288: - | AI288: strdionisio@yahoo.com.br | AJ288: 3138581302 | AK288: - | AL288: 20/06/2023 | AM288: 20/06/2027 | AN288: ANTONIO CARLOS SILVA LEAO | AO288: MUNICIPAL | AP288: Minas Gerais: Dionísio
A289: =_xlfn.XLOOKUP(AD289,'Municipios MG'!$B$2:$B$853,'Municipios MG'!$A$2:$A$853) -> 3122306 | B289: =_xlfn.XLOOKUP(AD289,'Municipios MG'!$B$2:$B$853,'Municipios MG'!$B$2:$B$853) -> Divinópolis | C289: =_xlfn.XLOOKUP(AD289,'Municipios MG'!$B$2:$B$853,'Municipios MG'!$C$2:$C$853) -> -20.142074 | D289: =_xlfn.XLOOKUP(AD289,'Municipios MG'!$B$2:$B$853,'Municipios MG'!$D$2:$D$853) -> -44.893886 | E289: =_xlfn.XLOOKUP(A289,Planilha3!$A$2:$A$5543,Planilha3!$C$2:$C$5543) -> - | F289: =_xlfn.XLOOKUP(A289,Planilha3!$A$2:$A$5543,Planilha3!$E$2:$E$5543) -> - | H289: 20.169.355/0001-16 | I289: ATIVO | J289: SINDICATO | K289: STR - STR DIVINOPOLIS | L289: SINDICATO DOS TRABALHADORES RURAIS DE DIVINOPOLIS | M289: 000.000.000.00000-0 | N289: CENTRAL DO BRASIL DEMOCRATICA DE TRABALHADORES - CBDT NACIONAL | O289: Confederação Nacional dos Trabalhadores Rurais Agricultores e Agricultoras Familiares | P289: FETAEMG - Federação dos Trabalhadores na Agricultura do Estado de Minas Gerais | Q289: PRESIDENCIALISMO | R289: 12 | S289: 706 | T289: DIRETA | U289: 1 | V289: 13612 | W289: 725 | X289: RURAL | Y289: TRABALHADORES | Z289: RURAL | AA289: Profissional dos Trabalhadores Rurais, plano da CONTAG | AB289: 35500-022 | AC289: MG | AD289: Divinópolis | AE289: Centro | AF289: Rua Oeste de Minas | AG289: 36 | AH289: - | AI289: sinddivinopolis@gmail.com | AJ289: 3732147404 | AK289: - | AL289: 25/03/2022 | AM289: 25/03/2026 | AN289: JOSE ANTONIO RIBEIRO | AO289: INTERMUNICIPAL | AP289: Minas Gerais: Divinópolis, Pedra do Indaiá, Santo Antônio do Monte, São Sebastião do Oeste
A290: =_xlfn.XLOOKUP(AD290,'Municipios MG'!$B$2:$B$853,'Municipios MG'!$A$2:$A$853) -> 3122470 | B290: =_xlfn.XLOOKUP(AD290,'Municipios MG'!$B$2:$B$853,'Municipios MG'!$B$2:$B$853) -> Dom Bosco | C290: =_xlfn.XLOOKUP(AD290,'Municipios MG'!$B$2:$B$853,'Municipios MG'!$C$2:$C$853) -> -16.65075 | D290: =_xlfn.XLOOKUP(AD290,'Municipios MG'!$B$2:$B$853,'Municipios MG'!$D$2:$D$853) -> -46.27145 | E290: =_xlfn.XLOOKUP(A290,Planilha3!$A$2:$A$5543,Planilha3!$C$2:$C$5543) -> - | F290: =_xlfn.XLOOKUP(A290,Planilha3!$A$2:$A$5543,Planilha3!$E$2:$E$5543) -> - | H290: 03.800.566/0001-96 | I290: ATIVO | J290: SINDICATO | K290: STR - Sindicato dos Trabalhadores Rurais de Dom Bosco - MG | L290: SINDICATO DOS TRABAHADORES RURAIS DE DOM BOSCO - MG | M290: 000.000.000.00000-0 | N290: - | O290: Confederação Nacional dos Trabalhadores Rurais Agricultores e Agricultoras Familiares | P290: FETAEMG - Federação dos Trabalhadores na Agricultura do Estado de Minas Gerais | Q290: PRESIDENCIALISMO | R290: 15 | S290: 31 | T290: DIRETA | U290: 1 | V290: 498 | W290: 31 | X290: RURAL | Y290: TRABALHADORES | Z290: RURAL | AA290: Trabalhadores Rurais | AB290: 38654-000 | AC290: MG | AD290: Dom Bosco | AE290: Centro | AF290: Rua José Mendes | AG290: 489 | AH290: casa | AI290: sindicato.dombosco@hotmail.com | AJ290: 3836757147 | AK290: - | AL290: 17/05/2026 | AM290: 17/05/2030 | AN290: BEATRIZ HELENA RODRIGUES SOUZA | AO290: MUNICIPAL | AP290: Minas Gerais: Dom Bosco
A291: =_xlfn.XLOOKUP(AD291,'Municipios MG'!$B$2:$B$853,'Municipios MG'!$A$2:$A$853) -> 3123700 | B291: =_xlfn.XLOOKUP(AD291,'Municipios MG'!$B$2:$B$853,'Municipios MG'!$B$2:$B$853) -> Engenheiro Caldas | C291: =_xlfn.XLOOKUP(AD291,'Municipios MG'!$B$2:$B$853,'Municipios MG'!$C$2:$C$853) -> -19.198103 | D291: =_xlfn.XLOOKUP(AD291,'Municipios MG'!$B$2:$B$853,'Municipios MG'!$D$2:$D$853) -> -42.049842 | E291: =_xlfn.XLOOKUP(A291,Planilha3!$A$2:$A$5543,Planilha3!$C$2:$C$5543) -> - | F291: =_xlfn.XLOOKUP(A291,Planilha3!$A$2:$A$5543,Planilha3!$E$2:$E$5543) -> - | H291: 20.972.535/0001-31 | I291: ATIVO | J291: SINDICATO | K291: STRAAFEC - Sindicato dos Trabalhadores Rurais, Assalariados e Agricultores Familiares do Municipio de Engenheiro Caldas | L291: SINDICATO DOS TRABALHADORES RURAIS ASSALARIADOS E AGRICULTORES FAMILIARES DO MUNICIPIO DE ENGENHEIRO CALDAS | M291: 000.000.000.00000-0 | N291: CTB - Central dos Trabalhadores e Trabalhadoras do Brasil | O291: Confederação Nacional dos Trabalhadores Rurais Agricultores e Agricultoras Familiares | P291: FETAEMG - Federação dos Trabalhadores na Agricultura do Estado de Minas Gerais | Q291: PRESIDENCIALISMO | R291: 16 | S291: 132 | T291: DIRETA | U291: 1 | V291: 2744 | W291: 143 | X291: RURAL | Y291: TRABALHADORES | Z291: RURAL | AA291: Profissional, dos Trabalhadores Rurais do Plano da CONTAG | AB291: 35130-000 | AC291: MG | AD291: Engenheiro Caldas | AE291: José Ernesto de Oliv | AF291: RUA SETE | AG291: 259 | AH291: - | AI291: sindrural.engcaldas@hotmail.com | AJ291: 3332341263 | AK291: - | AL291: 07/01/2024 | AM291: 06/01/2028 | AN291: MARIA MARTINS SOARES CORREIA | AO291: MUNICIPAL | AP291: Minas Gerais: Engenheiro Caldas
A292: =_xlfn.XLOOKUP(AD292,'Municipios MG'!$B$2:$B$853,'Municipios MG'!$A$2:$A$853) -> 3126505 | B292: =_xlfn.XLOOKUP(AD292,'Municipios MG'!$B$2:$B$853,'Municipios MG'!$B$2:$B$853) -> Francisco Badaró | C292: =_xlfn.XLOOKUP(AD292,'Municipios MG'!$B$2:$B$853,'Municipios MG'!$C$2:$C$853) -> -16.990691 | D292: =_xlfn.XLOOKUP(AD292,'Municipios MG'!$B$2:$B$853,'Municipios MG'!$D$2:$D$853) -> -42.349773 | E292: =_xlfn.XLOOKUP(A292,Planilha3!$A$2:$A$5543,Planilha3!$C$2:$C$5543) -> - | F292: =_xlfn.XLOOKUP(A292,Planilha3!$A$2:$A$5543,Planilha3!$E$2:$E$5543) -> - | H292: 16.886.673/0001-20 | I292: ATIVO | J292: SINDICATO | K292: STR Francisco Badaró/MG - Sindicato dos Trabalhadores Rurais de Francisco Badaró/MG | L292: SINDICATO DOS TRABALHADORES RURAIS DE FRANCISCO BADARO | M292: 000.000.000.00000-0 | N292: - | O292: Confederação Nacional dos Trabalhadores Rurais Agricultores e Agricultoras Familiares | P292: FETAEMG - Federação dos Trabalhadores na Agricultura do Estado de Minas Gerais | Q292: PRESIDENCIALISMO | R292: 13 | S292: 463 | T292: DECISAO_ASSEMBLEIA | U292: 1 | V292: 5040 | W292: 473 | X292: RURAL | Y292: TRABALHADORES | Z292: RURAL | AA292: Profissional, dos Trabalhadores Rurais do Plano da CONTAG | AB292: 39644-000 | AC292: MG | AD292: Francisco Badaró | AE292: - | AF292: Av. João Pinheiro | AG292: 12 | AH292: Fátima | AI292: strfb@uai.com.br | AJ292: 3337381246 | AK292: - | AL292: 07/04/2022 | AM292: 07/04/2026 | AN292: EDSON CLAUDIO RIBEIRO DA SILVA | AO292: MUNICIPAL | AP292: Minas Gerais: Francisco Badaró
A293: =_xlfn.XLOOKUP(AD293,'Municipios MG'!$B$2:$B$853,'Municipios MG'!$A$2:$A$853) -> 3126703 | B293: =_xlfn.XLOOKUP(AD293,'Municipios MG'!$B$2:$B$853,'Municipios MG'!$B$2:$B$853) -> Francisco Sá | C293: =_xlfn.XLOOKUP(AD293,'Municipios MG'!$B$2:$B$853,'Municipios MG'!$C$2:$C$853) -> -16.475681 | D293: =_xlfn.XLOOKUP(AD293,'Municipios MG'!$B$2:$B$853,'Municipios MG'!$D$2:$D$853) -> -43.488735 | E293: =_xlfn.XLOOKUP(A293,Planilha3!$A$2:$A$5543,Planilha3!$C$2:$C$5543) -> - | F293: =_xlfn.XLOOKUP(A293,Planilha3!$A$2:$A$5543,Planilha3!$E$2:$E$5543) -> - | H293: 25.217.647/0001-09 | I293: ATIVO | J293: SINDICATO | K293: STR Francisco Sá/MG - Sindicato dos Trabalhadores Rurais de Francisco Sá/MG | L293: SINDICATO DOS TRABALHADORES RURAIS DE FRANCISCO SA | M293: 000.000.000.00000-0 | N293: - | O293: Confederação Nacional dos Trabalhadores Rurais Agricultores e Agricultoras Familiares | P293: FETAEMG - Federação dos Trabalhadores na Agricultura do Estado de Minas Gerais | Q293: PRESIDENCIALISMO | R293: 16 | S293: 260 | T293: DECISAO_ASSEMBLEIA | U293: 1 | V293: 7793 | W293: 263 | X293: RURAL | Y293: TRABALHADORES | Z293: RURAL | AA293: Profissional, dos Trabalhadores Rurais do Plano da CONTAG. EXCETO a Categoria dos agricultores familiares, que exercem atividades na agricultura como proprietário (as), arrendatários (as), comodatários (as), parceiros (as), meeiros (as), posseiros (as), acampados (as), que desenvolvem suas atividades de forma individual ou coletiva com os membros da família, numa área de até 2 módulos rurais, conforme dispõe o Decreto-Lei 1.166 de 15 de abril de 1971, nos termos do art. 30 da Portaria 326/2013. | AB293: 39580-000 | AC293: MG | AD293: Francisco Sá | AE293: - | AF293: Rua Olímpio Dias | AG293: 180 | AH293: Centro | AI293: sindicatofranciscosa@gmail.com | AJ293: 3832331294 | AK293: - | AL293: 15/01/2023 | AM293: 14/01/2027 | AN293: JOSE JOAO RODRIGUES DE AMORIM | AO293: MUNICIPAL | AP293: Minas Gerais: Francisco Sá
A294: =_xlfn.XLOOKUP(AD294,'Municipios MG'!$B$2:$B$853,'Municipios MG'!$A$2:$A$853) -> 3127073 | B294: =_xlfn.XLOOKUP(AD294,'Municipios MG'!$B$2:$B$853,'Municipios MG'!$B$2:$B$853) -> Fruta de Leite | C294: =_xlfn.XLOOKUP(AD294,'Municipios MG'!$B$2:$B$853,'Municipios MG'!$C$2:$C$853) -> -16.116418 | D294: =_xlfn.XLOOKUP(AD294,'Municipios MG'!$B$2:$B$853,'Municipios MG'!$D$2:$D$853) -> -42.532222 | E294: =_xlfn.XLOOKUP(A294,Planilha3!$A$2:$A$5543,Planilha3!$C$2:$C$5543) -> - | F294: =_xlfn.XLOOKUP(A294,Planilha3!$A$2:$A$5543,Planilha3!$E$2:$E$5543) -> - | H294: 02.782.031/0001-77 | I294: ATIVO | J294: SINDICATO | K294: STR - STR FRUTA DE LEITE | L294: SINDICATO DOS TRABALHADORES RURAIS DE FRUTA DE LEITTE | M294: 000.000.000.00000-0 | N294: - | O294: Confederação Nacional dos Trabalhadores Rurais Agricultores e Agricultoras Familiares | P294: FETAEMG - Federação dos Trabalhadores na Agricultura do Estado de Minas Gerais | Q294: PRESIDENCIALISMO | R294: 12 | S294: 458 | T294: DECISAO_ASSEMBLEIA | U294: 1 | V294: 2215 | W294: 596 | X294: RURAL | Y294: TRABALHADORES | Z294: RURAL | AA294: Trabalhadores Rurais, Integrantes do Plano da Confederação Nacional dos Trabalhadores na Agricultura | AB294: 39558-000 | AC294: MG | AD294: Fruta de Leite | AE294: centro | AF294: rua cipriano moreira | AG294: 234 | AH294: - | AI294: - | AJ294: 3838419121 | AK294: - | AL294: 30/04/2022 | AM294: 29/04/2026 | AN294: VALDIVINO FERREIRA DOS SANTOS | AO294: MUNICIPAL | AP294: Minas Gerais: Fruta de Leite
A295: =_xlfn.XLOOKUP(AD295,'Municipios MG'!$B$2:$B$853,'Municipios MG'!$A$2:$A$853) -> 3127107 | B295: =_xlfn.XLOOKUP(AD295,'Municipios MG'!$B$2:$B$853,'Municipios MG'!$B$2:$B$853) -> Frutal | C295: =_xlfn.XLOOKUP(AD295,'Municipios MG'!$B$2:$B$853,'Municipios MG'!$C$2:$C$853) -> -20.025898 | D295: =_xlfn.XLOOKUP(AD295,'Municipios MG'!$B$2:$B$853,'Municipios MG'!$D$2:$D$853) -> -48.939154 | E295: =_xlfn.XLOOKUP(A295,Planilha3!$A$2:$A$5543,Planilha3!$C$2:$C$5543) -> - | F295: =_xlfn.XLOOKUP(A295,Planilha3!$A$2:$A$5543,Planilha3!$E$2:$E$5543) -> - | H295: 20.024.501/0001-15 | I295: ATIVO | J295: SINDICATO | K295: Sindicato dos Trabalhadores Rurais, Assalariados e Agricultores Familiares do Munícipio de Frutal e Comendador Gomes - MG | L295: SINDICATO DOS TRABALHADORES RURAIS ASSALARIADOS E AGRICULTORES FAMILIARES DO MUNICIPIO DE FRUTAL E COMENDADOR GOMES MG | M295: 000.000.000.00000-0 | N295: - | O295: - | P295: FETAEMG - Federação dos Trabalhadores na Agricultura do Estado de Minas Gerais | Q295: PRESIDENCIALISMO | R295: 12 | S295: 17 | T295: DIRETA | U295: 1 | V295: 1790 | W295: 25 | X295: RURAL | Y295: TRABALHADORES | Z295: RURAL | AA295: Trabalhadores e trabalhadoras rurais: os assalariados e assalariadas rurais,permanentes, safristas ou eventuais que exerçam suas atividades na agricultura, criação de animais, silvicultura, hortifruticultura e extrativismo rural, e os agricultores e agricultoras que exerçam atividades individualmente ou em regime de economia familiar, na qualidade de pequenos produtores, proprietários, posseiros, assentados, meeiros, parceiros, arrendatários, comodatários e extrativistas. | AB295: 38200-000 | AC295: MG | AD295: Frutal | AE295: XV de Novembro | AF295: Rua Minas Gerais | AG295: 168 | AH295: - | AI295: - | AJ295: 3434214577 | AK295: - | AL295: 16/01/2023 | AM295: 15/01/2027 | AN295: MARCILEIA ALVES FERREIRA | AO295: INTERMUNICIPAL | AP295: Minas Gerais: Comendador Gomes, Frutal
... A305: =_xlfn.XLOOKUP(AD305,'Municipios MG'!$B$2:$B$853,'Municipios MG'!$A$2:$A$853) -> 3133303 | B305: =_xlfn.XLOOKUP(AD305,'Municipios MG'!$B$2:$B$853,'Municipios MG'!$B$2:$B$853) -> Itaobim | C305: =_xlfn.XLOOKUP(AD305,'Municipios MG'!$B$2:$B$853,'Municipios MG'!$C$2:$C$853) -> -16.559526 | D305: =_xlfn.XLOOKUP(AD305,'Municipios MG'!$B$2:$B$853,'Municipios MG'!$D$2:$D$853) -> -41.498977 | E305: =_xlfn.XLOOKUP(A305,Planilha3!$A$2:$A$5543,Planilha3!$C$2:$C$5543) -> - | F305: =_xlfn.XLOOKUP(A305,Planilha3!$A$2:$A$5543,Planilha3!$E$2:$E$5543) -> - | H305: 18.416.446/0001-67 | I305: ATIVO | J305: SINDICATO | K305: SINDICATO DOS TRABALHADORES RURAIS DE ITAOBIM - SINDICATO DOS TRABALHADORES RURAIS DE ITAOBIM/MG | L305: SINDICATO DOS TRABALHADORES RURAIS DE ITAOBIM | M305: 000.000.000.00000-0 | N305: - | O305: - | P305: - | Q305: PRESIDENCIALISMO | R305: 16 | S305: 315 | T305: DIRETA | U305: 1 | V305: 1435 | W305: 317 | X305: RURAL | Y305: TRABALHADORES | Z305: RURAL | AA305: Profissional, dos Trabalhadores Rurais do plano da CONTAG | AB305: 39625-000 | AC305: MG | AD305: ITAOBIM | AE305: CENTRO | AF305: AVENIDA WALTER OLIVEIRA | AG305: 195 | AH305: A | AI305: stritaobim@hotmail.com | AJ305: 33999553161 | AK305: - | AL305: 22/02/2024 | AM305: 21/02/2028 | AN305: MARCELO PEREIRA DE JESUS | AO305: MUNICIPAL | AP305: Minas Gerais: Itaobim
A306: =_xlfn.XLOOKUP(AD306,'Municipios MG'!$B$2:$B$853,'Municipios MG'!$A$2:$A$853) -> 3133402 | B306: =_xlfn.XLOOKUP(AD306,'Municipios MG'!$B$2:$B$853,'Municipios MG'!$B$2:$B$853) -> Itapagipe | C306: =_xlfn.XLOOKUP(AD306,'Municipios MG'!$B$2:$B$853,'Municipios MG'!$C$2:$C$853) -> -19.903296 | D306: =_xlfn.XLOOKUP(AD306,'Municipios MG'!$B$2:$B$853,'Municipios MG'!$D$2:$D$853) -> -49.369821 | E306: =_xlfn.XLOOKUP(A306,Planilha3!$A$2:$A$5543,Planilha3!$C$2:$C$5543) -> - | F306: =_xlfn.XLOOKUP(A306,Planilha3!$A$2:$A$5543,Planilha3!$E$2:$E$5543) -> - | H306: 08.760.085/0001-18 | I306: INATIVO | J306: SINDICATO | K306: Sindicato dos Trabalhadores Rurais de Itapagipe - MG | L306: SINDICATO DOS TRABALHADORES RURAIS DE ITAPAGIPE | M306: 000.000.000.00000-0 | N306: UGT - União Geral dos Trabalhadores | O306: - | P306: - | Q306: PRESIDENCIALISMO | R306: - | S306: - | T306: - | U306: - | V306: 0 | W306: - | X306: RURAL | Y306: TRABALHADORES | Z306: RURAL | AA306: Profissional dos trabalhadores rurais os trabalhadores empregados assalariados em geral, que exercem atividades como trabalhadores, nos seguintes setores, bóia-fria, volantes e diaristas: a) Canavieiro (cortadores, bituqueiros, carregadores, plantadores, preparadores de aceiros); b) Citricultura (plantadores, tratadores, colhedores de frutas e carregadores); c) Cultura Diversificada: (preparadores de terra, semeadores, tratadores, colhedores, carregadores de culturas diversas, inclusive, horticultura, floricultura e fruticultura); d) Granjeiros (criadores de animais de pequeno porte, aves, coelhos, porcos), para abate ou comercialização de seus produtos; e) Pecuários (criadores e tratadores de animais incluindo retireiros, os inseminadores artificiais, aqueles que extraem e congelam sêmen do gado; f) Reflorestamento (Corte de madeira e Resinagem (aqueles que desenvolvem as atividades de reflorestamento incluindo o plantio, o tratamento e o corte de árvore, bem como a extração de sua resina); g) Extrativismo rural (aqueles que desenvolvem atividades de extração vegetal ou animal, os tratoristas, os motoristas rurais, operadores de máquinas, os aplicadores de defensivos agrícolas, os administradores de propriedades rurais. | AB306: 38240-000 | AC306: MG | AD306: Itapagipe | AE306: CENTRO | AF306: Rua 6 | AG306: 740 | AH306: - | AI306: marciobuck@terra.com.br | AJ306: 3434242481 | AK306: - | AL306: 17/10/2009 | AM306: 16/10/2013 | AN306: SANDRO ROBERTO MESQUITA | AO306: MUNICIPAL | AP306: Minas Gerais: Itapagipe
A307: =_xlfn.XLOOKUP(AD307,'Municipios MG'!$B$2:$B$853,'Municipios MG'!$A$2:$A$853) -> 3133808 | B307: =_xlfn.XLOOKUP(AD307,'Municipios MG'!$B$2:$B$853,'Municipios MG'!$B$2:$B$853) -> Itaúna | C307: =_xlfn.XLOOKUP(AD307,'Municipios MG'!$B$2:$B$853,'Municipios MG'!$C$2:$C$853) -> -20.074436 | D307: =_xlfn.XLOOKUP(AD307,'Municipios MG'!$B$2:$B$853,'Municipios MG'!$D$2:$D$853) -> -44.578277 | E307: =_xlfn.XLOOKUP(A307,Planilha3!$A$2:$A$5543,Planilha3!$C$2:$C$5543) -> - | F307: =_xlfn.XLOOKUP(A307,Planilha3!$A$2:$A$5543,Planilha3!$E$2:$E$5543) -> - | H307: 16.814.196/0001-98 | I307: ATIVO | J307: SINDICATO | K307: SINDICATO DOS TRABALHADORES RURAIS DE ITAÚNA E ITATIAIUÇU | L307: SINDICATO DOS TRABALHADORES RURAIS DE ITAUNA E ITATIAIUCU | M307: 000.000.000.00000-0 | N307: CTB - Central dos Trabalhadores e Trabalhadoras do Brasil | O307: Confederação Nacional dos Trabalhadores Rurais Agricultores e Agricultoras Familiares | P307: FETAEMG - Federação dos Trabalhadores na Agricultura do Estado de Minas Gerais | Q307: PRESIDENCIALISMO | R307: 16 | S307: 264 | T307: DECISAO_ASSEMBLEIA | U307: 1 | V307: 6765 | W307: 269 | X307: RURAL | Y307: TRABALHADORES | Z307: RURAL | AA307: Profissional dos Trabalhadores e Trabalhadoras rurais: assalariados e assalariadas rurais, empregados permanentes, safristas e eventuais na agricultura, criação de animais e hortifruticultura; e agricultores e agricultoras que exerçam atividades individualmente ou em regime de economia familiar, na qualidade de pequenos produtores, proprietários até dois módulos rurais, posseiros, assentados, meeiros, parceiros, arrendatários, comodatários e os aposentados(as) rurais. | AB307: 35680-030 | AC307: MG | AD307: Itaúna | AE307: Centro | AF307: Rua Antônio de Matos | AG307: 284 | AH307: Casa | AI307: stritauna@hotmail.com | AJ307: 3732413820 | AK307: - | AL307: 04/06/2023 | AM307: 03/06/2027 | AN307: MARIO SOTERO BORGES | AO307: INTERMUNICIPAL | AP307: Minas Gerais: Itatiaiuçu, Itaúna
A308: =_xlfn.XLOOKUP(AD308,'Municipios MG'!$B$2:$B$853,'Municipios MG'!$A$2:$A$853) -> 3133907 | B308: =_xlfn.XLOOKUP(AD308,'Municipios MG'!$B$2:$B$853,'Municipios MG'!$B$2:$B$853) -> Itaverava | C308: =_xlfn.XLOOKUP(AD308,'Municipios MG'!$B$2:$B$853,'Municipios MG'!$C$2:$C$853) -> -20.674727 | D308: =_xlfn.XLOOKUP(AD308,'Municipios MG'!$B$2:$B$853,'Municipios MG'!$D$2:$D$853) -> -43.604322 | E308: =_xlfn.XLOOKUP(A308,Planilha3!$A$2:$A$5543,Planilha3!$C$2:$C$5543) -> - | F308: =_xlfn.XLOOKUP(A308,Planilha3!$A$2:$A$5543,Planilha3!$E$2:$E$5543) -> - | H308: 20.073.086/0001-90 | I308: ATIVO | J308: SINDICATO | K308: STR Itaverava/MG - Sindicato dos Trabalhadores Rurais de Itaverava/MG | L308: SINDICATO DOS TRABALHADORES RURAIS DE ITAVERAVA | M308: 000.000.000.00000-0 | N308: - | O308: Confederação Nacional dos Trabalhadores Rurais Agricultores e Agricultoras Familiares | P308: FETAEMG - Federação dos Trabalhadores na Agricultura do Estado de Minas Gerais | Q308: PRESIDENCIALISMO | R308: 12 | S308: 110 | T308: DECISAO_ASSEMBLEIA | U308: 1 | V308: 3623 | W308: 113 | X308: RURAL | Y308: TRABALHADORES | Z308: RURAL | AA308: Categoria Profissional dos Trabalhadores Rurais do Plano da CONTAG | AB308: 36440-000 | AC308: MG | AD308: Itaverava | AE308: Centro | AF308: Praça José da Costa Carvalho | AG308: 115 | AH308: casa | AI308: sindtrabalhadoruralitaveravamg@gmail.com | AJ308: 3137571381 | AK308: - | AL308: 26/08/2018 | AM308: 26/08/2022 | AN308: JOAQUIM JESUS DE MARSELHAS | AO308: MUNICIPAL | AP308: Minas Gerais: Itaverava
A309: =_xlfn.XLOOKUP(AD309,'Municipios MG'!$B$2:$B$853,'Municipios MG'!$A$2:$A$853) -> 3134004 | B309: =_xlfn.XLOOKUP(AD309,'Municipios MG'!$B$2:$B$853,'Municipios MG'!$B$2:$B$853) -> Itinga | C309: =_xlfn.XLOOKUP(AD309,'Municipios MG'!$B$2:$B$853,'Municipios MG'!$C$2:$C$853) -> -16.601429 | D309: =_xlfn.XLOOKUP(AD309,'Municipios MG'!$B$2:$B$853,'Municipios MG'!$D$2:$D$853) -> -41.778178 | E309: =_xlfn.XLOOKUP(A309,Planilha3!$A$2:$A$5543,Planilha3!$C$2:$C$5543) -> - | F309: =_xlfn.XLOOKUP(A309,Planilha3!$A$2:$A$5543,Planilha3!$E$2:$E$5543) -> - | H309: 19.629.450/0001-76 | I309: ATIVO | J309: SINDICATO | K309: STR Itinga - STR Itinga - Sindicato dos Trabalhadores Rurais de Itinga | L309: SINDICATO DOS TRABALHADORES RURAIS DE ITINGA | M309: 000.000.000.00000-0 | N309: CTB - Central dos Trabalhadores e Trabalhadoras do Brasil | O309: CONTRAFBRASIL/CUT - CONFEDERACAO NACIONAL DOS TRABALHADORES E TRABALHADORAS NA AGRICULTURA FAMILIAR DO BRASIL | P309: FETAEMG - Federação dos Trabalhadores na Agricultura do Estado de Minas Gerais | Q309: PRESIDENCIALISMO | R309: 13 | S309: 878 | T309: DIRETA | U309: 1 | V309: 4996 | W309: 896 | X309: RURAL | Y309: TRABALHADORES | Z309: RURAL | AA309: Profissional dos Trabalhadores Rurais, do Plano da CONTAG | AB309: 39610-000 | AC309: MG | AD309: Itinga | AE309: CENTRO | AF309: TRAVESSA RIO BRANCO | AG309: 42 | AH309: PRÉDIO | AI309: str.itinga@gmail.com | AJ309: 3337331180 | AK309: - | AL309: 20/08/2022 | AM309: 19/08/2026 | AN309: PAULO CARDOSO DOS SANTOS | AO309: MUNICIPAL | AP309: Minas Gerais: Itinga
A310: =_xlfn.XLOOKUP(AD310,'Municipios MG'!$B$2:$B$853,'Municipios MG'!$A$2:$A$853) -> 3134400 | B310: =_xlfn.XLOOKUP(AD310,'Municipios MG'!$B$2:$B$853,'Municipios MG'!$B$2:$B$853) -> Iturama | C310: =_xlfn.XLOOKUP(AD310,'Municipios MG'!$B$2:$B$853,'Municipios MG'!$C$2:$C$853) -> -19.731948 | D310: =_xlfn.XLOOKUP(AD310,'Municipios MG'!$B$2:$B$853,'Municipios MG'!$D$2:$D$853) -> -50.201974 | E310: =_xlfn.XLOOKUP(A310,Planilha3!$A$2:$A$5543,Planilha3!$C$2:$C$5543) -> - | F310: =_xlfn.XLOOKUP(A310,Planilha3!$A$2:$A$5543,Planilha3!$E$2:$E$5543) -> - | H310: 20.039.178/0001-53 | I310: ATIVO | J310: SINDICATO | K310: STRI - SINDICATO DOS TRABALHADORES RURAIS DE ITURAMA | L310: SINDICATO DOS TRABALHADORES RURAIS DE ITURAMA | M310: 000.000.000.00000-0 | N310: CTB - Central dos Trabalhadores e Trabalhadoras do Brasil | O310: Confederação Nacional dos Trabalhadores Rurais Agricultores e Agricultoras Familiares | P310: FETAEMG - Federação dos Trabalhadores na Agricultura do Estado de Minas Gerais | Q310: PRESIDENCIALISMO | R310: 16 | S310: 145 | T310: DIRETA | U310: 3 | V310: 968 | W310: 350 | X310: RURAL | Y310: TRABALHADORES | Z310: RURAL | AA310: Profissional dos Trabalhadores Rurais, plano da CONTAG | AB310: 38280-000 | AC310: MG | AD310: Iturama | AE310: Jardim America | AF310: Avenida Belo Horizonte | AG310: 2035 | AH310: - | AI310: sindicatodeiturama@hotmail.com | AJ310: 3434110119 | AK310: - | AL310: 06/07/2025 | AM310: 05/07/2029 | AN310: MARCIO DA SILVA SANTOS | AO310: MUNICIPAL | AP310: Minas Gerais: Iturama
A311: =_xlfn.XLOOKUP(AD311,'Municipios MG'!$B$2:$B$853,'Municipios MG'!$A$2:$A$853) -> 3134707 | B311: =_xlfn.XLOOKUP(AD311,'Municipios MG'!$B$2:$B$853,'Municipios MG'!$B$2:$B$853) -> Jacinto | C311: =_xlfn.XLOOKUP(AD311,'Municipios MG'!$B$2:$B$853,'Municipios MG'!$C$2:$C$853) -> -16.141162 | D311: =_xlfn.XLOOKUP(AD311,'Municipios MG'!$B$2:$B$853,'Municipios MG'!$D$2:$D$853) -> -40.291429 | E311: =_xlfn.XLOOKUP(A311,Planilha3!$A$2:$A$5543,Planilha3!$C$2:$C$5543) -> - | F311: =_xlfn.XLOOKUP(A311,Planilha3!$A$2:$A$5543,Planilha3!$E$2:$E$5543) -> - | H311: 19.912.161/0001-80 | I311: ATIVO | J311: SINDICATO | K311: Sindicato dos Trabalhadores Rurais de Jacinto - Sindicato dos Trabalhadores Rurais de Jacinto | L311: SINDICATO DOS TRABALHADORES RURAIS DE JACINTO | M311: 000.000.000.00000-0 | N311: CUT - Central Única dos Trabalhadores | O311: Confederação Nacional dos Trabalhadores Rurais Agricultores e Agricultoras Familiares | P311: FETAEMG - Federação dos Trabalhadores na Agricultura do Estado de Minas Gerais | Q311: PRESIDENCIALISMO | R311: 18 | S311: 644 | T311: DIRETA | U311: 1 | V311: 3188 | W311: 655 | X311: RURAL | Y311: TRABALHADORES | Z311: RURAL | AA311: Profissional, dos Trabalhadores Rurais do Plano da CONTAG | AB311: 39930-000 | AC311: MG | AD311: Jacinto | AE311: centro | AF311: Rua Prefeito antonio Querasma | AG311: 137 | AH311: - | AI311: strjacinto@gmail.com | AJ311: 3337231069 | AK311: - | AL311: 05/12/2022 | AM311: 05/12/2026 | AN311: JOAO ALVES BERBERINO | AO311: MUNICIPAL | AP311: Minas Gerais: Jacinto
A312: =_xlfn.XLOOKUP(AD312,'Municipios MG'!$B$2:$B$853,'Municipios MG'!$A$2:$A$853) -> 3135100 | B312: =_xlfn.XLOOKUP(AD312,'Municipios MG'!$B$2:$B$853,'Municipios MG'!$B$2:$B$853) -> Janaúba | C312: =_xlfn.XLOOKUP(AD312,'Municipios MG'!$B$2:$B$853,'Municipios MG'!$C$2:$C$853) -> -15.799028 | D312: =_xlfn.XLOOKUP(AD312,'Municipios MG'!$B$2:$B$853,'Municipios MG'!$D$2:$D$853) -> -43.307683 | E312: =_xlfn.XLOOKUP(A312,Planilha3!$A$2:$A$5543,Planilha3!$C$2:$C$5543) -> - | F312: =_xlfn.XLOOKUP(A312,Planilha3!$A$2:$A$5543,Planilha3!$E$2:$E$5543) -> - | H312: 11.044.158/0001-80 | I312: INATIVO | J312: SINDICATO | K312: SAFER/Janaúba, MG. - Sindicato dos Agricultores Familiares e Empreendedores Familiares Rurais | L312: SINDICATO DOS AGRICULTORES FAMILIARES E EMPREENDEDORES FAMILIARES RURAIS DE JANAUBA | M312: 000.000.000.00000-0 | N312: CENTRAL DOS SINDICATOS BRASILEIROS - CSB | O312: - | P312: - | Q312: PRESIDENCIALISMO | R312: 12 | S312: 106 | T312: DIRETA | U312: 1 | V312: 2038 | W312: 106 | X312: RURAL | Y312: TRABALHADORES | Z312: RURAL | AA312: Econômica dos Agricultores (as) familiares, Empreendedores rurais familiares, Silvicultores, Aquicultores, Extrativistas e Pescadores. (Lei nº11.326 de 24 de julho de 2006). | AB312: 39440-000 | AC312: MG | AD312: Janaúba | AE312: Padre Eustaqui | AF312: Rua Belo Horizonte | AG312: 347 | AH312: Casa | AI312: safer.sindicato@yahoo.com.br | AJ312: 3838213290 | AK312: - | AL312: 13/07/2013 | AM312: 13/07/2017 | AN312: SONIA JOSE DOS SANTOS | AO312: MUNICIPAL | AP312: Minas Gerais: Janaúba
A313: =_xlfn.XLOOKUP(AD313,'Municipios MG'!$B$2:$B$853,'Municipios MG'!$A$2:$A$853) -> 3135100 | B313: =_xlfn.XLOOKUP(AD313,'Municipios MG'!$B$2:$B$853,'Municipios MG'!$B$2:$B$853) -> Janaúba | C313: =_xlfn.XLOOKUP(AD313,'Municipios MG'!$B$2:$B$853,'Municipios MG'!$C$2:$C$853) -> -15.799028 | D313: =_xlfn.XLOOKUP(AD313,'Municipios MG'!$B$2:$B$853,'Municipios MG'!$D$2:$D$853) -> -43.307683 | E313: =_xlfn.XLOOKUP(A313,Planilha3!$A$2:$A$5543,Planilha3!$C$2:$C$5543) -> - | F313: =_xlfn.XLOOKUP(A313,Planilha3!$A$2:$A$5543,Planilha3!$E$2:$E$5543) -> - | H313: 20.567.640/0001-95 | I313: INATIVO | J313: SINDICATO | K313: STR - JANAUBA - SINDICATO DOS TRABALHADORES RURAIS DE JANAUBA | L313: SINDICATO DOS TRABALHADORES E TRABALHADORAS RURAIS DE JANAUB | M313: 000.000.000.00000-0 | N313: NCST - Nova Central Sindical de Trabalhadores | O313: - | P313: FETAEMG - Federação dos Trabalhadores na Agricultura do Estado de Minas Gerais | Q313: PRESIDENCIALISMO | R313: - | S313: - | T313: - | U313: - | V313: 1356 | W313: - | X313: RURAL | Y313: TRABALHADORES | Z313: RURAL | AA313: Profissional, dos Trabalhadores Rurais do Plano da CONTAG | AB313: 39440-000 | AC313: MG | AD313: Janaúba | AE313: CENTRO | AF313: RUA PIO XII | AG313: 300 | AH313: - | AI313: - | AJ313: 3838211898 | AK313: - | AL313: 14/03/2013 | AM313: 13/03/2017 | AN313: ADIJAR BARBOSA DA FONSECA | AO313: MUNICIPAL | AP313: Minas Gerais: Janaúba
A314: =_xlfn.XLOOKUP(AD314,'Municipios MG'!$B$2:$B$853,'Municipios MG'!$A$2:$A$853) -> 3135308 | B314: =_xlfn.XLOOKUP(AD314,'Municipios MG'!$B$2:$B$853,'Municipios MG'!$B$2:$B$853) -> Japaraíba | C314: =_xlfn.XLOOKUP(AD314,'Municipios MG'!$B$2:$B$853,'Municipios MG'!$C$2:$C$853) -> -20.141618 | D314: =_xlfn.XLOOKUP(AD314,'Municipios MG'!$B$2:$B$853,'Municipios MG'!$D$2:$D$853) -> -45.504118 | E314: =_xlfn.XLOOKUP(A314,Planilha3!$A$2:$A$5543,Planilha3!$C$2:$C$5543) -> - | F314: =_xlfn.XLOOKUP(A314,Planilha3!$A$2:$A$5543,Planilha3!$E$2:$E$5543) -> - | H314: 20.719.332/0001-38 | I314: ATIVO | J314: SINDICATO | K314: STR - Sindicato dos Trabalhadores Rurais de Japaraíba | L314: SINDICATO DOS TRABALHADORES RURAIS DE JAPARAIBA | M314: 000.000.000.00000-0 | N314: - | O314: - | P314: FETAEMG - Federação dos Trabalhadores na Agricultura do Estado de Minas Gerais | Q314: PRESIDENCIALISMO | R314: 17 | S314: 28 | T314: DIRETA | U314: 1 | V314: 1393 | W314: 28 | X314: RURAL | Y314: TRABALHADORES | Z314: RURAL | AA314: Profissional dos Trabalhadores Rurais do Plano da CONTAG | AB314: 35580-000 | AC314: MG | AD314: Japaraíba | AE314: Centro | AF314: Rua Nossa Senhora do Rosário | AG314: 03 | AH314: - | AI314: strjaparaiba@hotmail.com | AJ314: 3733541155 | AK314: - | AL314: 01/01/2023 | AM314: 31/12/2026 | AN314: SEBASTIAO JOSE LOPES | AO314: MUNICIPAL | AP314: Minas Gerais: Japaraíba
A315: =_xlfn.XLOOKUP(AD315,'Municipios MG'!$B$2:$B$853,'Municipios MG'!$A$2:$A$853) -> 3135357 | B315: =_xlfn.XLOOKUP(AD315,'Municipios MG'!$B$2:$B$853,'Municipios MG'!$B$2:$B$853) -> Japonvar | C315: =_xlfn.XLOOKUP(AD315,'Municipios MG'!$B$2:$B$853,'Municipios MG'!$C$2:$C$853) -> -16.000957 | D315: =_xlfn.XLOOKUP(AD315,'Municipios MG'!$B$2:$B$853,'Municipios MG'!$D$2:$D$853) -> -44.276127 | E315: =_xlfn.XLOOKUP(A315,Planilha3!$A$2:$A$5543,Planilha3!$C$2:$C$5543) -> - | F315: =_xlfn.XLOOKUP(A315,Planilha3!$A$2:$A$5543,Planilha3!$E$2:$E$5543) -> - | H315: 02.933.541/0001-06 | I315: ATIVO | J315: SINDICATO | K315: Sindicato dos Trabalhadores Rurais de Japonvar - MG | L315: SINDICATO DOS TRABALHADORES RURAIS DE JAPONVAR | M315: 000.000.000.00000-0 | N315: - | O315: - | P315: - | Q315: PRESIDENCIALISMO | R315: - | S315: - | T315: - | U315: - | V315: - | W315: - | X315: RURAL | Y315: TRABALHADORES | Z315: RURAL | AA315: Trabalhadores Rurais, integrantes do Plano da Confederação Nacional dos Trabalhadores na Agricultura. | AB315: 39335-000 | AC315: MG | AD315: Japonvar | AE315: CENTRO | AF315: RUA MINAS GERAIS | AG315: 121 | AH315: A | AI315: sindicatojaponvar@yahoo.com | AJ315: 3832319209 | AK315: - | AL315: 28/02/2022 | AM315: 27/02/2026 | AN315: RITA DE FATIMA RODRIGUES CORDEIRO | AO315: MUNICIPAL | AP315: Minas Gerais: Japonvar
A316: =_xlfn.XLOOKUP(AD316,'Municipios MG'!$B$2:$B$853,'Municipios MG'!$A$2:$A$853) -> 3135456 | B316: =_xlfn.XLOOKUP(AD316,'Municipios MG'!$B$2:$B$853,'Municipios MG'!$B$2:$B$853) -> Jenipapo de Minas | C316: =_xlfn.XLOOKUP(AD316,'Municipios MG'!$B$2:$B$853,'Municipios MG'!$C$2:$C$853) -> -17.080423 | D316: =_xlfn.XLOOKUP(AD316,'Municipios MG'!$B$2:$B$853,'Municipios MG'!$D$2:$D$853) -> -42.256047 | E316: =_xlfn.XLOOKUP(A316,Planilha3!$A$2:$A$5543,Planilha3!$C$2:$C$5543) -> - | F316: =_xlfn.XLOOKUP(A316,Planilha3!$A$2:$A$5543,Planilha3!$E$2:$E$5543) -> - | H316: 03.353.519/0001-41 | I316: ATIVO | J316: SINDICATO | K316: STR Jenipapo de Minas - Sindicato dos Trabalhadores Rurais de Jenipapo de Minas/MG | L316: SINDICATO DOS TRABALHADORES RURAIS DE JENIPAPO DE MINAS | M316: 000.000.000.00000-0 | N316: - | O316: - | P316: - | Q316: PRESIDENCIALISMO | R316: 16 | S316: 407 | T316: DIRETA | U316: 2 | V316: 1800 | W316: 627 | X316: RURAL | Y316: TRABALHADORES | Z316: RURAL | AA316: Profissional dos Trabalhadores e trabalhadoras rurais: Assalariados e assalariadas rurais, empregados permanentes, safristas e eventuais na agricultura, criação de animais, silvicultura, hortifruticultura e extrativismo rural; e agricultores e agricultoras que exerçam atividades individualmente ou em regime de economia familiar, na qualidade de pequenos agricultores, proprietários, posseiros, assentados, meeiros, parceiros, comodatários e extrativistas | AB316: 39645-000 | AC316: MG | AD316: Jenipapo de Minas | AE316: Centro | AF316: Rua Turmalina | AG316: 1010 | AH316: co | AI316: strjenipapo@hotmail.com | AJ316: 3337389084 | AK316: - | AL316: 01/01/2023 | AM316: 31/12/2026 | AN316: ANTONIO PEREIRA DE AGUILAR | AO316: MUNICIPAL | AP316: Minas Gerais: Jenipapo de Minas
A317: =_xlfn.XLOOKUP(AD317,'Municipios MG'!$B$2:$B$853,'Municipios MG'!$A$2:$A$853) -> 3135605 | B317: =_xlfn.XLOOKUP(AD317,'Municipios MG'!$B$2:$B$853,'Municipios MG'!$B$2:$B$853) -> Jequitaí | C317: =_xlfn.XLOOKUP(AD317,'Municipios MG'!$B$2:$B$853,'Municipios MG'!$C$2:$C$853) -> -17.216373 | D317: =_xlfn.XLOOKUP(AD317,'Municipios MG'!$B$2:$B$853,'Municipios MG'!$D$2:$D$853) -> -44.441687 | E317: =_xlfn.XLOOKUP(A317,Planilha3!$A$2:$A$5543,Planilha3!$C$2:$C$5543) -> - | F317: =_xlfn.XLOOKUP(A317,Planilha3!$A$2:$A$5543,Planilha3!$E$2:$E$5543) -> - | H317: 25.222.407/0001-94 | I317: ATIVO | J317: SINDICATO | K317: Sindicato dos Trabalhadores Rurais de Jequitaí/MG | L317: SIND DOS TRABALHADORES RURAIS DE JEQUITAI | M317: 000.000.000.00000-0 | N317: - | O317: - | P317: - | Q317: PRESIDENCIALISMO | R317: 12 | S317: 162 | T317: DIRETA | U317: 1 | V317: 2357 | W317: 164 | X317: RURAL | Y317: TRABALHADORES | Z317: RURAL | AA317: Profissional dos_x000D_ Trabalhadores e Trabalhadoras Rurais, assalariados e assalariadas rurais, empregados_x000D_ permanentes, safristas e eventuais na agricultura, criação de animais e hortifruticultura;_x000D_ e agricultores e agricultoras que exerçam atividades individualmente ou em regime de_x000D_ economia familiar, na qualidade de pequenos produtores, proprietários até dois módulos_x000D_ rurais, posseiros, assentados, meeiros, parceiros, arrendatários, comodatários e os_x000D_ aposentados (as) rurais. | AB317: 39370-000 | AC317: MG | AD317: Jequitaí | AE317: CENTRO | AF317: RUA JOAO BATISTA FONSECA | AG317: 206 | AH317: CASA | AI317: strjequitai@gmail.com | AJ317: 3837441190 | AK317: - | AL317: 16/12/2023 | AM317: 15/12/2027 | AN317: FERNANDO MENDES PARANHA | AO317: MUNICIPAL | AP317: Minas Gerais: Jequitaí
A318: =_xlfn.XLOOKUP(AD318,'Municipios MG'!$B$2:$B$853,'Municipios MG'!$A$2:$A$853) -> 3136108 | B318: =_xlfn.XLOOKUP(AD318,'Municipios MG'!$B$2:$B$853,'Municipios MG'!$B$2:$B$853) -> Joanésia | C318: =_xlfn.XLOOKUP(AD318,'Municipios MG'!$B$2:$B$853,'Municipios MG'!$C$2:$C$853) -> -19.168696 | D318: =_xlfn.XLOOKUP(AD318,'Municipios MG'!$B$2:$B$853,'Municipios MG'!$D$2:$D$853) -> -42.674702 | E318: =_xlfn.XLOOKUP(A318,Planilha3!$A$2:$A$5543,Planilha3!$C$2:$C$5543) -> - | F318: =_xlfn.XLOOKUP(A318,Planilha3!$A$2:$A$5543,Planilha3!$E$2:$E$5543) -> - | H318: 05.296.705/0001-11 | I318: ATIVO | J318: SINDICATO | K318: STR JOANESIA/MG - SINDICATO DOS TRABALHADORES RURAIS DE JOANESIA/MG | L318: SINDICATO DOS TRABALHADORES RURAIS DE JOANESIA-MG | M318: 000.000.000.00000-0 | N318: - | O318: - | P318: - | Q318: PRESIDENCIALISMO | R318: 17 | S318: 219 | T318: DIRETA | U318: 1 | V318: 4718 | W318: 221 | X318: RURAL | Y318: TRABALHADORES | Z318: RURAL | AA318: Profissional, dos Trabalhadores Rurais do Plano da CONTAG | AB318: 35194-000 | AC318: MG | AD318: Joanésia | AE318: CENTRO | AF318: RUA LABATUT | AG318: 10 | AH318: CASA | AI318: sindicatonesia@hotmail.com | AJ318: 3332521378 | AK318: - | AL318: 25/02/2026 | AM318: 24/02/2030 | AN318: SEBASTIAO DANIEL DE ASSIS | AO318: MUNICIPAL | AP318: Minas Gerais: Joanésia
A319: =_xlfn.XLOOKUP(AD319,'Municipios MG'!$B$2:$B$853,'Municipios MG'!$A$2:$A$853) -> 3136504 | B319: =_xlfn.XLOOKUP(AD319,'Municipios MG'!$B$2:$B$853,'Municipios MG'!$B$2:$B$853) -> Jordânia | C319: =_xlfn.XLOOKUP(AD319,'Municipios MG'!$B$2:$B$853,'Municipios MG'!$C$2:$C$853) -> -15.901065 | D319: =_xlfn.XLOOKUP(AD319,'Municipios MG'!$B$2:$B$853,'Municipios MG'!$D$2:$D$853) -> -40.180014 | E319: =_xlfn.XLOOKUP(A319,Planilha3!$A$2:$A$5543,Planilha3!$C$2:$C$5543) -> - | F319: =_xlfn.XLOOKUP(A319,Planilha3!$A$2:$A$5543,Planilha3!$E$2:$E$5543) -> - | H319: 18.019.067/0001-33 | I319: ATIVO | J319: SINDICATO | K319: STR JORDANIA | L319: SINDICATO DOS TRABALHADORES RURAIS DE JORDANIA | M319: 000.000.000.00000-0 | N319: CTB - Central dos Trabalhadores e Trabalhadoras do Brasil | O319: Confederação Nacional dos Trabalhadores Rurais Agricultores e Agricultoras Familiares | P319: FETAEMG - Federação dos Trabalhadores na Agricultura do Estado de Minas Gerais | Q319: PRESIDENCIALISMO | R319: 16 | S319: 396 | T319: DECISAO_ASSEMBLEIA | U319: 2 | V319: 5607 | W319: 567 | X319: RURAL | Y319: TRABALHADORES | Z319: RURAL | AA319: Profissional, dos Trabalhadores Rurais do Plano da CONTAG | AB319: 39920-000 | AC319: MG | AD319: Jordânia | AE319: CENTRO | AF319: RUA JUVENCIO PINHEIRO | AG319: 234 | AH319: - | AI319: - | AJ319: 3337261383 | AK319: - | AL319: 26/07/2023 | AM319: 25/07/2027 | AN319: TEREZA PEREIRA LIMA | AO319: MUNICIPAL | AP319: Minas Gerais: Jordânia
A320: =_xlfn.XLOOKUP(AD320,'Municipios MG'!$B$2:$B$853,'Municipios MG'!$A$2:$A$853) -> 3136801 | B320: =_xlfn.XLOOKUP(AD320,'Municipios MG'!$B$2:$B$853,'Municipios MG'!$B$2:$B$853) -> Juramento | C320: =_xlfn.XLOOKUP(AD320,'Municipios MG'!$B$2:$B$853,'Municipios MG'!$C$2:$C$853) -> -16.85127 | D320: =_xlfn.XLOOKUP(AD320,'Municipios MG'!$B$2:$B$853,'Municipios MG'!$D$2:$D$853) -> -43.590194 | E320: =_xlfn.XLOOKUP(A320,Planilha3!$A$2:$A$5543,Planilha3!$C$2:$C$5543) -> - | F320: =_xlfn.XLOOKUP(A320,Planilha3!$A$2:$A$5543,Planilha3!$E$2:$E$5543) -> - | H320: 25.214.552/0001-23 | I320: ATIVO | J320: SINDICATO | K320: SINDICATO DOS TRABALHADORES RURAIS DE JURAMENTO/MG | L320: SINDICATO DOS TRABALHADORES RURAIS DE JURAMENTO | M320: 000.000.000.00000-0 | N320: - | O320: - | P320: - | Q320: PRESIDENCIALISMO | R320: 15 | S320: 105 | T320: DECISAO_ASSEMBLEIA | U320: 1 | V320: 236 | W320: 105 | X320: RURAL | Y320: TRABALHADORES | Z320: RURAL | AA320: Profissional dos Trabalhadores e Trabalhadoras Rurais ativos_x000D_ e inativos: assalariados e assalariadas rurais, empregados permanentes, safristas e_x000D_ eventuais na agricultura, criação de animais, hortifruticultura; e agricultores e agricultoras_x000D_ que exerçam atividades individualmente ou em regime de economia familiar, na qualidade_x000D_ de pequenos produtores, proprietários até dois módulos rurais, posseiros, assentados,_x000D_ meeiros, parceiros, arrendatários, comodatários e os aposentados(as) rurais. | AB320: 39590-000 | AC320: MG | AD320: Juramento | AE320: CENTRO | AF320: RUA RAIMUNDO DE CASTRO | AG320: 20 | AH320: A | AI320: juramentomgsindicatorural@yahoo.com.br | AJ320: 3834250488 | AK320: - | AL320: 23/10/2022 | AM320: 23/10/2026 | AN320: ELTON BICALHO MAIA | AO320: MUNICIPAL | AP320: Minas Gerais: Juramento
A321: =_xlfn.XLOOKUP(AD321,'Municipios MG'!$B$2:$B$853,'Municipios MG'!$A$2:$A$853) -> 3137205 | B321: =_xlfn.XLOOKUP(AD321,'Municipios MG'!$B$2:$B$853,'Municipios MG'!$B$2:$B$853) -> Lagoa da Prata | C321: =_xlfn.XLOOKUP(AD321,'Municipios MG'!$B$2:$B$853,'Municipios MG'!$C$2:$C$853) -> -20.023765 | D321: =_xlfn.XLOOKUP(AD321,'Municipios MG'!$B$2:$B$853,'Municipios MG'!$D$2:$D$853) -> -45.541692 | E321: =_xlfn.XLOOKUP(A321,Planilha3!$A$2:$A$5543,Planilha3!$C$2:$C$5543) -> - | F321: =_xlfn.XLOOKUP(A321,Planilha3!$A$2:$A$5543,Planilha3!$E$2:$E$5543) -> - | H321: 20.897.484/0001-20 | I321: ATIVO | J321: SINDICATO | K321: STRs - Sindicato dos Trabalhadores Rurais de Lagoa da Prata | L321: SINDICATO DOS TRABALHADORES RURAIS DE LAGOA DA PRATA | M321: 000.000.000.00000-0 | N321: CUT - Central Única dos Trabalhadores | O321: - | P321: FETAEMG - Federação dos Trabalhadores na Agricultura do Estado de Minas Gerais | Q321: PRESIDENCIALISMO | R321: 10 | S321: 160 | T321: DIRETA | U321: 1 | V321: 221 | W321: 192 | X321: RURAL | Y321: TRABALHADORES | Z321: RURAL | AA321: Profissional dos Trabalhadores Rurais, do Plano da CONTAG | AB321: 35590-000 | AC321: MG | AD321: Lagoa da Prata | AE321: Santa Eugênia | AF321: Rua Alagoas | AG321: 878 | AH321: casa | AI321: sindtrabrural@yahoo.com.br | AJ321: 3732612792 | AK321: - | AL321: 20/07/2025 | AM321: 19/07/2028 | AN321: NELSO RUFINO DE PAULO | AO321: MUNICIPAL | AP321: Minas Gerais: Lagoa da Prata
A322: =_xlfn.XLOOKUP(AD322,'Municipios MG'!$B$2:$B$853,'Municipios MG'!$A$2:$A$853) -> 3138302 | B322: =_xlfn.XLOOKUP(AD322,'Municipios MG'!$B$2:$B$853,'Municipios MG'!$B$2:$B$853) -> Leandro Ferreira | C322: =_xlfn.XLOOKUP(AD322,'Municipios MG'!$B$2:$B$853,'Municipios MG'!$C$2:$C$853) -> -19.719223 | D322: =_xlfn.XLOOKUP(AD322,'Municipios MG'!$B$2:$B$853,'Municipios MG'!$D$2:$D$853) -> -45.026284 | E322: =_xlfn.XLOOKUP(A322,Planilha3!$A$2:$A$5543,Planilha3!$C$2:$C$5543) -> - | F322: =_xlfn.XLOOKUP(A322,Planilha3!$A$2:$A$5543,Planilha3!$E$2:$E$5543) -> - | H322: 17.983.420/0001-38 | I322: INATIVO | J322: SINDICATO | K322: STR Leandro Ferreira/MG - Sindicato dos Trabahadores Rurais de Leandro Ferreira/MG | L322: SINDICATO DOS TRABALHADORES RURAIS DE LEANDRO FERREIRA | M322: 000.000.000.00000-0 | N322: - | O322: Confederação Nacional dos Trabalhadores Rurais Agricultores e Agricultoras Familiares | P322: FETAEMG - Federação dos Trabalhadores na Agricultura do Estado de Minas Gerais | Q322: PRESIDENCIALISMO | R322: - | S322: - | T322: - | U322: - | V322: 85 | W322: - | X322: RURAL | Y322: TRABALHADORES | Z322: RURAL | AA322: Profissional Trabalhadores Rurais, plano da CONTAG | AB322: 35657-000 | AC322: MG | AD322: Leandro Ferreira | AE322: - | AF322: Rua da Pilata | AG322: 174 | AH322: Centro | AI322: maria.odete@fetaemg.org.br | AJ322: 3732771291 | AK322: - | AL322: 09/06/2010 | AM322: 09/06/2013 | AN322: MORILLO VICTOR MARTINS | AO322: MUNICIPAL | AP322: Minas Gerais: Leandro Ferreira
A323: =_xlfn.XLOOKUP(AD323,'Municipios MG'!$B$2:$B$853,'Municipios MG'!$A$2:$A$853) -> 3138609 | B323: =_xlfn.XLOOKUP(AD323,'Municipios MG'!$B$2:$B$853,'Municipios MG'!$B$2:$B$853) -> Lima Duarte | C323: =_xlfn.XLOOKUP(AD323,'Municipios MG'!$B$2:$B$853,'Municipios MG'!$C$2:$C$853) -> -21.841096 | D323: =_xlfn.XLOOKUP(AD323,'Municipios MG'!$B$2:$B$853,'Municipios MG'!$D$2:$D$853) -> -43.796383 | E323: =_xlfn.XLOOKUP(A323,Planilha3!$A$2:$A$5543,Planilha3!$C$2:$C$5543) -> - | F323: =_xlfn.XLOOKUP(A323,Planilha3!$A$2:$A$5543,Planilha3!$E$2:$E$5543) -> - | H323: 17.697.673/0001-45 | I323: ATIVO | J323: SINDICATO | K323: Sindicato dos Trabalhadores Rurais de Lima Duarte, Olaria e Pedro Teixeira | L323: SINDICATO DOS TRABALHADORES E TRABALHADORAS RURAIS DE LIMA D | M323: 000.000.000.00000-0 | N323: CTB - Central dos Trabalhadores e Trabalhadoras do Brasil | O323: Confederação Nacional dos Trabalhadores Rurais Agricultores e Agricultoras Familiares | P323: FETAEMG - Federação dos Trabalhadores na Agricultura do Estado de Minas Gerais | Q323: PRESIDENCIALISMO | R323: 12 | S323: 47 | T323: DIRETA | U323: 1 | V323: 100 | W323: 47 | X323: RURAL | Y323: TRABALHADORES | Z323: RURAL | AA323: Profissional, dos Trabalhadores Rurais do Plano da CONTAG | AB323: 36140-000 | AC323: MG | AD323: Lima Duarte | AE323: CENTRO | AF323: RUA JOSÉ DE SALES | AG323: 47 | AH323: casa | AI323: sttrldpt@gmail.com | AJ323: 3232811244 | AK323: - | AL323: 23/12/2025 | AM323: 22/12/2029 | AN323: GILMARLE EDUARDO CARVALHO DE PAIVA | AO323: INTERMUNICIPAL | AP323: Minas Gerais: Lima Duarte, Olaria, Pedro Teixeira
A324: =_xlfn.XLOOKUP(AD324,'Municipios MG'!$B$2:$B$853,'Municipios MG'!$A$2:$A$853) -> 3138625 | B324: =_xlfn.XLOOKUP(AD324,'Municipios MG'!$B$2:$B$853,'Municipios MG'!$B$2:$B$853) -> Limeira do Oeste | C324: =_xlfn.XLOOKUP(AD324,'Municipios MG'!$B$2:$B$853,'Municipios MG'!$C$2:$C$853) -> -19.547777 | D324: =_xlfn.XLOOKUP(AD324,'Municipios MG'!$B$2:$B$853,'Municipios MG'!$D$2:$D$853) -> -50.57529 | E324: =_xlfn.XLOOKUP(A324,Planilha3!$A$2:$A$5543,Planilha3!$C$2:$C$5543) -> - | F324: =_xlfn.XLOOKUP(A324,Planilha3!$A$2:$A$5543,Planilha3!$E$2:$E$5543) -> - | H324: 00.060.500/0001-19 | I324: ATIVO | J324: SINDICATO | K324: STR - Sindicato dos Trabalhadores Rurais de Limeira do Oeste - MG | L324: SINDICATO DOS TRABALHADORES RURAIS ASSALARIADOS E AGRICULTORES FAMILIARES DE LIMEIRA DO OESTE - MG | M324: 000.000.000.00000-0 | N324: - | O324: - | P324: - | Q324: PRESIDENCIALISMO | R324: 14 | S324: 29 | T324: DIRETA | U324: 1 | V324: 1464 | W324: 58 | X324: RURAL | Y324: TRABALHADORES | Z324: RURAL | AA324: Trabalhadores e Trabalhadoras Rurais: assalariados e assalariadas rurais, permanentes, safristas e eventuais na agricultura, criação de animais, silvicultura, hortifruticultura e extrativismo rural; agricultores e agricultoras que exerçam atividades individualmente ou em regime de economia familiar, na qualidade de pequenos produtores, proprietários, posseiros, assentados, meeiros, parceiros, arrendatários, comodatários e extrativistas. | AB324: 38295-000 | AC324: MG | AD324: Limeira do Oeste | AE324: Jardim Paraiso | AF324: Rua Paraiba | AG324: 632 | AH324: . | AI324: nirley_costa243@hotmail.com | AJ324: 3434531313 | AK324: - | AL324: 04/03/2023 | AM324: 03/03/2027 | AN324: AILTO DE MORAES CAVALCANTE | AO324: MUNICIPAL | AP324: Minas Gerais: Limeira do Oeste
A325: =_xlfn.XLOOKUP(AD325,'Municipios MG'!$B$2:$B$853,'Municipios MG'!$A$2:$A$853) -> 3139102 | B325: =_xlfn.XLOOKUP(AD325,'Municipios MG'!$B$2:$B$853,'Municipios MG'!$B$2:$B$853) -> Madre de Deus de Minas | C325: =_xlfn.XLOOKUP(AD325,'Municipios MG'!$B$2:$B$853,'Municipios MG'!$C$2:$C$853) -> -21.477322 | D325: =_xlfn.XLOOKUP(AD325,'Municipios MG'!$B$2:$B$853,'Municipios MG'!$D$2:$D$853) -> -44.340886 | E325: =_xlfn.XLOOKUP(A325,Planilha3!$A$2:$A$5543,Planilha3!$C$2:$C$5543) -> - | F325: =_xlfn.XLOOKUP(A325,Planilha3!$A$2:$A$5543,Planilha3!$E$2:$E$5543) -> - | H325: 20.418.752/0001-84 | I325: ATIVO | J325: SINDICATO | K325: Sindicato dos Trabalhadores Rurais de Madre de Deus de Minas | L325: SINDICATO DOS TRABALHADORES RURAIS DE MADRE DE DEUS DE MINAS | M325: 000.000.000.00000-0 | N325: CTB - Central dos Trabalhadores e Trabalhadoras do Brasil | O325: Confederação Nacional dos Trabalhadores Rurais Agricultores e Agricultoras Familiares | P325: FETAEMG - Federação dos Trabalhadores na Agricultura do Estado de Minas Gerais | Q325: PRESIDENCIALISMO | R325: 12 | S325: 31 | T325: DECISAO_ASSEMBLEIA | U325: 1 | V325: 1200 | W325: 31 | X325: RURAL | Y325: TRABALHADORES | Z325: RURAL | AA325: Profissional dos Trabalhadores Rurais, do Plano da CONTAG | AB325: 37305-000 | AC325: MG | AD325: Madre de Deus de Minas | AE325: CENTRO | AF325: AVENIDA PRESIDENTE TANCREDO NEVES | AG325: 110 | AH325: - | AI325: - | AJ325: 3233381416 | AK325: - | AL325: 04/03/2022 | AM325: 03/03/2026 | AN325: ANA LUCIA DA SILVA | AO325: MUNICIPAL | AP325: Minas Gerais: Madre de Deus de Minas
A326: =_xlfn.XLOOKUP(AD326,'Municipios MG'!$B$2:$B$853,'Municipios MG'!$A$2:$A$853) -> 3139300 | B326: =_xlfn.XLOOKUP(AD326,'Municipios MG'!$B$2:$B$853,'Municipios MG'!$B$2:$B$853) -> Manga | C326: =_xlfn.XLOOKUP(AD326,'Municipios MG'!$B$2:$B$853,'Municipios MG'!$C$2:$C$853) -> -14.755922 | D326: =_xlfn.XLOOKUP(AD326,'Municipios MG'!$B$2:$B$853,'Municipios MG'!$D$2:$D$853) -> -43.936762 | E326: =_xlfn.XLOOKUP(A326,Planilha3!$A$2:$A$5543,Planilha3!$C$2:$C$5543) -> - | F326: =_xlfn.XLOOKUP(A326,Planilha3!$A$2:$A$5543,Planilha3!$E$2:$E$5543) -> - | H326: 20.538.450/0001-40 | I326: ATIVO | J326: SINDICATO | K326: STR DE MANGA - SINDICATO DOS TRABALHADORES RURAIS DE MANGA | L326: SINDICATO DOS TRABALHADORES RURAIS DE MANGA | M326: 000.000.000.00000-0 | N326: CENTRAL DO BRASIL DEMOCRATICA DE TRABALHADORES - CBDT NACIONAL | O326: - | P326: - | Q326: PRESIDENCIALISMO | R326: 12 | S326: 312 | T326: DECISAO_ASSEMBLEIA | U326: 3 | V326: 5600 | W326: 408 | X326: RURAL | Y326: TRABALHADORES | Z326: RURAL | AA326: Categoria Profissional dos Trabalhadores Rurais do Plano da CONTAG | AB326: 39460-000 | AC326: MG | AD326: Manga | AE326: CENTRO | AF326: RUA SETE DE SETEMBRO | AG326: 32 | AH326: - | AI326: - | AJ326: 3836151288 | AK326: - | AL326: 01/01/2021 | AM326: 31/12/2024 | AN326: ROZANIA RAMOS DE JESUS | AO326: MUNICIPAL | AP326: Minas Gerais: Manga
A327: =_xlfn.XLOOKUP(AD327,'Municipios MG'!$B$2:$B$853,'Municipios MG'!$A$2:$A$853) -> 3140407 | B327: =_xlfn.XLOOKUP(AD327,'Municipios MG'!$B$2:$B$853,'Municipios MG'!$B$2:$B$853) -> Marmelópolis | C327: =_xlfn.XLOOKUP(AD327,'Municipios MG'!$B$2:$B$853,'Municipios MG'!$C$2:$C$853) -> -22.446517 | D327: =_xlfn.XLOOKUP(AD327,'Municipios MG'!$B$2:$B$853,'Municipios MG'!$D$2:$D$853) -> -45.160048 | E327: =_xlfn.XLOOKUP(A327,Planilha3!$A$2:$A$5543,Planilha3!$C$2:$C$5543) -> - | F327: =_xlfn.XLOOKUP(A327,Planilha3!$A$2:$A$5543,Planilha3!$E$2:$E$5543) -> - | H327: 18.617.167/0001-61 | I327: INATIVO | J327: SINDICATO | K327: STR Marmelópolis/MG - Sindicato dos Trabalhadores Rurais de Marmelópolis/MG | L327: SINDICATO DOS TRABALHADORES RURAIS DE MARMELOPOLIS | M327: 000.000.000.00000-0 | N327: - | O327: Confederação Nacional dos Trabalhadores Rurais Agricultores e Agricultoras Familiares | P327: FETAEMG - Federação dos Trabalhadores na Agricultura do Estado de Minas Gerais | Q327: PRESIDENCIALISMO | R327: 12 | S327: 242 | T327: DIRETA | U327: 1 | V327: 310 | W327: 253 | X327: RURAL | Y327: TRABALHADORES | Z327: RURAL | AA327: Profissional, dos Trabalhadores Rurais do Plano da CONTAG | AB327: 37516-000 | AC327: MG | AD327: Marmelópolis | AE327: - | AF327: Rua José Acelino da Silva | AG327: 85 | AH327: Centro | AI327: siatmarmelopolis@yahoo.com.br | AJ327: 3536251233 | AK327: - | AL327: 12/05/2012 | AM327: 12/05/2015 | AN327: NORIVAL ALVES RIBEIRO | AO327: MUNICIPAL | AP327: Minas Gerais: Marmelópolis
A328: =_xlfn.XLOOKUP(AD328,'Municipios MG'!$B$2:$B$853,'Municipios MG'!$A$2:$A$853) -> 3140506 | B328: =_xlfn.XLOOKUP(AD328,'Municipios MG'!$B$2:$B$853,'Municipios MG'!$B$2:$B$853) -> Martinho Campos | C328: =_xlfn.XLOOKUP(AD328,'Municipios MG'!$B$2:$B$853,'Municipios MG'!$C$2:$C$853) -> -19.329742 | D328: =_xlfn.XLOOKUP(AD328,'Municipios MG'!$B$2:$B$853,'Municipios MG'!$D$2:$D$853) -> -45.23865 | E328: =_xlfn.XLOOKUP(A328,Planilha3!$A$2:$A$5543,Planilha3!$C$2:$C$5543) -> - | F328: =_xlfn.XLOOKUP(A328,Planilha3!$A$2:$A$5543,Planilha3!$E$2:$E$5543) -> - | H328: 16.867.079/0001-92 | I328: ATIVO | J328: SINDICATO | K328: STR DE MARTINHO CAMPOS | L328: SINDICATO DOS TRABALHADORES RURAIS DE MARTINHO CAMPOS | M328: 000.000.000.00000-0 | N328: - | O328: Confederação Nacional dos Trabalhadores Rurais Agricultores e Agricultoras Familiares | P328: FETAEMG - Federação dos Trabalhadores na Agricultura do Estado de Minas Gerais | Q328: PRESIDENCIALISMO | R328: 15 | S328: 46 | T328: DECISAO_ASSEMBLEIA | U328: 1 | V328: 1652 | W328: 46 | X328: RURAL | Y328: TRABALHADORES | Z328: RURAL | AA328: Profissional dos Trabalhadores Rurais, plano da CONTAG | AB328: 35606-000 | AC328: MG | AD328: Martinho Campos | AE328: CENTRO | AF328: RUA PADRE MARINHO | AG328: 883 | AH328: - | AI328: - | AJ328: 3735241157 | AK328: - | AL328: 14/09/2019 | AM328: 14/09/2023 | AN328: ANTONIO DA COSTA CORREA | AO328: MUNICIPAL | AP328: Minas Gerais: Martinho Campos
A329: =_xlfn.XLOOKUP(AD329,'Municipios MG'!$B$2:$B$853,'Municipios MG'!$A$2:$A$853) -> 3141009 | B329: =_xlfn.XLOOKUP(AD329,'Municipios MG'!$B$2:$B$853,'Municipios MG'!$B$2:$B$853) -> Mato Verde | C329: =_xlfn.XLOOKUP(AD329,'Municipios MG'!$B$2:$B$853,'Municipios MG'!$C$2:$C$853) -> -15.397322 | D329: =_xlfn.XLOOKUP(AD329,'Municipios MG'!$B$2:$B$853,'Municipios MG'!$D$2:$D$853) -> -42.866515 | E329: =_xlfn.XLOOKUP(A329,Planilha3!$A$2:$A$5543,Planilha3!$C$2:$C$5543) -> - | F329: =_xlfn.XLOOKUP(A329,Planilha3!$A$2:$A$5543,Planilha3!$E$2:$E$5543) -> - | H329: 18.650.895/0001-75 | I329: ATIVO | J329: SINDICATO | K329: STR MATO VERDE - SINDICATO DOS TRABALHADORES RURAIS DE MATO VERDE | L329: SINDICATO DOS TRABALHADORES RURAIS DE MATO VERDE MG E CATUTI | M329: 000.000.000.00000-0 | N329: - | O329: - | P329: - | Q329: PRESIDENCIALISMO | R329: 12 | S329: 932 | T329: DECISAO_ASSEMBLEIA | U329: 1 | V329: 7082 | W329: 943 | X329: RURAL | Y329: TRABALHADORES | Z329: RURAL | AA329: Profissional, dos Trabalhadores Rurais do Plano da CONTAG | AB329: 39527-000 | AC329: MG | AD329: Mato Verde | AE329: SAO BENTO | AF329: RUA ANTONIO SILVEIRA COSTA | AG329: 190 | AH329: CASA | AI329: strmatoverde@yahoo.com.br | AJ329: 3838131365 | AK329: - | AL329: 29/09/2017 | AM329: 29/09/2021 | AN329: NAILTON ALVES | AO329: MUNICIPAL | AP329: Minas Gerais: Mato Verde
A330: =_xlfn.XLOOKUP(AD330,'Municipios MG'!$B$2:$B$853,'Municipios MG'!$A$2:$A$853) -> 3141504 | B330: =_xlfn.XLOOKUP(AD330,'Municipios MG'!$B$2:$B$853,'Municipios MG'!$B$2:$B$853) -> Mendes Pimentel | C330: =_xlfn.XLOOKUP(AD330,'Municipios MG'!$B$2:$B$853,'Municipios MG'!$C$2:$C$853) -> -18.661778 | D330: =_xlfn.XLOOKUP(AD330,'Municipios MG'!$B$2:$B$853,'Municipios MG'!$D$2:$D$853) -> -41.405615 | E330: =_xlfn.XLOOKUP(A330,Planilha3!$A$2:$A$5543,Planilha3!$C$2:$C$5543) -> - | F330: =_xlfn.XLOOKUP(A330,Planilha3!$A$2:$A$5543,Planilha3!$E$2:$E$5543) -> - | H330: 18.505.305/0001-10 | I330: ATIVO | J330: SINDICATO | K330: STR - SINDICATO DOS TRABALHADORES RURAIS DE MENDES PIMENTEL | L330: SINDICATO DOS TRABALHADORES RURAIS DE MENDES PIMENTEL | M330: 000.000.000.00000-0 | N330: CENTRAL DO BRASIL DEMOCRATICA DE TRABALHADORES - CBDT NACIONAL | O330: Confederação Nacional dos Trabalhadores Rurais Agricultores e Agricultoras Familiares | P330: FETAEMG - Federação dos Trabalhadores na Agricultura do Estado de Minas Gerais | Q330: PRESIDENCIALISMO | R330: 14 | S330: 562 | T330: DIRETA | U330: 2 | V330: 6075 | W330: 619 | X330: RURAL | Y330: TRABALHADORES | Z330: RURAL | AA330: Profissional dos Trabalhadores Rurais, do Plano da CONTAG | AB330: 35270-000 | AC330: MG | AD330: Mendes Pimentel | AE330: CENTRO | AF330: RUA JOSE ISIDORO DA CUNHA | AG330: 03 | AH330: - | AI330: sindmendes@hotmail.com | AJ330: 3332461295 | AK330: - | AL330: 01/11/2025 | AM330: 31/10/2029 | AN330: CLAUDENICE TEIXEIRA APOLONIA | AO330: MUNICIPAL | AP330: Minas Gerais: Mendes Pimentel
A331: =_xlfn.XLOOKUP(AD331,'Municipios MG'!$B$2:$B$853,'Municipios MG'!$A$2:$A$853) -> 3141702 | B331: =_xlfn.XLOOKUP(AD331,'Municipios MG'!$B$2:$B$853,'Municipios MG'!$B$2:$B$853) -> Mesquita | C331: =_xlfn.XLOOKUP(AD331,'Municipios MG'!$B$2:$B$853,'Municipios MG'!$C$2:$C$853) -> -19.224346 | D331: =_xlfn.XLOOKUP(AD331,'Municipios MG'!$B$2:$B$853,'Municipios MG'!$D$2:$D$853) -> -42.605661 | E331: =_xlfn.XLOOKUP(A331,Planilha3!$A$2:$A$5543,Planilha3!$C$2:$C$5543) -> - | F331: =_xlfn.XLOOKUP(A331,Planilha3!$A$2:$A$5543,Planilha3!$E$2:$E$5543) -> - | H331: 17.990.169/0001-39 | I331: ATIVO | J331: SINDICATO | K331: STRMESQUITA - SIND DOS TRAB RURAIS, ASSAL E AGRIC FAM DE MESQUITA | L331: SINDICATO DOS TRABALHADORES RURAIS ASSALARIADOS E AGRICULTOR | M331: 000.000.000.00000-0 | N331: - | O331: Confederação Nacional dos Trabalhadores Rurais Agricultores e Agricultoras Familiares | P331: FETAEMG - Federação dos Trabalhadores na Agricultura do Estado de Minas Gerais | Q331: PRESIDENCIALISMO | R331: 16 | S331: 325 | T331: DIRETA | U331: 2 | V331: 4702 | W331: 488 | X331: RURAL | Y331: TRABALHADORES | Z331: RURAL | AA331: Profissional, dos Trabalhadores Rurais do Plano da CONTAG | AB331: 35116-000 | AC331: MG | AD331: Mesquita | AE331: CENTRO | AF331: PRAÇA DR. CRISTIANO MACHADO | AG331: 12 | AH331: A | AI331: strmesq@terra.com.br | AJ331: 3332511336 | AK331: - | AL331: 25/05/2023 | AM331: 25/05/2027 | AN331: MARIA TEREZINHA ROSA DOS SANTOS | AO331: MUNICIPAL | AP331: Minas Gerais: Mesquita
A332: =_xlfn.XLOOKUP(AD332,'Municipios MG'!$B$2:$B$853,'Municipios MG'!$A$2:$A$853) -> 3142007 | B332: =_xlfn.XLOOKUP(AD332,'Municipios MG'!$B$2:$B$853,'Municipios MG'!$B$2:$B$853) -> Mirabela | C332: =_xlfn.XLOOKUP(AD332,'Municipios MG'!$B$2:$B$853,'Municipios MG'!$C$2:$C$853) -> -16.258453 | D332: =_xlfn.XLOOKUP(AD332,'Municipios MG'!$B$2:$B$853,'Municipios MG'!$D$2:$D$853) -> -44.160644 | E332: =_xlfn.XLOOKUP(A332,Planilha3!$A$2:$A$5543,Planilha3!$C$2:$C$5543) -> - | F332: =_xlfn.XLOOKUP(A332,Planilha3!$A$2:$A$5543,Planilha3!$E$2:$E$5543) -> - | H332: 25.214.818/0001-38 | I332: ATIVO | J332: SINDICATO | K332: STR de Mirabela/MG - Sindicato dos Trabalhadores Rurais de Mirabela/MG | L332: SINDICATO DOS TRABALHADORES RURAIS DE MIRABELA | M332: 000.000.000.00000-0 | N332: - | O332: Confederação Nacional dos Trabalhadores Rurais Agricultores e Agricultoras Familiares | P332: FETAEMG - Federação dos Trabalhadores na Agricultura do Estado de Minas Gerais | Q332: PRESIDENCIALISMO | R332: 12 | S332: 250 | T332: DIRETA | U332: 1 | V332: 4376 | W332: 251 | X332: RURAL | Y332: TRABALHADORES | Z332: RURAL | AA332: Trabalhadores Rurais | AB332: 39373-000 | AC332: MG | AD332: Mirabela | AE332: CENTRO | AF332: RUA CAPITAO LUIZ RIBEIRO | AG332: 673 | AH332: A | AI332: strmirabela@gmail.com | AJ332: 3832391286 | AK332: - | AL332: 14/12/2024 | AM332: 13/12/2028 | AN332: JOSE VANDERLI MENDES PEREIRA | AO332: MUNICIPAL | AP332: Minas Gerais: Mirabela
A333: =_xlfn.XLOOKUP(AD333,'Municipios MG'!$B$2:$B$853,'Municipios MG'!$A$2:$A$853) -> 3142700 | B333: =_xlfn.XLOOKUP(AD333,'Municipios MG'!$B$2:$B$853,'Municipios MG'!$B$2:$B$853) -> Montalvânia | C333: =_xlfn.XLOOKUP(AD333,'Municipios MG'!$B$2:$B$853,'Municipios MG'!$C$2:$C$853) -> -14.420365 | D333: =_xlfn.XLOOKUP(AD333,'Municipios MG'!$B$2:$B$853,'Municipios MG'!$D$2:$D$853) -> -44.363621 | E333: =_xlfn.XLOOKUP(A333,Planilha3!$A$2:$A$5543,Planilha3!$C$2:$C$5543) -> - | F333: =_xlfn.XLOOKUP(A333,Planilha3!$A$2:$A$5543,Planilha3!$E$2:$E$5543) -> - | H333: 86.813.417/0001-99 | I333: ATIVO | J333: SINDICATO | K333: STR MONTALVANIA MG - SINDICATO DOS TRABALHADORES RURAIS DE MONTALVANIA/MG | L333: SINDICATO DOS TRABALHADORES RURAIS DE MONTALVANIA | M333: 000.000.000.00000-0 | N333: - | O333: - | P333: - | Q333: PRESIDENCIALISMO | R333: 14 | S333: 380 | T333: DIRETA | U333: 2 | V333: 9857 | W333: 702 | X333: RURAL | Y333: TRABALHADORES | Z333: RURAL | AA333: Profissional, dos Trabalhadores Rurais do Plano da CONTAG | AB333: 39495-000 | AC333: MG | AD333: Montalvânia | AE333: CENTRO | AF333: RUA DANTE | AG333: 177 | AH333: CASA | AI333: strmtvmg@yahoo.com.br | AJ333: 3836141515 | AK333: - | AL333: 15/01/2024 | AM333: 14/01/2028 | AN333: RICARDO PEREIRA LEITE | AO333: MUNICIPAL | AP333: Minas Gerais: Montalvânia
A334: =_xlfn.XLOOKUP(AD334,'Municipios MG'!$B$2:$B$853,'Municipios MG'!$A$2:$A$853) -> 3143302 | B334: =_xlfn.XLOOKUP(AD334,'Municipios MG'!$B$2:$B$853,'Municipios MG'!$B$2:$B$853) -> Montes Claros | C334: =_xlfn.XLOOKUP(AD334,'Municipios MG'!$B$2:$B$853,'Municipios MG'!$C$2:$C$853) -> -16.722707 | D334: =_xlfn.XLOOKUP(AD334,'Municipios MG'!$B$2:$B$853,'Municipios MG'!$D$2:$D$853) -> -43.865422 | E334: =_xlfn.XLOOKUP(A334,Planilha3!$A$2:$A$5543,Planilha3!$C$2:$C$5543) -> - | F334: =_xlfn.XLOOKUP(A334,Planilha3!$A$2:$A$5543,Planilha3!$E$2:$E$5543) -> - | H334: 11.809.730/0001-54 | I334: INATIVO | J334: SINDICATO | K334: SAFER/Montes Claros - Sindicato dos Agricultores Familiares e Empreendedores Familiares Rurais de Montes Claros e Região - MG | L334: SINDICATO DOS AGRICULTORES FAMILIARES E EMPREENDEDORES FAMILIARES RURAIS DE MONTES CLAROS-MG E REGIAO | M334: 000.000.000.00000-0 | N334: - | O334: - | P334: - | Q334: PRESIDENCIALISMO | R334: 9 | S334: 32 | T334: DIRETA | U334: 1 | V334: 128 | W334: 32 | X334: RURAL | Y334: TRABALHADORES | Z334: RURAL | AA334: Categoria dos_x000D_ agricultores familiares, que exercem atividades na agricultura como_x000D_ proprietário (as), arrendatários (as), comodatários (as), parceiros_x000D_ (as), meeiros (as), posseiros (as), acampados (as), que desenvolvem_x000D_ suas atividades de forma individual ou coletiva com os membros da_x000D_ família, numa área de até 2 módulos rurais, conforme dispõe o_x000D_ Decreto-Lei 1.166 de 15 de abril de 1971 | AB334: 39400-058 | AC334: MG | AD334: Montes Claros | AE334: Centro | AF334: Rua Dom Pedro II | AG334: 757 | AH334: casa | AI334: safermontesclaros@outlook.com | AJ334: 3830824795 | AK334: - | AL334: 09/03/2018 | AM334: 09/03/2022 | AN334: NILTON DE QUADROS COSTA | AO334: INTERMUNICIPAL | AP334: Minas Gerais: Bocaiúva, Brasília de Minas, Claro dos Poções, Coração de Jesus, Engenheiro Navarro, Francisco Dumont, Francisco Sá, Glaucilândia, Guaraciama, Juramento, Mirabela, Montes Claros, Olhos-d'Água, Patis
... A336: =_xlfn.XLOOKUP(AD336,'Municipios MG'!$B$2:$B$853,'Municipios MG'!$A$2:$A$853) -> 3143708 | B336: =_xlfn.XLOOKUP(AD336,'Municipios MG'!$B$2:$B$853,'Municipios MG'!$B$2:$B$853) -> Morro do Pilar | C336: =_xlfn.XLOOKUP(AD336,'Municipios MG'!$B$2:$B$853,'Municipios MG'!$C$2:$C$853) -> -19.218342 | D336: =_xlfn.XLOOKUP(AD336,'Municipios MG'!$B$2:$B$853,'Municipios MG'!$D$2:$D$853) -> -43.374804 | E336: =_xlfn.XLOOKUP(A336,Planilha3!$A$2:$A$5543,Planilha3!$C$2:$C$5543) -> - | F336: =_xlfn.XLOOKUP(A336,Planilha3!$A$2:$A$5543,Planilha3!$E$2:$E$5543) -> - | H336: 21.015.706/0001-05 | I336: INATIVO | J336: SINDICATO | K336: STR Morro do Pilar/MG - Sindicato dos Trabalhadores Rurais de Morro do Pilar/MG | L336: SINDICATO DOS TRABALHADORES RURAIS DE MORRO DO PILAR | M336: 000.000.000.00000-0 | N336: CTB - Central dos Trabalhadores e Trabalhadoras do Brasil | O336: Confederação Nacional dos Trabalhadores Rurais Agricultores e Agricultoras Familiares | P336: FETAEMG - Federação dos Trabalhadores na Agricultura do Estado de Minas Gerais | Q336: PRESIDENCIALISMO | R336: 12 | S336: 135 | T336: DIRETA | U336: 1 | V336: 299 | W336: 141 | X336: RURAL | Y336: TRABALHADORES | Z336: RURAL | AA336: Profissional, dos Trabalhadores Rurais do Plano da CONTAG | AB336: 35875-000 | AC336: MG | AD336: Morro do Pilar | AE336: - | AF336: Rua Nossa Senhora do Pilar | AG336: 559 | AH336: Centro | AI336: moradamy@hotmail.com | AJ336: 3138665449 | AK336: - | AL336: 19/06/2011 | AM336: 19/06/2015 | AN336: BENEDITO FERREIRA DA SILVA | AO336: MUNICIPAL | AP336: Minas Gerais: Morro do Pilar
A337: =_xlfn.XLOOKUP(AD337,'Municipios MG'!$B$2:$B$853,'Municipios MG'!$A$2:$A$853) -> 3144300 | B337: =_xlfn.XLOOKUP(AD337,'Municipios MG'!$B$2:$B$853,'Municipios MG'!$B$2:$B$853) -> Nanuque | C337: =_xlfn.XLOOKUP(AD337,'Municipios MG'!$B$2:$B$853,'Municipios MG'!$C$2:$C$853) -> -17.838993 | D337: =_xlfn.XLOOKUP(AD337,'Municipios MG'!$B$2:$B$853,'Municipios MG'!$D$2:$D$853) -> -40.351739 | E337: =_xlfn.XLOOKUP(A337,Planilha3!$A$2:$A$5543,Planilha3!$C$2:$C$5543) -> - | F337: =_xlfn.XLOOKUP(A337,Planilha3!$A$2:$A$5543,Planilha3!$E$2:$E$5543) -> - | H337: 22.054.076/0001-32 | I337: INATIVO | J337: SINDICATO | K337: S.T.R. NANUQUE - Sindicato dos Trabalhadores Rurais de Nanuque | L337: SINDICATO DOS TRABALHADORES RURAIS DE NANUQUE MG | M337: 000.000.000.00000-0 | N337: - | O337: Confederação Nacional dos Trabalhadores Rurais Agricultores e Agricultoras Familiares | P337: FETAEMG - Federação dos Trabalhadores na Agricultura do Estado de Minas Gerais | Q337: PRESIDENCIALISMO | R337: - | S337: - | T337: - | U337: - | V337: 0 | W337: - | X337: RURAL | Y337: TRABALHADORES | Z337: RURAL | AA337: Rural Econômica dos Trabalhadores Rurais, plano da CNA | AB337: 39860-000 | AC337: MG | AD337: Nanuque | AE337: Centro | AF337: Rua: Minas Novas | AG337: 203 | AH337: - | AI337: strnanuque@hotmail.com | AJ337: 3336215950 | AK337: - | AL337: 01/01/2006 | AM337: 01/01/2009 | AN337: JUVENAL OLIVEIRA DOS SANTOS | AO337: MUNICIPAL | AP337: Minas Gerais: Nanuque
A338: =_xlfn.XLOOKUP(AD338,'Municipios MG'!$B$2:$B$853,'Municipios MG'!$A$2:$A$853) -> 3145059 | B338: =_xlfn.XLOOKUP(AD338,'Municipios MG'!$B$2:$B$853,'Municipios MG'!$B$2:$B$853) -> Nova Porteirinha | C338: =_xlfn.XLOOKUP(AD338,'Municipios MG'!$B$2:$B$853,'Municipios MG'!$C$2:$C$853) -> -15.80221 | D338: =_xlfn.XLOOKUP(AD338,'Municipios MG'!$B$2:$B$853,'Municipios MG'!$D$2:$D$853) -> -43.302551 | E338: =_xlfn.XLOOKUP(A338,Planilha3!$A$2:$A$5543,Planilha3!$C$2:$C$5543) -> - | F338: =_xlfn.XLOOKUP(A338,Planilha3!$A$2:$A$5543,Planilha3!$E$2:$E$5543) -> - | H338: 07.201.671/0001-60 | I338: ATIVO | J338: SINDICATO | K338: Sindicato dos Trabalhadores e Trabalhadoras Rurais de Nova Porteirinha/MG | L338: SINDICATO DOS TRABALHADORES E TRABALHADORAS RURAIS DO MUNICIPIO DE NOVA PORTEIRINHA-MG | M338: 000.000.000.00000-0 | N338: - | O338: - | P338: - | Q338: PRESIDENCIALISMO | R338: 11 | S338: 11 | T338: DIRETA | U338: 1 | V338: 11 | W338: 11 | X338: RURAL | Y338: TRABALHADORES | Z338: RURAL | AA338: Profissional dos Trabalhadores e_x000D_ Trabalhadoras rurais ativos e inativos: assalariados e assalariadas rurais, empregados_x000D_ permanentes, safristas e eventuais na agricultura, criação de animais, hortifruticultura e_x000D_ agricultores e agricultoras que exerçam atividades individualmente ou em regime de_x000D_ economia familiar, na qualidade de pequenos produtores, proprietários até dois módulos_x000D_ rurais, posseiros, assentados, meeiros, parceiros, arrendatários, comodatários e os_x000D_ aposentados(as) rurais. | AB338: 39525-000 | AC338: MG | AD338: Nova Porteirinha | AE338: CENTRO | AF338: RUA TANCREDO NEVES | AG338: 210 | AH338: A | AI338: strnovap@bol.com.br | AJ338: 3838341265 | AK338: - | AL338: 29/08/2019 | AM338: 28/08/2023 | AN338: MARCIA DANUBIA DE SOUZA | AO338: MUNICIPAL | AP338: Minas Gerais: Nova Porteirinha
A339: =_xlfn.XLOOKUP(AD339,'Municipios MG'!$B$2:$B$853,'Municipios MG'!$A$2:$A$853) -> 3145356 | B339: =_xlfn.XLOOKUP(AD339,'Municipios MG'!$B$2:$B$853,'Municipios MG'!$B$2:$B$853) -> Novo Oriente de Minas | C339: =_xlfn.XLOOKUP(AD339,'Municipios MG'!$B$2:$B$853,'Municipios MG'!$C$2:$C$853) -> -17.409166 | D339: =_xlfn.XLOOKUP(AD339,'Municipios MG'!$B$2:$B$853,'Municipios MG'!$D$2:$D$853) -> -41.222097 | E339: =_xlfn.XLOOKUP(A339,Planilha3!$A$2:$A$5543,Planilha3!$C$2:$C$5543) -> - | F339: =_xlfn.XLOOKUP(A339,Planilha3!$A$2:$A$5543,Planilha3!$E$2:$E$5543) -> - | H339: 02.877.436/0001-99 | I339: ATIVO | J339: SINDICATO | K339: STR NOVO ORIENTE DE MINAS - SINDICATO DOS TRABALHADORES RURAIS DE NOVO ORIENTE DE MINAS/MG | L339: SINDICATO DOS TRABALHADORES RURAIS DE NOVO ORIENTE DE MINAS | M339: 000.000.000.00000-0 | N339: CTB - Central dos Trabalhadores e Trabalhadoras do Brasil | O339: Confederação Nacional dos Trabalhadores Rurais Agricultores e Agricultoras Familiares | P339: FETAEMG - Federação dos Trabalhadores na Agricultura do Estado de Minas Gerais | Q339: PRESIDENCIALISMO | R339: 20 | S339: 327 | T339: DECISAO_ASSEMBLEIA | U339: 1 | V339: 2342 | W339: 327 | X339: RURAL | Y339: TRABALHADORES | Z339: RURAL | AA339: Trabalhadores e Trabalhadoras Rurais ativos e inativos: assalariados e assalariadas rurais, empregados permanentes, safristas e eventuais na agricultura, criação de animais, hortifruticultura; e agricultores e agricultoras que exerçam atividades individualmente ou em regime de economia familiar, na qualidade de pequenos produtores, proprietários até dois módulos rurais, posseiros, assentados, meeiros, parceiros, arrendatários, comodatários e os aposentados(as) rurais | AB339: 39817-000 | AC339: MG | AD339: Novo Oriente de Minas | AE339: CENTRO | AF339: RUA VINTE E UM DE ABRIL | AG339: 330 | AH339: CASA | AI339: sttrnovoriente@hotmail.com | AJ339: 3335328457 | AK339: - | AL339: 21/03/2023 | AM339: 21/03/2027 | AN339: AMILTON BERNARDINO TEIXEIRA | AO339: MUNICIPAL | AP339: Minas Gerais: Novo Oriente de Minas
A340: =_xlfn.XLOOKUP(AD340,'Municipios MG'!$B$2:$B$853,'Municipios MG'!$A$2:$A$853) -> 3145851 | B340: =_xlfn.XLOOKUP(AD340,'Municipios MG'!$B$2:$B$853,'Municipios MG'!$B$2:$B$853) -> Oratórios | C340: =_xlfn.XLOOKUP(AD340,'Municipios MG'!$B$2:$B$853,'Municipios MG'!$C$2:$C$853) -> -20.430996 | D340: =_xlfn.XLOOKUP(AD340,'Municipios MG'!$B$2:$B$853,'Municipios MG'!$D$2:$D$853) -> -42.806339 | E340: =_xlfn.XLOOKUP(A340,Planilha3!$A$2:$A$5543,Planilha3!$C$2:$C$5543) -> - | F340: =_xlfn.XLOOKUP(A340,Planilha3!$A$2:$A$5543,Planilha3!$E$2:$E$5543) -> - | H340: 05.957.784/0001-64 | I340: ATIVO | J340: SINDICATO | K340: Sindicato dos Trabalhadores e Trabalhadoras Rurais de Oratórios/MG | L340: SINDICATO DOS TRABALHADORES E TRABALHADORAS RURAIS DE ORATORIOS - MG | M340: 000.000.000.00000-0 | N340: - | O340: - | P340: - | Q340: PRESIDENCIALISMO | R340: 15 | S340: 134 | T340: DECISAO_ASSEMBLEIA | U340: 1 | V340: 930 | W340: 143 | X340: RURAL | Y340: TRABALHADORES | Z340: RURAL | AA340: Profissional dos Trabalhadores e Trabalhadoras Rurais ativos e inativos: assalariados e_x000D_ assalariadas rurais, empregados permanentes, safristas e eventuais na agricultura, criação_x000D_ de animais e hortifruticultura; e agricultores e agricultoras que exerçam atividades_x000D_ individualmente ou em regime de economia familiar, na qualidade de pequenos_x000D_ produtores, proprietários até dois módulos rurais, posseiros, assentados, meeiros,_x000D_ parceiros, arrendatários, comodatários e os aposentados(as) rurais. | AB340: 35439-000 | AC340: MG | AD340: Oratórios | AE340: CENTRO | AF340: RUA ANHANGA | AG340: 153 | AH340: CASA | AI340: stroratorios@gmail.com | AJ340: 3138769410 | AK340: - | AL340: 20/12/2021 | AM340: 20/12/2025 | AN340: VICENTE AMARO MARTINS | AO340: MUNICIPAL | AP340: Minas Gerais: Oratórios
A341: =_xlfn.XLOOKUP(AD341,'Municipios MG'!$B$2:$B$853,'Municipios MG'!$A$2:$A$853) -> 3146552 | B341: =_xlfn.XLOOKUP(AD341,'Municipios MG'!$B$2:$B$853,'Municipios MG'!$B$2:$B$853) -> Pai Pedro | C341: =_xlfn.XLOOKUP(AD341,'Municipios MG'!$B$2:$B$853,'Municipios MG'!$C$2:$C$853) -> -15.537066 | D341: =_xlfn.XLOOKUP(AD341,'Municipios MG'!$B$2:$B$853,'Municipios MG'!$D$2:$D$853) -> -43.070556 | E341: =_xlfn.XLOOKUP(A341,Planilha3!$A$2:$A$5543,Planilha3!$C$2:$C$5543) -> - | F341: =_xlfn.XLOOKUP(A341,Planilha3!$A$2:$A$5543,Planilha3!$E$2:$E$5543) -> - | H341: 06.086.172/0001-06 | I341: ATIVO | J341: SINDICATO | K341: STR Pai Pedro/MG - Sindicato dos Trabalhadores Rurais de Pai Pedro/MG | L341: SINDICATO DOS TRABALHADORES E TRABALHADORAS RURAIS DE PAI PEDRO | M341: 000.000.000.00000-0 | N341: - | O341: Confederação Nacional dos Trabalhadores Rurais Agricultores e Agricultoras Familiares | P341: FETAEMG - Federação dos Trabalhadores na Agricultura do Estado de Minas Gerais | Q341: PRESIDENCIALISMO | R341: 15 | S341: 455 | T341: DECISAO_ASSEMBLEIA | U341: 1 | V341: 2379 | W341: 463 | X341: RURAL | Y341: TRABALHADORES | Z341: RURAL | AA341: Trabalhadores Rurais | AB341: 39517-000 | AC341: MG | AD341: Pai Pedro | AE341: - | AF341: Av. Salinas | AG341: 65 | AH341: Centro | AI341: str.paipedro@gmail.com | AJ341: 3838318148 | AK341: - | AL341: 01/12/2022 | AM341: 30/11/2026 | AN341: NELSON HOMERO DE OLIVEIRA | AO341: MUNICIPAL | AP341: Minas Gerais: Pai Pedro
A342: =_xlfn.XLOOKUP(AD342,'Municipios MG'!$B$2:$B$853,'Municipios MG'!$A$2:$A$853) -> 3146503 | B342: =_xlfn.XLOOKUP(AD342,'Municipios MG'!$B$2:$B$853,'Municipios MG'!$B$2:$B$853) -> Pains | C342: =_xlfn.XLOOKUP(AD342,'Municipios MG'!$B$2:$B$853,'Municipios MG'!$C$2:$C$853) -> -20.370917 | D342: =_xlfn.XLOOKUP(AD342,'Municipios MG'!$B$2:$B$853,'Municipios MG'!$D$2:$D$853) -> -45.660813 | E342: =_xlfn.XLOOKUP(A342,Planilha3!$A$2:$A$5543,Planilha3!$C$2:$C$5543) -> - | F342: =_xlfn.XLOOKUP(A342,Planilha3!$A$2:$A$5543,Planilha3!$E$2:$E$5543) -> - | H342: 16.785.958/0001-75 | I342: ATIVO | J342: SINDICATO | K342: SINDICATO DOS TRABALHADORES RURAIS DE PAINS - SINDICATO DOS TRABALHADORES RURAIS DE PAINS | L342: SINDICATO DOS TRABALHADORES RURAIS DE PAINS | M342: 000.000.000.00000-0 | N342: - | O342: - | P342: - | Q342: PRESIDENCIALISMO | R342: 12 | S342: 23 | T342: DIRETA | U342: 1 | V342: 1338 | W342: 23 | X342: RURAL | Y342: TRABALHADORES | Z342: RURAL | AA342: Categoria Profissional dos Trabalhadores Rurais do Plano da CONTAG | AB342: 35582-000 | AC342: MG | AD342: PAINS | AE342: CENTRO | AF342: ESTACAO RODOVIARIA | AG342: S/N | AH342: SALA: 3; | AI342: strdepains@gmail.com | AJ342: 3733231344 | AK342: - | AL342: 08/05/2022 | AM342: 08/05/2026 | AN342: MARIA APARECIDA BEIRIGO RIBEIRO | AO342: MUNICIPAL | AP342: Minas Gerais: Pains
A343: =_xlfn.XLOOKUP(AD343,'Municipios MG'!$B$2:$B$853,'Municipios MG'!$A$2:$A$853) -> 3147105 | B343: =_xlfn.XLOOKUP(AD343,'Municipios MG'!$B$2:$B$853,'Municipios MG'!$B$2:$B$853) -> Pará de Minas | C343: =_xlfn.XLOOKUP(AD343,'Municipios MG'!$B$2:$B$853,'Municipios MG'!$C$2:$C$853) -> -19.864738 | D343: =_xlfn.XLOOKUP(AD343,'Municipios MG'!$B$2:$B$853,'Municipios MG'!$D$2:$D$853) -> -44.60538 | E343: =_xlfn.XLOOKUP(A343,Planilha3!$A$2:$A$5543,Planilha3!$C$2:$C$5543) -> - | F343: =_xlfn.XLOOKUP(A343,Planilha3!$A$2:$A$5543,Planilha3!$E$2:$E$5543) -> - | H343: 18.672.451/0001-30 | I343: ATIVO | J343: SINDICATO | K343: Sindicato dos Trabalhadores e Trabalhadoras Rurais de Pará de Minas, Onça do Pitangui e Igaratinga - MG | L343: SINDICATO DOS TRABALHADORES RURAIS, ASSALARIADOS, E AGRICULTORES FAMILIARES DE PARA DE MINAS, ONCA DE PITANGUI E IGARATINGA | M343: 000.000.000.00000-0 | N343: CENTRAL DO BRASIL DEMOCRATICA DE TRABALHADORES - CBDT NACIONAL | O343: Confederação Nacional dos Trabalhadores Rurais Agricultores e Agricultoras Familiares | P343: FETAEMG - Federação dos Trabalhadores na Agricultura do Estado de Minas Gerais | Q343: PRESIDENCIALISMO | R343: 12 | S343: 144 | T343: DECISAO_ASSEMBLEIA | U343: 1 | V343: 3518 | W343: 152 | X343: RURAL | Y343: TRABALHADORES | Z343: RURAL | AA343: Trabalhadores e Trabalhadoras rurais: assalariados e assalariadas rurais, empregados permanentes, safristas e eventuais, na agricultura, criação de animais, silvicultura, extrativismo rural; e agricultores e agricultoras que_x000D_ exerçam atividades individualmente ou em regime de economia familiar, na qualidade de pequenos produtores, proprietários, posseiros, assentados, meeiros, parceiros, arrendatários, comodatários e extrativistas. | AB343: 35660-020 | AC343: MG | AD343: Pará de Minas | AE343: Centro | AF343: Rua Ricardo Braga | AG343: 37 | AH343: - | AI343: - | AJ343: 3732312007 | AK343: - | AL343: 26/08/2022 | AM343: 25/08/2026 | AN343: VICENTE GERALDO RABELO MOREIRA | AO343: INTERMUNICIPAL | AP343: Minas Gerais: Igaratinga, Onça de Pitangui, Pará de Minas
A344: =_xlfn.XLOOKUP(AD344,'Municipios MG'!$B$2:$B$853,'Municipios MG'!$A$2:$A$853) -> 3148202 | B344: =_xlfn.XLOOKUP(AD344,'Municipios MG'!$B$2:$B$853,'Municipios MG'!$B$2:$B$853) -> Patrocínio do Muriaé | C344: =_xlfn.XLOOKUP(AD344,'Municipios MG'!$B$2:$B$853,'Municipios MG'!$C$2:$C$853) -> -21.151711 | D344: =_xlfn.XLOOKUP(AD344,'Municipios MG'!$B$2:$B$853,'Municipios MG'!$D$2:$D$853) -> -42.212653 | E344: =_xlfn.XLOOKUP(A344,Planilha3!$A$2:$A$5543,Planilha3!$C$2:$C$5543) -> - | F344: =_xlfn.XLOOKUP(A344,Planilha3!$A$2:$A$5543,Planilha3!$E$2:$E$5543) -> - | H344: 18.710.348/0001-38 | I344: ATIVO | J344: SINDICATO | K344: STR Patrícinio do Muriaé/MG - Sindicato dos Trabalhadores Rurais de Patrocinio do Muriaé/MG | L344: SINDICATO DOS TRABALHADORES RURAIS DE PATROCINIO DO MURIAE | M344: 000.000.000.00000-0 | N344: - | O344: - | P344: - | Q344: PRESIDENCIALISMO | R344: 15 | S344: 37 | T344: DECISAO_ASSEMBLEIA | U344: 1 | V344: 37 | W344: 37 | X344: RURAL | Y344: TRABALHADORES | Z344: RURAL | AA344: Trabalhadores e Trabalhadoras rurais: assalariados e assalariadas rurais, empregados permanentes, safristas e eventuais na agricultura, criação de animais e hortifruticultura; e agricultores e agricultoras que exerçam atividades individualmente ou em regime de economia familiar, na qualidade de pequenos produtores, proprietários até dois módulos rurais, posseiros, assentados, meeiros, parceiros, arrendatários, comodatários e os aposentados(as) rurais. | AB344: 36860-000 | AC344: MG | AD344: Patrocínio do Muriaé | AE344: Centro | AF344: Rua Evaristo Castro | AG344: 0 | AH344: Centro | AI344: fetaemgzm@yahoo.com.br | AJ344: 3284914910 | AK344: - | AL344: 11/11/2018 | AM344: 11/11/2022 | AN344: PEDRO DA SILVA SOARES | AO344: MUNICIPAL | AP344: Minas Gerais: Patrocínio do Muriaé
A345: =_xlfn.XLOOKUP(AD345,'Municipios MG'!$B$2:$B$853,'Municipios MG'!$A$2:$A$853) -> 3148400 | B345: =_xlfn.XLOOKUP(AD345,'Municipios MG'!$B$2:$B$853,'Municipios MG'!$B$2:$B$853) -> Paulistas | C345: =_xlfn.XLOOKUP(AD345,'Municipios MG'!$B$2:$B$853,'Municipios MG'!$C$2:$C$853) -> -18.431738 | D345: =_xlfn.XLOOKUP(AD345,'Municipios MG'!$B$2:$B$853,'Municipios MG'!$D$2:$D$853) -> -42.872625 | E345: =_xlfn.XLOOKUP(A345,Planilha3!$A$2:$A$5543,Planilha3!$C$2:$C$5543) -> - | F345: =_xlfn.XLOOKUP(A345,Planilha3!$A$2:$A$5543,Planilha3!$E$2:$E$5543) -> - | H345: 97.475.180/0001-08 | I345: ATIVO | J345: SINDICATO | K345: STR PAULISTAS - SINDICATO DOS TRABALHADORES RURAIS DE PAULISTAS/MG | L345: SINDICATO DOS TRABALHADORES RURAIS DE PAULISTAS | M345: 000.000.000.00000-0 | N345: - | O345: - | P345: - | Q345: PRESIDENCIALISMO | R345: 12 | S345: 158 | T345: DECISAO_ASSEMBLEIA | U345: 1 | V345: 1774 | W345: 163 | X345: RURAL | Y345: TRABALHADORES | Z345: RURAL | AA345: Profissional dos Trabalhadores Rurais, do Plano da CONTAG | AB345: 39765-000 | AC345: MG | AD345: Paulistas | AE345: Centro | AF345: Rua Joao Ulisses Alves | AG345: 509 | AH345: casa | AI345: paulistassindicato@hotmail.com | AJ345: 3334131191 | AK345: - | AL345: 16/11/2022 | AM345: 15/11/2026 | AN345: ALBIS SARDINHA DA PAIXAO | AO345: MUNICIPAL | AP345: Minas Gerais: Paulistas
A346: =_xlfn.XLOOKUP(AD346,'Municipios MG'!$B$2:$B$853,'Municipios MG'!$A$2:$A$853) -> 3148707 | B346: =_xlfn.XLOOKUP(AD346,'Municipios MG'!$B$2:$B$853,'Municipios MG'!$B$2:$B$853) -> Pedra Azul | C346: =_xlfn.XLOOKUP(AD346,'Municipios MG'!$B$2:$B$853,'Municipios MG'!$C$2:$C$853) -> -16.005923 | D346: =_xlfn.XLOOKUP(AD346,'Municipios MG'!$B$2:$B$853,'Municipios MG'!$D$2:$D$853) -> -41.281752 | E346: =_xlfn.XLOOKUP(A346,Planilha3!$A$2:$A$5543,Planilha3!$C$2:$C$5543) -> - | F346: =_xlfn.XLOOKUP(A346,Planilha3!$A$2:$A$5543,Planilha3!$E$2:$E$5543) -> - | H346: 18.511.683/0001-07 | I346: ATIVO | J346: SINDICATO | K346: STR-PEDRA AZUL - Sindicato dos Trabalhadores Rurais de Pedra Azul | L346: SINDICATO DOS TRABALHADORES RURAIS | M346: 000.000.000.00000-0 | N346: CUT - Central Única dos Trabalhadores | O346: - | P346: FETAEMG - Federação dos Trabalhadores na Agricultura do Estado de Minas Gerais | Q346: PRESIDENCIALISMO | R346: 16 | S346: 310 | T346: DIRETA | U346: 1 | V346: 4558 | W346: 317 | X346: RURAL | Y346: TRABALHADORES | Z346: RURAL | AA346: Profissional dos Trabalhadores Rurais, plano da CONTAG | AB346: 39970-000 | AC346: MG | AD346: Pedra Azul | AE346: Centro | AF346: Avenida Sete de Setembro | AG346: 75 | AH346: - | AI346: sindicatopa@yahoo.com.br | AJ346: 3337511968 | AK346: - | AL346: 18/11/2022 | AM346: 17/11/2026 | AN346: VALDOMIRO RODRIGUES | AO346: MUNICIPAL | AP346: Minas Gerais: Pedra Azul
A347: =_xlfn.XLOOKUP(AD347,'Municipios MG'!$B$2:$B$853,'Municipios MG'!$A$2:$A$853) -> 3149705 | B347: =_xlfn.XLOOKUP(AD347,'Municipios MG'!$B$2:$B$853,'Municipios MG'!$B$2:$B$853) -> Perdigão | C347: =_xlfn.XLOOKUP(AD347,'Municipios MG'!$B$2:$B$853,'Municipios MG'!$C$2:$C$853) -> -19.955123 | D347: =_xlfn.XLOOKUP(AD347,'Municipios MG'!$B$2:$B$853,'Municipios MG'!$D$2:$D$853) -> -45.079363 | E347: =_xlfn.XLOOKUP(A347,Planilha3!$A$2:$A$5543,Planilha3!$C$2:$C$5543) -> - | F347: =_xlfn.XLOOKUP(A347,Planilha3!$A$2:$A$5543,Planilha3!$E$2:$E$5543) -> - | H347: 19.151.984/0001-30 | I347: INATIVO | J347: SINDICATO | K347: Sindicato dos Trabalhadores Rurais do Município de Perdigão - MG | L347: SINDICATO DOS TRABALHADORES RURAIS DE PERDIGAO | M347: 000.000.000.00000-0 | N347: CTB - Central dos Trabalhadores e Trabalhadoras do Brasil | O347: Confederação Nacional dos Trabalhadores Rurais Agricultores e Agricultoras Familiares | P347: FETAEMG - Federação dos Trabalhadores na Agricultura do Estado de Minas Gerais | Q347: PRESIDENCIALISMO | R347: 12 | S347: 67 | T347: DIRETA | U347: 1 | V347: 93 | W347: 67 | X347: RURAL | Y347: TRABALHADORES | Z347: RURAL | AA347: Trabalhadores e trabalhadoras rurais: assalariados e assalariadas rurais, empregados permanentes, safristas e eventuais na agricultura, criação de animais, silvicultura, hortifruticultura e extrativismo rural; e agricultores e agricultoras que exerçam regime de economia familiar na qualidade de pequenos produtores, proprietários, posseiros, assentados, meeiros, parceiros, arrendatários, comodatários, extrativistas e aposentados rurais | AB347: 35515-000 | AC347: MG | AD347: Perdigão | AE347: - | AF347: Rua Padre Alfredo Dohr | AG347: 17 | AH347: Centro | AI347: maria.odete@fetaemg.org.br | AJ347: 3732871896 | AK347: - | AL347: 23/07/2012 | AM347: 22/07/2016 | AN347: ANTONIO DOS SANTOS BEIRIGO | AO347: MUNICIPAL | AP347: Minas Gerais: Perdigão
A348: =_xlfn.XLOOKUP(AD348,'Municipios MG'!$B$2:$B$853,'Municipios MG'!$A$2:$A$853) -> 3150307 | B348: =_xlfn.XLOOKUP(AD348,'Municipios MG'!$B$2:$B$853,'Municipios MG'!$B$2:$B$853) -> Piedade do Rio Grande | C348: =_xlfn.XLOOKUP(AD348,'Municipios MG'!$B$2:$B$853,'Municipios MG'!$C$2:$C$853) -> -21.469733 | D348: =_xlfn.XLOOKUP(AD348,'Municipios MG'!$B$2:$B$853,'Municipios MG'!$D$2:$D$853) -> -44.202502 | E348: =_xlfn.XLOOKUP(A348,Planilha3!$A$2:$A$5543,Planilha3!$C$2:$C$5543) -> - | F348: =_xlfn.XLOOKUP(A348,Planilha3!$A$2:$A$5543,Planilha3!$E$2:$E$5543) -> - | H348: 17.954.165/0001-03 | I348: ATIVO | J348: SINDICATO | K348: STR Piedade do Rio Grande/MG - Sindicato dos Trabalhadores Rurais de Piedade do Rio Grande/MG | L348: SINDICATO DOS TRABALHADORES RURAIS DE PIEDADE R GRANDE | M348: 000.000.000.00000-0 | N348: - | O348: Confederação Nacional dos Trabalhadores Rurais Agricultores e Agricultoras Familiares | P348: FETAEMG - Federação dos Trabalhadores na Agricultura do Estado de Minas Gerais | Q348: PRESIDENCIALISMO | R348: 12 | S348: 100 | T348: DIRETA | U348: 1 | V348: 200 | W348: 108 | X348: RURAL | Y348: TRABALHADORES | Z348: RURAL | AA348: Categoria Profissional dos Trabalhadores Rurais do Plano da CONTAG | AB348: 36227-000 | AC348: MG | AD348: Piedade do Rio Grande | AE348: - | AF348: Rua Geraldo Carlos | AG348: 184 | AH348: Centro | AI348: - | AJ348: 3233351480 | AK348: - | AL348: 14/05/2014 | AM348: 13/05/2018 | AN348: GERALDO KENEDY DE AQUINO | AO348: INTERMUNICIPAL | AP348: Minas Gerais: Ibertioga, Piedade do Rio Grande, Santana do Garambéu
A349: =_xlfn.XLOOKUP(AD349,'Municipios MG'!$B$2:$B$853,'Municipios MG'!$A$2:$A$853) -> 3150406 | B349: =_xlfn.XLOOKUP(AD349,'Municipios MG'!$B$2:$B$853,'Municipios MG'!$B$2:$B$853) -> Piedade dos Gerais | C349: =_xlfn.XLOOKUP(AD349,'Municipios MG'!$B$2:$B$853,'Municipios MG'!$C$2:$C$853) -> -20.46101 | D349: =_xlfn.XLOOKUP(AD349,'Municipios MG'!$B$2:$B$853,'Municipios MG'!$D$2:$D$853) -> -44.227916 | E349: =_xlfn.XLOOKUP(A349,Planilha3!$A$2:$A$5543,Planilha3!$C$2:$C$5543) -> - | F349: =_xlfn.XLOOKUP(A349,Planilha3!$A$2:$A$5543,Planilha3!$E$2:$E$5543) -> - | H349: 23.849.896/0001-83 | I349: ATIVO | J349: SINDICATO | K349: SINDICATO DOS TRABALHADORES RURAIS DE PIEDADE GERAIS - SINDICATO DOS TRABALHADORES RURAIS DE PIEDADE GERAIS | L349: SINDICATO DOS TRABALHADORES RURAIS DE PIEDADE GERAIS | M349: 000.000.000.00000-0 | N349: - | O349: - | P349: - | Q349: PRESIDENCIALISMO | R349: 12 | S349: 212 | T349: DIRETA | U349: 1 | V349: 2186 | W349: 218 | X349: RURAL | Y349: TRABALHADORES | Z349: RURAL | AA349: profissional dos trabalhadores e trabalhadoras rurais: Assalariados e assalariadas rurais , empregados permanentes, safristas e eventuais na agricultura, criação de animais, silvicultura, hortifruticultura e extrativismo rural, agricultores e agricultoras que exerçam atividades individualmente ou em regime de economia familiar, na qualidade de pequenos produtores, proprietários, posseiros, assentados, meeiros, parceiros, arrendatários, comodatários, extrativistas e os aposentados (as) rurais | AB349: 35476-000 | AC349: MG | AD349: PIEDADE DOS GERAIS | AE349: CENTRO | AF349: RUA NICANOR FERREIRA GOMES | AG349: 144 | AH349: A | AI349: sindicatopiedadegerais@yahoo.com.br | AJ349: 3135761208 | AK349: - | AL349: 19/04/2022 | AM349: 18/04/2026 | AN349: JACINTO XAVIER DE SANTANA | AO349: MUNICIPAL | AP349: Minas Gerais: Piedade dos Gerais
... A396: =_xlfn.XLOOKUP(AD396,'Municipios MG'!$B$2:$B$853,'Municipios MG'!$A$2:$A$853) -> 3164704 | B396: =_xlfn.XLOOKUP(AD396,'Municipios MG'!$B$2:$B$853,'Municipios MG'!$B$2:$B$853) -> São Sebastião do Paraíso | C396: =_xlfn.XLOOKUP(AD396,'Municipios MG'!$B$2:$B$853,'Municipios MG'!$C$2:$C$853) -> -20.918065 | D396: =_xlfn.XLOOKUP(AD396,'Municipios MG'!$B$2:$B$853,'Municipios MG'!$D$2:$D$853) -> -46.986472 | E396: =_xlfn.XLOOKUP(A396,Planilha3!$A$2:$A$5543,Planilha3!$C$2:$C$5543) -> 12300 | F396: =_xlfn.XLOOKUP(A396,Planilha3!$A$2:$A$5543,Planilha3!$E$2:$E$5543) -> 13284 | H396: 19.104.470/0001-23 | I396: INATIVO | J396: SINDICATO | K396: STR - STR SAO SEBASTIAO DO PARAISO | L396: SINDICATO DOS TRABALHADORES RURAIS DE S S DO PARAISO | M396: 000.000.000.00000-0 | N396: CENTRAL DO BRASIL DEMOCRATICA DE TRABALHADORES - CBDT NACIONAL | O396: Confederação Nacional dos Trabalhadores Rurais Agricultores e Agricultoras Familiares | P396: FETAEMG - Federação dos Trabalhadores na Agricultura do Estado de Minas Gerais | Q396: PRESIDENCIALISMO | R396: 12 | S396: 28 | T396: DIRETA | U396: 1 | V396: 36 | W396: 28 | X396: RURAL | Y396: TRABALHADORES | Z396: RURAL | AA396: Profissional dos Trabalhadores Rurais, do Plano da CONTAG | AB396: 37950-000 | AC396: MG | AD396: São Sebastião do Paraíso | AE396: VILA SANTA MARIA | AF396: RUA ALFERES PATRICIO | AG396: 730 | AH396: - | AI396: - | AJ396: 3535312706 | AK396: - | AL396: 11/03/2012 | AM396: 10/03/2016 | AN396: ZILDA MARIA DE JESUS | AO396: MUNICIPAL | AP396: Minas Gerais: São Sebastião do Paraíso
A397: =_xlfn.XLOOKUP(AD397,'Municipios MG'!$B$2:$B$853,'Municipios MG'!$A$2:$A$853) -> 3114402 | B397: =_xlfn.XLOOKUP(AD397,'Municipios MG'!$B$2:$B$853,'Municipios MG'!$B$2:$B$853) -> Carmo do Rio Claro | C397: =_xlfn.XLOOKUP(AD397,'Municipios MG'!$B$2:$B$853,'Municipios MG'!$C$2:$C$853) -> -20.972997 | D397: =_xlfn.XLOOKUP(AD397,'Municipios MG'!$B$2:$B$853,'Municipios MG'!$D$2:$D$853) -> -46.121965 | E397: =_xlfn.XLOOKUP(A397,Planilha3!$A$2:$A$5543,Planilha3!$C$2:$C$5543) -> 11060 | F397: =_xlfn.XLOOKUP(A397,Planilha3!$A$2:$A$5543,Planilha3!$E$2:$E$5543) -> 15938 | H397: 19.342.930/0001-51 | I397: INATIVO | J397: SINDICATO | K397: STR - SINDICATO DOS TRABALHADORES RURAIS DE CARMO DO RIO CLARO | L397: SINDICATO DOS TRABALHADORES RURAIS DE CARMO DO RIO CLARO | M397: 000.000.000.00000-0 | N397: - | O397: Confederação Nacional dos Trabalhadores Rurais Agricultores e Agricultoras Familiares | P397: FETAEMG - Federação dos Trabalhadores na Agricultura do Estado de Minas Gerais | Q397: JUNTA_GOVERNATIVA | R397: - | S397: - | T397: - | U397: - | V397: 43 | W397: - | X397: RURAL | Y397: TRABALHADORES | Z397: RURAL | AA397: Profissional dos Trabalhadores Rurais, do Plano da CONTAG | AB397: 37150-000 | AC397: MG | AD397: Carmo do Rio Claro | AE397: CASCALHO | AF397: RUA IRMÃS DA PROVIDENCIA | AG397: 44 | AH397: - | AI397: strcarmo@gmail.com | AJ397: 3535612669 | AK397: - | AL397: 16/09/2010 | AM397: 12/02/2011 | AN397: - | AO397: MUNICIPAL | AP397: Minas Gerais: Carmo do Rio Claro
A398: =_xlfn.XLOOKUP(AD398,'Municipios MG'!$B$2:$B$853,'Municipios MG'!$A$2:$A$853) -> 3151503 | B398: =_xlfn.XLOOKUP(AD398,'Municipios MG'!$B$2:$B$853,'Municipios MG'!$B$2:$B$853) -> Piumhi | C398: =_xlfn.XLOOKUP(AD398,'Municipios MG'!$B$2:$B$853,'Municipios MG'!$C$2:$C$853) -> -20.470883 | D398: =_xlfn.XLOOKUP(AD398,'Municipios MG'!$B$2:$B$853,'Municipios MG'!$D$2:$D$853) -> -45.960569 | E398: =_xlfn.XLOOKUP(A398,Planilha3!$A$2:$A$5543,Planilha3!$C$2:$C$5543) -> 9900 | F398: =_xlfn.XLOOKUP(A398,Planilha3!$A$2:$A$5543,Planilha3!$E$2:$E$5543) -> 10692 | H398: 16.786.675/0001-48 | I398: INATIVO | J398: SINDICATO | K398: STR de Piumhi - Sindicato dos Trabalhadores Rurais de Piumhi | L398: SINDICATO DOS TRABALHADORES RURAIS ASSALARIADOS E AGRICULTOR | M398: 000.000.000.00000-0 | N398: CENTRAL DO BRASIL DEMOCRATICA DE TRABALHADORES - CBDT NACIONAL | O398: - | P398: FETAEMG - Federação dos Trabalhadores na Agricultura do Estado de Minas Gerais | Q398: PRESIDENCIALISMO | R398: 12 | S398: 108 | T398: DIRETA | U398: 1 | V398: 154 | W398: 109 | X398: RURAL | Y398: TRABALHADORES | Z398: RURAL | AA398: Profissional dos Trabalhadores Rurais, do Plano da CONTAG | AB398: 37925-000 | AC398: MG | AD398: Piumhi | AE398: Centro | AF398: Rua Padre Abel | AG398: 930 | AH398: - | AI398: strurais@netpiumhi.com.br | AJ398: 3733711223 | AK398: - | AL398: 30/05/2008 | AM398: 30/05/2012 | AN398: WILSON ALVES ARANTES | AO398: INTERMUNICIPAL | AP398: Minas Gerais: Capitólio, Doresópolis, Piumhi, São Roque de Minas, Vargem Bonita
A399: =_xlfn.XLOOKUP(AD399,'Municipios MG'!$B$2:$B$853,'Municipios MG'!$A$2:$A$853) -> 3117108 | B399: =_xlfn.XLOOKUP(AD399,'Municipios MG'!$B$2:$B$853,'Municipios MG'!$B$2:$B$853) -> Conceição da Aparecida | C399: =_xlfn.XLOOKUP(AD399,'Municipios MG'!$B$2:$B$853,'Municipios MG'!$C$2:$C$853) -> -21.09662 | D399: =_xlfn.XLOOKUP(AD399,'Municipios MG'!$B$2:$B$853,'Municipios MG'!$D$2:$D$853) -> -46.203127 | E399: =_xlfn.XLOOKUP(A399,Planilha3!$A$2:$A$5543,Planilha3!$C$2:$C$5543) -> 9000 | F399: =_xlfn.XLOOKUP(A399,Planilha3!$A$2:$A$5543,Planilha3!$E$2:$E$5543) -> 10260 | H399: 18.915.983/0001-51 | I399: INATIVO | J399: SINDICATO | K399: STR Conceição da Aparecida/MG - Sindicato dos Trabalhadores Rurais de Conceição da Aparecida/MG | L399: SINDICATO DOS TRABALHADORES RURAIS | M399: 000.000.000.00000-0 | N399: - | O399: Confederação Nacional dos Trabalhadores Rurais Agricultores e Agricultoras Familiares | P399: FETAEMG - Federação dos Trabalhadores na Agricultura do Estado de Minas Gerais | Q399: PRESIDENCIALISMO | R399: 16 | S399: 87 | T399: DIRETA | U399: 1 | V399: 159 | W399: 88 | X399: RURAL | Y399: TRABALHADORES | Z399: RURAL | AA399: Profissional, dos Trabalhadores Rurais do plano da CONTAG | AB399: 37148-000 | AC399: MG | AD399: Conceição da Aparecida | AE399: - | AF399: Rua Coronel Cassemiro | AG399: 155 | AH399: Centro | AI399: - | AJ399: 3535641450 | AK399: - | AL399: 03/02/2010 | AM399: 02/02/2013 | AN399: REINALDO FERREIRA | AO399: MUNICIPAL | AP399: Sem estados definidos
A400: =_xlfn.XLOOKUP(AD400,'Municipios MG'!$B$2:$B$853,'Municipios MG'!$A$2:$A$853) -> 3147204 | B400: =_xlfn.XLOOKUP(AD400,'Municipios MG'!$B$2:$B$853,'Municipios MG'!$B$2:$B$853) -> Paraguaçu | C400: =_xlfn.XLOOKUP(AD400,'Municipios MG'!$B$2:$B$853,'Municipios MG'!$C$2:$C$853) -> -21.547316 | D400: =_xlfn.XLOOKUP(AD400,'Municipios MG'!$B$2:$B$853,'Municipios MG'!$D$2:$D$853) -> -45.732695 | E400: =_xlfn.XLOOKUP(A400,Planilha3!$A$2:$A$5543,Planilha3!$C$2:$C$5543) -> 8600 | F400: =_xlfn.XLOOKUP(A400,Planilha3!$A$2:$A$5543,Planilha3!$E$2:$E$5543) -> 9822 | H400: 25.659.392/0001-26 | I400: INATIVO | J400: SINDICATO | K400: Sindicato dos Trabalhadores Rurais de Paraguaçu MG | L400: SINDICATO DOS TRABALHADORES RURAIS DE PARAGUACU MG | M400: 000.000.000.00000-0 | N400: CUT - Central Única dos Trabalhadores | O400: - | P400: - | Q400: PRESIDENCIALISMO | R400: 12 | S400: 27 | T400: DIRETA | U400: 1 | V400: 27 | W400: 27 | X400: RURAL | Y400: TRABALHADORES | Z400: RURAL | AA400: Trabalhadores Rurais | AB400: 37120-000 | AC400: MG | AD400: Paraguaçu | AE400: Centro | AF400: Rua Presidente Vargas | AG400: 231 | AH400: Casa | AI400: - | AJ400: 3500000000 | AK400: - | AL400: 27/06/2011 | AM400: 26/06/2014 | AN400: DENIS MARCOLINO | AO400: MUNICIPAL | AP400: Minas Gerais: Paraguaçu
A401: =_xlfn.XLOOKUP(AD401,'Municipios MG'!$B$2:$B$853,'Municipios MG'!$A$2:$A$853) -> 3143203 | B401: =_xlfn.XLOOKUP(AD401,'Municipios MG'!$B$2:$B$853,'Municipios MG'!$B$2:$B$853) -> Monte Santo de Minas | C401: =_xlfn.XLOOKUP(AD401,'Municipios MG'!$B$2:$B$853,'Municipios MG'!$C$2:$C$853) -> -21.190475 | D401: =_xlfn.XLOOKUP(AD401,'Municipios MG'!$B$2:$B$853,'Municipios MG'!$D$2:$D$853) -> -46.977119 | E401: =_xlfn.XLOOKUP(A401,Planilha3!$A$2:$A$5543,Planilha3!$C$2:$C$5543) -> 7750 | F401: =_xlfn.XLOOKUP(A401,Planilha3!$A$2:$A$5543,Planilha3!$E$2:$E$5543) -> 13020 | H401: 19.830.033/0001-97 | I401: INATIVO | J401: SINDICATO | K401: STR - SINDICATO DOS TRABALHADORES RURAIS DE MONTE SANTO DE MINAS- MG | L401: SINDICATO DOS TRABALHADORES RURAIS DE MONTE S DE MINAS | M401: 000.000.000.00000-0 | N401: - | O401: Confederação Nacional dos Trabalhadores Rurais Agricultores e Agricultoras Familiares | P401: FETAEMG - Federação dos Trabalhadores na Agricultura do Estado de Minas Gerais | Q401: PRESIDENCIALISMO | R401: 12 | S401: 24 | T401: DIRETA | U401: 1 | V401: - | W401: 26 | X401: RURAL | Y401: TRABALHADORES | Z401: RURAL | AA401: Profissionais, dos Trabalhadores Rurais do plano da CNTA | AB401: 37958-000 | AC401: MG | AD401: Monte Santo de Minas | AE401: CENTRO | AF401: RUA JUCELINO KUBSTSCHECK | AG401: 111 | AH401: - | AI401: contabilrocha@yahoo.com.br | AJ401: 3535911188 | AK401: - | AL401: 24/01/2011 | AM401: 24/01/2014 | AN401: JOSE DONIZETE MARCAL | AO401: INTERMUNICIPAL | AP401: Minas Gerais: Itamogi, Monte Santo de Minas
A402: =_xlfn.XLOOKUP(AD402,'Municipios MG'!$B$2:$B$853,'Municipios MG'!$A$2:$A$853) -> 3130507 | B402: =_xlfn.XLOOKUP(AD402,'Municipios MG'!$B$2:$B$853,'Municipios MG'!$B$2:$B$853) -> Ilicínea | C402: =_xlfn.XLOOKUP(AD402,'Municipios MG'!$B$2:$B$853,'Municipios MG'!$C$2:$C$853) -> -20.940389 | D402: =_xlfn.XLOOKUP(AD402,'Municipios MG'!$B$2:$B$853,'Municipios MG'!$D$2:$D$853) -> -45.828464 | E402: =_xlfn.XLOOKUP(A402,Planilha3!$A$2:$A$5543,Planilha3!$C$2:$C$5543) -> 6390 | F402: =_xlfn.XLOOKUP(A402,Planilha3!$A$2:$A$5543,Planilha3!$E$2:$E$5543) -> 8818 | H402: 17.417.171/0001-13 | I402: INATIVO | J402: SINDICATO | K402: STR - SINDICATO DOS TRABALHADORES RURAIS DE ILICINEA-MG | L402: SINDICATO DOS TRABALHADORES RURAIS DE ILICINEA | M402: 000.000.000.00000-0 | N402: CUT - Central Única dos Trabalhadores | O402: Confederação Nacional dos Trabalhadores Rurais Agricultores e Agricultoras Familiares | P402: FETAEMG - Federação dos Trabalhadores na Agricultura do Estado de Minas Gerais | Q402: PRESIDENCIALISMO | R402: - | S402: 0 | T402: DECISAO_ASSEMBLEIA | U402: - | V402: 83 | W402: 0 | X402: RURAL | Y402: TRABALHADORES | Z402: RURAL | AA402: Profissional, dos Trabalhadores Rurais do Plano da CONTAG | AB402: 37175-000 | AC402: MG | AD402: Ilicínea | AE402: Centro | AF402: Rua: 12 de Outubro | AG402: 351 | AH402: sede | AI402: nirlei.cristaini13@hotmal.com | AJ402: 3538541325 | AK402: - | AL402: 01/07/2006 | AM402: 30/06/2012 | AN402: ANTONIO GERALDO NETO | AO402: MUNICIPAL | AP402: Minas Gerais: Ilicínea
A403: =_xlfn.XLOOKUP(AD403,'Municipios MG'!$B$2:$B$853,'Municipios MG'!$A$2:$A$853) -> 3115102 | B403: =_xlfn.XLOOKUP(AD403,'Municipios MG'!$B$2:$B$853,'Municipios MG'!$B$2:$B$853) -> Cássia | C403: =_xlfn.XLOOKUP(AD403,'Municipios MG'!$B$2:$B$853,'Municipios MG'!$C$2:$C$853) -> -20.582856 | D403: =_xlfn.XLOOKUP(AD403,'Municipios MG'!$B$2:$B$853,'Municipios MG'!$D$2:$D$853) -> -46.924036 | E403: =_xlfn.XLOOKUP(A403,Planilha3!$A$2:$A$5543,Planilha3!$C$2:$C$5543) -> 5710 | F403: =_xlfn.XLOOKUP(A403,Planilha3!$A$2:$A$5543,Planilha3!$E$2:$E$5543) -> 9026 | H403: 20.946.679/0001-13 | I403: INATIVO | J403: SINDICATO | K403: SINDICATO DOS TRABALHADORES RURAIS DE CASSIA | L403: SINDICATO DOS TRABALHADORES RURAIS DE CASSIA | M403: 000.000.000.00000-0 | N403: CENTRAL DOS SINDICATOS BRASILEIROS - CSB | O403: - | P403: FETAEMG - Federação dos Trabalhadores na Agricultura do Estado de Minas Gerais | Q403: PRESIDENCIALISMO | R403: 14 | S403: 140 | T403: DIRETA | U403: 1 | V403: 169 | W403: 142 | X403: RURAL | Y403: TRABALHADORES | Z403: RURAL | AA403: Profissional dos Trabalhadores Rurais, do Plano da CONTAG | AB403: 37980-000 | AC403: MG | AD403: Cássia | AE403: JARDIM ALVORADA | AF403: RUA CARACAS | AG403: 40 | AH403: - | AI403: - | AJ403: 3535412047 | AK403: - | AL403: 01/04/2012 | AM403: 01/04/2016 | AN403: SEBASTIAO GONCALVES | AO403: MUNICIPAL | AP403: Minas Gerais: Cássia
A404: =_xlfn.XLOOKUP(AD404,'Municipios MG'!$B$2:$B$853,'Municipios MG'!$A$2:$A$853) -> 3102001 | B404: =_xlfn.XLOOKUP(AD404,'Municipios MG'!$B$2:$B$853,'Municipios MG'!$B$2:$B$853) -> Alterosa | C404: =_xlfn.XLOOKUP(AD404,'Municipios MG'!$B$2:$B$853,'Municipios MG'!$C$2:$C$853) -> -21.25587 | D404: =_xlfn.XLOOKUP(AD404,'Municipios MG'!$B$2:$B$853,'Municipios MG'!$D$2:$D$853) -> -46.145321 | E404: =_xlfn.XLOOKUP(A404,Planilha3!$A$2:$A$5543,Planilha3!$C$2:$C$5543) -> 5300 | F404: =_xlfn.XLOOKUP(A404,Planilha3!$A$2:$A$5543,Planilha3!$E$2:$E$5543) -> 5406 | H404: 21.410.303/0001-52 | I404: INATIVO | J404: SINDICATO | K404: SITRA - Sindicato dos Trabalhadores Rurais de Alterosa | L404: SINDICATO DOS TRABALHADORES RURAIS DE ALTEROSA | M404: 000.000.000.00000-0 | N404: - | O404: Confederação Nacional dos Trabalhadores Rurais Agricultores e Agricultoras Familiares | P404: FETAEMG - Federação dos Trabalhadores na Agricultura do Estado de Minas Gerais | Q404: PRESIDENCIALISMO | R404: - | S404: - | T404: - | U404: - | V404: 0 | W404: - | X404: RURAL | Y404: TRABALHADORES | Z404: RURAL | AA404: Profissional dos Trabalhadores Rurais, plano da CONTAG | AB404: 37145-000 | AC404: MG | AD404: Alterosa | AE404: Centro | AF404: Rua Professor Cornelio Nunes | AG404: 45 | AH404: casa | AI404: sitra_alterosa@hotmail.com | AJ404: 3532941247 | AK404: - | AL404: 08/10/2007 | AM404: 07/10/2010 | AN404: ANDERSON DE CASTRO ABREU | AO404: MUNICIPAL | AP404: Minas Gerais: Alterosa
A405: =_xlfn.XLOOKUP(AD405,'Municipios MG'!$B$2:$B$853,'Municipios MG'!$A$2:$A$853) -> 3128709 | B405: =_xlfn.XLOOKUP(AD405,'Municipios MG'!$B$2:$B$853,'Municipios MG'!$B$2:$B$853) -> Guaxupé | C405: =_xlfn.XLOOKUP(AD405,'Municipios MG'!$B$2:$B$853,'Municipios MG'!$C$2:$C$853) -> -21.303781 | D405: =_xlfn.XLOOKUP(AD405,'Municipios MG'!$B$2:$B$853,'Municipios MG'!$D$2:$D$853) -> -46.713537 | E405: =_xlfn.XLOOKUP(A405,Planilha3!$A$2:$A$5543,Planilha3!$C$2:$C$5543) -> 4500 | F405: =_xlfn.XLOOKUP(A405,Planilha3!$A$2:$A$5543,Planilha3!$E$2:$E$5543) -> 7020 | H405: 07.128.798/0001-09 | I405: INATIVO | J405: SINDICATO | K405: Sindicato dos Trabalhadores e Trabalhadoras Rurais de Guaxupé - MG | L405: SINDICATO DOS TRABALHADORES RURAIS ASSALARIADOS E AGRICULTORES FAMILIARES DO MUNICIPIO DE GUAXUPE | M405: 000.000.000.00000-0 | N405: - | O405: - | P405: - | Q405: PRESIDENCIALISMO | R405: - | S405: 0 | T405: DECISAO_ASSEMBLEIA | U405: - | V405: - | W405: 0 | X405: RURAL | Y405: TRABALHADORES | Z405: RURAL | AA405: Trabalhadores e trabalhadoras rurais: assalariados e assalariadas rurais, empregados permanentes, safristas e eventuais na agricultura, criação de animais, silvicultura, hortifruticultura, e extrativismo rural; agricultores e agricultoras que exerçam atividades individualmente ou em regime de economia familiar, na qualidade de pequenos produtores, proprietários, posseiros, assentados, meeiros, parceiros, arrendatários, comodatários e extrativistas. | AB405: 37800-000 | AC405: MG | AD405: Guaxupé | AE405: Centro | AF405: Rua Pereira do Nascimento | AG405: 345 | AH405: Terreo | AI405: strguaxupe@bol.com.br | AJ405: 3536577827 | AK405: - | AL405: 31/12/2004 | AM405: 31/12/2009 | AN405: MARCOS DE ARAUJO | AO405: MUNICIPAL | AP405: Minas Gerais: Guaxupé
A406: =_xlfn.XLOOKUP(AD406,'Municipios MG'!$B$2:$B$853,'Municipios MG'!$A$2:$A$853) -> 3128709 | B406: =_xlfn.XLOOKUP(AD406,'Municipios MG'!$B$2:$B$853,'Municipios MG'!$B$2:$B$853) -> Guaxupé | C406: =_xlfn.XLOOKUP(AD406,'Municipios MG'!$B$2:$B$853,'Municipios MG'!$C$2:$C$853) -> -21.303781 | D406: =_xlfn.XLOOKUP(AD406,'Municipios MG'!$B$2:$B$853,'Municipios MG'!$D$2:$D$853) -> -46.713537 | E406: =_xlfn.XLOOKUP(A406,Planilha3!$A$2:$A$5543,Planilha3!$C$2:$C$5543) -> 4500 | F406: =_xlfn.XLOOKUP(A406,Planilha3!$A$2:$A$5543,Planilha3!$E$2:$E$5543) -> 7020 | H406: 19.307.305/0001-79 | I406: INATIVO | J406: SINDICATO | K406: Sindicato dos Trabalhadores Rurais de Guaxupé | L406: SINDICATO DOS TRABALHADORES RURAIS DE GUAXUPE | M406: 000.000.000.00000-0 | N406: CENTRAL DO BRASIL DEMOCRATICA DE TRABALHADORES - CBDT NACIONAL | O406: Confederação Nacional dos Trabalhadores Rurais Agricultores e Agricultoras Familiares | P406: FETAEMG - Federação dos Trabalhadores na Agricultura do Estado de Minas Gerais | Q406: PRESIDENCIALISMO | R406: 12 | S406: 197 | T406: DIRETA | U406: 1 | V406: 373 | W406: 197 | X406: RURAL | Y406: TRABALHADORES | Z406: RURAL | AA406: Profissional, dos Trabalhadores Rurais do Plano da CONTAG | AB406: 37800-000 | AC406: MG | AD406: Guaxupé | AE406: centro | AF406: Rua:Urbano Leite Ribeiro | AG406: 17 | AH406: - | AI406: strg.guaxupe@bol.com.br | AJ406: 3535512149 | AK406: - | AL406: 01/11/2012 | AM406: 31/10/2015 | AN406: GILVAN CANDIDO DA SILVA | AO406: MUNICIPAL | AP406: Minas Gerais: Guaxupé
A407: =_xlfn.XLOOKUP(AD407,'Municipios MG'!$B$2:$B$853,'Municipios MG'!$A$2:$A$853) -> 3128303 | B407: =_xlfn.XLOOKUP(AD407,'Municipios MG'!$B$2:$B$853,'Municipios MG'!$B$2:$B$853) -> Guaranésia | C407: =_xlfn.XLOOKUP(AD407,'Municipios MG'!$B$2:$B$853,'Municipios MG'!$C$2:$C$853) -> -21.30556 | D407: =_xlfn.XLOOKUP(AD407,'Municipios MG'!$B$2:$B$853,'Municipios MG'!$D$2:$D$853) -> -46.795491 | E407: =_xlfn.XLOOKUP(A407,Planilha3!$A$2:$A$5543,Planilha3!$C$2:$C$5543) -> 4350 | F407: =_xlfn.XLOOKUP(A407,Planilha3!$A$2:$A$5543,Planilha3!$E$2:$E$5543) -> 4177 | H407: 19.307.362/0001-58 | I407: INATIVO | J407: SINDICATO | K407: SINDICATO DOS TRABALHADORES RURAIS DE GUARANESIA | L407: SINDICATO DOS TRABALHADORES RURAIS DE GUARANESIA | M407: 000.000.000.00000-0 | N407: CENTRAL DO BRASIL DEMOCRATICA DE TRABALHADORES - CBDT NACIONAL | O407: - | P407: FETAEMG - Federação dos Trabalhadores na Agricultura do Estado de Minas Gerais | Q407: PRESIDENCIALISMO | R407: 12 | S407: 127 | T407: DIRETA | U407: 1 | V407: 253 | W407: 127 | X407: RURAL | Y407: TRABALHADORES | Z407: RURAL | AA407: Profissional dos Trabalhadores Rurais, do Plano da CONTAG | AB407: 37810-000 | AC407: MG | AD407: Guaranésia | AE407: centro | AF407: RUA CARDEAL CARMELO | AG407: 6 | AH407: - | AI407: strg@guaranesia.com.br | AJ407: 3535551202 | AK407: - | AL407: 01/07/2010 | AM407: 30/06/2013 | AN407: JOAO FRANCISCO GONCALVES | AO407: MUNICIPAL | AP407: Minas Gerais: Guaranésia
A408: =_xlfn.XLOOKUP(AD408,'Municipios MG'!$B$2:$B$853,'Municipios MG'!$A$2:$A$853) -> 3120201 | B408: =_xlfn.XLOOKUP(AD408,'Municipios MG'!$B$2:$B$853,'Municipios MG'!$B$2:$B$853) -> Cristais | C408: =_xlfn.XLOOKUP(AD408,'Municipios MG'!$B$2:$B$853,'Municipios MG'!$C$2:$C$853) -> -20.875233 | D408: =_xlfn.XLOOKUP(AD408,'Municipios MG'!$B$2:$B$853,'Municipios MG'!$D$2:$D$853) -> -45.518504 | E408: =_xlfn.XLOOKUP(A408,Planilha3!$A$2:$A$5543,Planilha3!$C$2:$C$5543) -> 3560 | F408: =_xlfn.XLOOKUP(A408,Planilha3!$A$2:$A$5543,Planilha3!$E$2:$E$5543) -> 3825 | H408: 20.929.063/0001-34 | I408: INATIVO | J408: SINDICATO | K408: STR de Cristais - Sindicato dos Trabalhadores Rurais de Cristais | L408: SINDICATO DOS TRABALHADORES RURAIS DE CRISTAIS | M408: 000.000.000.00000-0 | N408: - | O408: Confederação Nacional dos Trabalhadores Rurais Agricultores e Agricultoras Familiares | P408: FETAEMG - Federação dos Trabalhadores na Agricultura do Estado de Minas Gerais | Q408: PRESIDENCIALISMO | R408: 12 | S408: 139 | T408: DIRETA | U408: 1 | V408: 139 | W408: 139 | X408: RURAL | Y408: TRABALHADORES | Z408: RURAL | AA408: Profissional, do Plano da CONTAG | AB408: 37275-000 | AC408: MG | AD408: Cristais | AE408: Centro | AF408: Rua Leopoldo Moreira Maia | AG408: 13 | AH408: Prédio | AI408: str@stratus.com.br | AJ408: 3538351519 | AK408: - | AL408: 26/03/2006 | AM408: 26/03/2009 | AN408: ANTONIO CARLOS DOS SANTOS | AO408: MUNICIPAL | AP408: Minas Gerais: Cristais
A409: =_xlfn.XLOOKUP(AD409,'Municipios MG'!$B$2:$B$853,'Municipios MG'!$A$2:$A$853) -> 3104106 | B409: =_xlfn.XLOOKUP(AD409,'Municipios MG'!$B$2:$B$853,'Municipios MG'!$B$2:$B$853) -> Arceburgo | C409: =_xlfn.XLOOKUP(AD409,'Municipios MG'!$B$2:$B$853,'Municipios MG'!$C$2:$C$853) -> -21.360181 | D409: =_xlfn.XLOOKUP(AD409,'Municipios MG'!$B$2:$B$853,'Municipios MG'!$D$2:$D$853) -> -46.944354 | E409: =_xlfn.XLOOKUP(A409,Planilha3!$A$2:$A$5543,Planilha3!$C$2:$C$5543) -> 1760 | F409: =_xlfn.XLOOKUP(A409,Planilha3!$A$2:$A$5543,Planilha3!$E$2:$E$5543) -> 2340 | H409: 21.394.705/0001-00 | I409: INATIVO | J409: SINDICATO | K409: SINDICATO DOS TRABALHADORES RURAIS DE ARCEBURGO | L409: SINDICATO DOS TRABALHADORES RURAIS DE ARCEBURGO | M409: 000.000.000.00000-0 | N409: CUT - Central Única dos Trabalhadores | O409: Confederação Nacional dos Trabalhadores Rurais Agricultores e Agricultoras Familiares | P409: FETAEMG - Federação dos Trabalhadores na Agricultura do Estado de Minas Gerais | Q409: PRESIDENCIALISMO | R409: 12 | S409: 64 | T409: DIRETA | U409: 1 | V409: 92 | W409: 64 | X409: RURAL | Y409: TRABALHADORES | Z409: RURAL | AA409: Profissional, dos Trabalhadores Rurais do Plano da CONTAG | AB409: 37820-000 | AC409: MG | AD409: Arceburgo | AE409: CENTRO | AF409: RUA :BALBINO SOARES | AG409: 71 | AH409: - | AI409: strarceburgo@hotmail.com | AJ409: 3535561324 | AK409: - | AL409: 01/01/2013 | AM409: 31/12/2016 | AN409: ADRIANO ALVES DE ALMEIDA | AO409: MUNICIPAL | AP409: Minas Gerais: Arceburgo
A410: =_xlfn.XLOOKUP(AD410,'Municipios MG'!$B$2:$B$853,'Municipios MG'!$A$2:$A$853) -> 3148301 | B410: =_xlfn.XLOOKUP(AD410,'Municipios MG'!$B$2:$B$853,'Municipios MG'!$B$2:$B$853) -> Paula Cândido | C410: =_xlfn.XLOOKUP(AD410,'Municipios MG'!$B$2:$B$853,'Municipios MG'!$C$2:$C$853) -> -20.870162 | D410: =_xlfn.XLOOKUP(AD410,'Municipios MG'!$B$2:$B$853,'Municipios MG'!$D$2:$D$853) -> -42.983155 | E410: =_xlfn.XLOOKUP(A410,Planilha3!$A$2:$A$5543,Planilha3!$C$2:$C$5543) -> 1080 | F410: =_xlfn.XLOOKUP(A410,Planilha3!$A$2:$A$5543,Planilha3!$E$2:$E$5543) -> 1620 | H410: 65.249.849/0001-49 | I410: INATIVO | J410: SINDICATO | K410: STR - Sindicato dos Trabalhadores Rurais | L410: SINDICATO DOS TRABALHADORES RURAIS DE PAULA CANDIDO | M410: 000.000.000.00000-0 | N410: - | O410: Confederação Nacional dos Trabalhadores Rurais Agricultores e Agricultoras Familiares | P410: FETAEMG - Federação dos Trabalhadores na Agricultura do Estado de Minas Gerais | Q410: PRESIDENCIALISMO | R410: 12 | S410: 74 | T410: DIRETA | U410: 1 | V410: 108 | W410: 87 | X410: RURAL | Y410: TRABALHADORES | Z410: RURAL | AA410: Trabalhadores Rurais | AB410: 36544-000 | AC410: MG | AD410: Paula Cândido | AE410: CENTRO | AF410: RUA RAIMUNDO LUDGERO ALVES | AG410: 167 | AH410: - | AI410: sind_rural@ig.com.br | AJ410: 3235371353 | AK410: - | AL410: 14/03/2010 | AM410: 14/03/2013 | AN410: ANTONIO ROMUALDO DE FREITAS | AO410: MUNICIPAL | AP410: Minas Gerais: Paula Cândido
A411: =_xlfn.XLOOKUP(AD411,'Municipios MG'!$B$2:$B$853,'Municipios MG'!$A$2:$A$853) -> 3137403 | B411: =_xlfn.XLOOKUP(AD411,'Municipios MG'!$B$2:$B$853,'Municipios MG'!$B$2:$B$853) -> Lagoa Dourada | C411: =_xlfn.XLOOKUP(AD411,'Municipios MG'!$B$2:$B$853,'Municipios MG'!$C$2:$C$853) -> -20.918599 | D411: =_xlfn.XLOOKUP(AD411,'Municipios MG'!$B$2:$B$853,'Municipios MG'!$D$2:$D$853) -> -44.071116 | E411: =_xlfn.XLOOKUP(A411,Planilha3!$A$2:$A$5543,Planilha3!$C$2:$C$5543) -> 262 | F411: =_xlfn.XLOOKUP(A411,Planilha3!$A$2:$A$5543,Planilha3!$E$2:$E$5543) -> 393 | H411: 01.809.673/0001-50 | I411: INATIVO | J411: SINDICATO | K411: STR Lagoa Dourada/MG - Sindicato dos Trabalhadores Rurais de Lagoa Dourada/MG | L411: SINDICATO DOS TRABALHADORES RURAIS DE LAGOA DOURADA/MG | M411: 000.000.000.00000-0 | N411: CTB - Central dos Trabalhadores e Trabalhadoras do Brasil | O411: Confederação Nacional dos Trabalhadores Rurais Agricultores e Agricultoras Familiares | P411: FETAEMG - Federação dos Trabalhadores na Agricultura do Estado de Minas Gerais | Q411: PRESIDENCIALISMO | R411: 14 | S411: 182 | T411: DIRETA | U411: 1 | V411: 365 | W411: 195 | X411: RURAL | Y411: TRABALHADORES | Z411: RURAL | AA411: Trabalhadores Rurais, integrantes do Plano da Confederação Nacional dos Trabalhadores na Agricultura | AB411: 36345-000 | AC411: MG | AD411: Lagoa Dourada | AE411: - | AF411: Rua Ernesto Queiroz | AG411: 0 | AH411: Parque de Exposições | AI411: - | AJ411: 3233631524 | AK411: - | AL411: 09/08/2011 | AM411: 09/08/2015 | AN411: SEBASTIAO OCTAVIO MARTINS | AO411: MUNICIPAL | AP411: Minas Gerais: Lagoa Dourada
...

Sheet Municipios MG
A1: Codigo_IBGE | B1: Municipio | C1: Latitude | D1: Longitude | E1: Regiao_Cafeeira
A2: 3100203 | B2: Abaeté | C2: -19.155848 | D2: -45.446191 | E2: Fora das principais regiões cafeeiras
A3: 3100302 | B3: Abre Campo | C3: -20.301445 | D3: -42.48099 | E3: Matas de Minas
A4: 3100401 | B4: Acaiaca | C4: -20.360409 | D4: -43.148239 | E4: Campo das Vertentes
A5: 3100500 | B5: Açucena | C5: -19.076713 | D5: -42.546211 | E5: Matas de Minas
A6: 3100609 | B6: Água Boa | C6: -17.991053 | D6: -42.389643 | E6: Chapada de Minas
A7: 3100708 | B7: Água Comprida | C7: -20.059312 | D7: -48.108077 | E7: Cerrado Mineiro
A8: 3100807 | B8: Aguanil | C8: -20.937432 | D8: -45.389465 | E8: Sul de Minas
A9: 3100906 | B9: Águas Formosas | C9: -17.082304 | D9: -40.935228 | E9: Chapada de Minas
A10: 3101003 | B10: Águas Vermelhas | C10: -15.74532 | D10: -41.458788 | E10: Chapada de Minas
A11: 3101102 | B11: Aimorés | C11: -19.49195 | D11: -41.073327 | E11: Matas de Minas
A12: 3101201 | B12: Aiuruoca | C12: -21.975897 | D12: -44.602824 | E12: Sul de Minas
A13: 3101300 | B13: Alagoa | C13: -22.171136 | D13: -44.638099 | E13: Sul de Minas
... A853: 3172202 | B853: Wenceslau Braz | C853: -22.529013 | D853: -45.356774 | E853: Sul de Minas

Sheet Planilha2
A1: Fontes
A2: CNES - Cadastro Nacional de Entidades Sindicais - https://cnes.trabalho.gov.br/app/
A3: Filtros: Grau da Entidade - Todos / Classe - RURAL / Grupo - TRABALHADORES / Área Geoeconômica - RURAL / UF da Sede - MG
A4: Data / hora Emissão: 18/10/2026 15:56
A5: Quantidade de registros recuperados: 420
A7: Tabela 1613 - Área destinada à colheita, área colhida, quantidade produzida, rendimento médio e valor da produção das lavouras permanentes
C8: Ano x Produto das lavouras permanentes x Variável
C9: 2025
C10: Café (em grão) Total

Sheet Planilha3
A1: IBGE | B1: Município | C1: Área colhida | E1: Quantidade produzida
A2: 1100015 | B2: Alta Floresta D'Oeste (RO) | C2: 4246 | D2: Hectares | E2: 14424 | F2: Toneladas
A3: 1100023 | B3: Ariquemes (RO) | C3: 370 | D3: Hectares | E3: 1251 | F3: Toneladas
A4: 1100031 | B4: Cabixi (RO) | C4: 15 | D4: Hectares | E4: 46 | F4: Toneladas
A5: 1100049 | B5: Cacoal (RO) | C5: 4990 | D5: Hectares | E5: 17066 | F5: Toneladas
A6: 1100056 | B6: Cerejeiras (RO) | C6: 18 | D6: Hectares | E6: 60 | F6: Toneladas
A7: 1100064 | B7: Colorado do Oeste (RO) | C7: 20 | D7: Hectares | E7: 55 | F7: Toneladas
A8: 1100072 | B8: Corumbiara (RO) | C8: 4 | D8: Hectares | E8: 11 | F8: Toneladas
A9: 1100080 | B9: Costa Marques (RO) | C9: 140 | D9: Hectares | E9: 487 | F9: Toneladas
A10: 1100098 | B10: Espigão D'Oeste (RO) | C10: 720 | D10: Hectares | E10: 2519 | F10: Toneladas
A11: 1100106 | B11: Guajará-Mirim (RO) | C11: 20 | D11: Hectares | E11: 45 | F11: Toneladas
A12: 1100114 | B12: Jaru (RO) | C12: 205 | D12: Hectares | E12: 831 | F12: Toneladas
A13: 1100122 | B13: Ji-Paraná (RO) | C13: 180 | D13: Hectares | E13: 503 | F13: Toneladas
... A61: 1200302 | B61: Feijó (AC) | C61: 45 | D61: Hectares | E61: 87 | F61: Toneladas
A62: 1200328 | B62: Jordão (AC) | C62: - | D62: Hectares | E62: - | F62: Toneladas
A63: 1200336 | B63: Mâncio Lima (AC) | C63: 485 | D63: Hectares | E63: 1908 | F63: Toneladas
A64: 1200344 | B64: Manoel Urbano (AC) | C64: 60 | D64: Hectares | E64: 102 | F64: Toneladas
A65: 1200351 | B65: Marechal Thaumaturgo (AC) | C65: 5 | D65: Hectares | E65: 13 | F65: Toneladas
A66: 1200385 | B66: Plácido de Castro (AC) | C66: 45 | D66: Hectares | E66: 68 | F66: Toneladas
A67: 1200393 | B67: Porto Walter (AC) | C67: 15 | D67: Hectares | E67: 36 | F67: Toneladas
A68: 1200401 | B68: Rio Branco (AC) | C68: 5 | D68: Hectares | E68: 6 | F68: Toneladas
A69: 1200427 | B69: Rodrigues Alves (AC) | C69: 25 | D69: Hectares | E69: 99 | F69: Toneladas
A70: 1200435 | B70: Santa Rosa do Purus (AC) | C70: - | D70: Hectares | E70: - | F70: Toneladas
A71: 1200450 | B71: Senador Guiomard (AC) | C71: 50 | D71: Hectares | E71: 180 | F71: Toneladas
A72: 1200500 | B72: Sena Madureira (AC) | C72: 31 | D72: Hectares | E72: 115 | F72: Toneladas
A73: 1200609 | B73: Tarauacá (AC) | C73: - | D73: Hectares | E73: - | F73: Toneladas
A74: 1200708 | B74: Xapuri (AC) | C74: 45 | D74: Hectares | E74: 63 | F74: Toneladas
A75: 1200807 | B75: Porto Acre (AC) | C75: 18 | D75: Hectares | E75: 49 | F75: Toneladas
A76: 1300029 | B76: Alvarães (AM) | C76: - | D76: Hectares | E76: - | F76: Toneladas
A77: 1300060 | B77: Amaturá (AM) | C77: - | D77: Hectares | E77: - | F77: Toneladas
A78: 1300086 | B78: Anamã (AM) | C78: - | D78: Hectares | E78: - | F78: Toneladas
A79: 1300102 | B79: Anori (AM) | C79: - | D79: Hectares | E79: - | F79: Toneladas
A80: 1300144 | B80: Apuí (AM) | C80: 790 | D80: Hectares | E80: 1106 | F80: Toneladas
A81: 1300201 | B81: Atalaia do Norte (AM) | C81: - | D81: Hectares | E81: - | F81: Toneladas
A82: 1300300 | B82: Autazes (AM) | C82: 6 | D82: Hectares | E82: 6 | F82: Toneladas
A83: 1300409 | B83: Barcelos (AM) | C83: - | D83: Hectares | E83: - | F83: Toneladas
A84: 1300508 | B84: Barreirinha (AM) | C84: - | D84: Hectares | E84: - | F84: Toneladas
A85: 1300607 | B85: Benjamin Constant (AM) | C85: - | D85: Hectares | E85: - | F85: Toneladas
A86: 1300631 | B86: Beruri (AM) | C86: - | D86: Hectares | E86: - | F86: Toneladas
A87: 1300680 | B87: Boa Vista do Ramos (AM) | C87: 1 | D87: Hectares | E87: 1 | F87: Toneladas
A88: 1300706 | B88: Boca do Acre (AM) | C88: 4 | D88: Hectares | E88: 6 | F88: Toneladas
A89: 1300805 | B89: Borba (AM) | C89: 8 | D89: Hectares | E89: 11 | F89: Toneladas
A90: 1300839 | B90: Caapiranga (AM) | C90: - | D90: Hectares | E90: - | F90: Toneladas
A91: 1300904 | B91: Canutama (AM) | C91: - | D91: Hectares | E91: - | F91: Toneladas
A92: 1301001 | B92: Carauari (AM) | C92: 2 | D92: Hectares | E92: 2 | F92: Toneladas
A93: 1301100 | B93: Careiro (AM) | C93: 20 | D93: Hectares | E93: 36 | F93: Toneladas
A94: 1301159 | B94: Careiro da Várzea (AM) | C94: - | D94: Hectares | E94: - | F94: Toneladas
A95: 1301209 | B95: Coari (AM) | C95: 20 | D95: Hectares | E95: 30 | F95: Toneladas
A96: 1301308 | B96: Codajás (AM) | C96: - | D96: Hectares | E96: - | F96: Toneladas
A97: 1301407 | B97: Eirunepé (AM) | C97: - | D97: Hectares | E97: - | F97: Toneladas
A98: 1301506 | B98: Envira (AM) | C98: 16 | D98: Hectares | E98: 19 | F98: Toneladas
A99: 1301605 | B99: Fonte Boa (AM) | C99: - | D99: Hectares | E99: - | F99: Toneladas
A100: 1301654 | B100: Guajará (AM) | C100: 218 | D100: Hectares | E100: 305 | F100: Toneladas
A101: 1301704 | B101: Humaitá (AM) | C101: 300 | D101: Hectares | E101: 450 | F101: Toneladas
A102: 1301803 | B102: Ipixuna (AM) | C102: - | D102: Hectares | E102: - | F102: Toneladas
A103: 1301852 | B103: Iranduba (AM) | C103: 2 | D103: Hectares | E103: 3 | F103: Toneladas
A104: 1301902 | B104: Itacoatiara (AM) | C104: 12 | D104: Hectares | E104: 12 | F104: Toneladas
A105: 1301951 | B105: Itamarati (AM) | C105: - | D105: Hectares | E105: - | F105: Toneladas
A106: 1302009 | B106: Itapiranga (AM) | C106: 11 | D106: Hectares | E106: 17 | F106: Toneladas
A107: 1302108 | B107: Japurá (AM) | C107: - | D107: Hectares | E107: - | F107: Toneladas
A108: 1302207 | B108: Juruá (AM) | C108: - | D108: Hectares | E108: - | F108: Toneladas
A109: 1302306 | B109: Jutaí (AM) | C109: - | D109: Hectares | E109: - | F109: Toneladas
A110: 1302405 | B110: Lábrea (AM) | C110: 93 | D110: Hectares | E110: 116 | F110: Toneladas
A111: 1302504 | B111: Manacapuru (AM) | C111: - | D111: Hectares | E111: - | F111: Toneladas
A112: 1302553 | B112: Manaquiri (AM) | C112: - | D112: Hectares | E112: - | F112: Toneladas
A113: 1302603 | B113: Manaus (AM) | C113: - | D113: Hectares | E113: - | F113: Toneladas
A114: 1302702 | B114: Manicoré (AM) | C114: 30 | D114: Hectares | E114: 45 | F114: Toneladas
A115: 1302801 | B115: Maraã (AM) | C115: - | D115: Hectares | E115: - | F115: Toneladas
A116: 1302900 | B116: Maués (AM) | C116: - | D116: Hectares | E116: - | F116: Toneladas
A117: 1303007 | B117: Nhamundá (AM) | C117: - | D117: Hectares | E117: - | F117: Toneladas
A118: 1303106 | B118: Nova Olinda do Norte (AM) | C118: 6 | D118: Hectares | E118: 8 | F118: Toneladas
A119: 1303205 | B119: Novo Airão (AM) | C119: - | D119: Hectares | E119: - | F119: Toneladas
A120: 1303304 | B120: Novo Aripuanã (AM) | C120: - | D120: Hectares | E120: - | F120: Toneladas
A121: 1303403 | B121: Parintins (AM) | C121: 2 | D121: Hectares | E121: 2 | F121: Toneladas
A122: 1303502 | B122: Pauini (AM) | C122: - | D122: Hectares | E122: - | F122: Toneladas
A123: 1303536 | B123: Presidente Figueiredo (AM) | C123: 10 | D123: Hectares | E123: 20 | F123: Toneladas
A124: 1303569 | B124: Rio Preto da Eva (AM) | C124: 95 | D124: Hectares | E124: 228 | F124: Toneladas
A125: 1303601 | B125: Santa Isabel do Rio Negro (AM) | C125: - | D125: Hectares | E125: - | F125: Toneladas
A126: 1303700 | B126: Santo Antônio do Içá (AM) | C126: - | D126: Hectares | E126: - | F126: Toneladas
A127: 1303809 | B127: São Gabriel da Cachoeira (AM) | C127: - | D127: Hectares | E127: - | F127: Toneladas
A128: 1303908 | B128: São Paulo de Olivença (AM) | C128: 1 | D128: Hectares | E128: 1 | F128: Toneladas
A129: 1303957 | B129: São Sebastião do Uatumã (AM) | C129: 2 | D129: Hectares | E129: 2 | F129: Toneladas
A130: 1304005 | B130: Silves (AM) | C130: 15 | D130: Hectares | E130: 23 | F130: Toneladas
A131: 1304062 | B131: Tabatinga (AM) | C131: - | D131: Hectares | E131: - | F131: Toneladas
A132: 1304104 | B132: Tapauá (AM) | C132: - | D132: Hectares | E132: - | F132: Toneladas
A133: 1304203 | B133: Tefé (AM) | C133: 1 | D133: Hectares | E133: 2 | F133: Toneladas
A134: 1304237 | B134: Tonantins (AM) | C134: - | D134: Hectares | E134: - | F134: Toneladas
A135: 1304260 | B135: Uarini (AM) | C135: - | D135: Hectares | E135: - | F135: Toneladas
A136: 1304302 | B136: Urucará (AM) | C136: 4 | D136: Hectares | E136: 8 | F136: Toneladas
A137: 1304401 | B137: Urucurituba (AM) | C137: 2 | D137: Hectares | E137: 2 | F137: Toneladas
A138: 1400027 | B138: Amajari (RR) | C138: - | D138: Hectares | E138: - | F138: Toneladas
A139: 1400050 | B139: Alto Alegre (RR) | C139: - | D139: Hectares | E139: - | F139: Toneladas
A140: 1400100 | B140: Boa Vista (RR) | C140: - | D140: Hectares | E140: - | F140: Toneladas
A141: 1400159 | B141: Bonfim (RR) | C141: 2 | D141: Hectares | E141: 2 | F141: Toneladas
A142: 1400175 | B142: Cantá (RR) | C142: - | D142: Hectares | E142: - | F142: Toneladas
A143: 1400209 | B143: Caracaraí (RR) | C143: - | D143: Hectares | E143: - | F143: Toneladas
A144: 1400233 | B144: Caroebe (RR) | C144: - | D144: Hectares | E144: - | F144: Toneladas
A145: 1400282 | B145: Iracema (RR) | C145: - | D145: Hectares | E145: - | F145: Toneladas
A146: 1400308 | B146: Mucajaí (RR) | C146: - | D146: Hectares | E146: - | F146: Toneladas
A147: 1400407 | B147: Normandia (RR) | C147: - | D147: Hectares | E147: - | F147: Toneladas
...
